Workbook

Sheet Orders
A1: don | B1: order_date | C1: customer_id | D1: city | E1: payment_method | F1: order_amount | G1: order_status | H1: Normalized_Order_ID | I1: Capture_Count | J1: Captured_Amount | K1: Amount_Variance | L1: Reconciliation_Status | N1: Reconciliation Status | O1: Order Count | P1: Total_Order_Value | Q1: Total_Captured_Amount | S1: Order Status | T1: No Capture Count | U1: No Capture Order Value
A2: ORD26000001 | B2: 46286 | C2: CUST28289 | D2: Pune | E2: UPI | F2: 299 | G2: Paid | H2: =UPPER(SUBSTITUTE(TRIM(A2),"-","")) -> ORD26000001 | I2: =COUNTIFS(PG_Transactions!$AK:$AK,$H2,PG_Transactions!$E:$E,"CAPTURE",PG_Transactions!$AQ:$AQ,1) -> 1 | J2: =SUMIFS(PG_Transactions!$G:$G,PG_Transactions!$AK:$AK,$H2,PG_Transactions!$E:$E,"CAPTURE",PG_Transactions!$AQ:$AQ,1) -> 299 | K2: =ROUND(J2-F2,2) -> 0 | L2: =IF(I2=0,"No Capture",IF(I2>1,"Multiple Capture Rows - Review",IF(ABS(K2)<0.01,"Amount Match",IF(K2<0,"Captured Less Than Order","Captured More Than Order")))) -> Amount Match | N2: Amount Match | O2: =COUNTIF($L$2:$L$6001,N2) -> 5464 | P2: =SUMIF($L$2:$L$6001,N2,$F$2:$F$6001) -> 19786999 | Q2: =SUMIF($L$2:$L$6001,N2,$J$2:$J$6001) -> 19786999 | S2: Paid | T2: =COUNTIFS($G$2:$G$6001,S2,$L$2:$L$6001,"No Capture") -> 20 | U2: =SUMIFS($F$2:$F$6001,$G$2:$G$6001,S2,$L$2:$L$6001,"No Capture") -> 67617
A3: ORD26000002 | B3: 46287 | C3: CUST38657 | D3: Bengaluru | E3: UPI | F3: 4647 | G3: Paid | H3: =UPPER(SUBSTITUTE(TRIM(A3),"-","")) -> ORD26000002 | I3: =COUNTIFS(PG_Transactions!$AK:$AK,$H3,PG_Transactions!$E:$E,"CAPTURE",PG_Transactions!$AQ:$AQ,1) -> 1 | J3: =SUMIFS(PG_Transactions!$G:$G,PG_Transactions!$AK:$AK,$H3,PG_Transactions!$E:$E,"CAPTURE",PG_Transactions!$AQ:$AQ,1) -> 4647 | K3: =ROUND(J3-F3,2) -> 0 | L3: =IF(I3=0,"No Capture",IF(I3>1,"Multiple Capture Rows - Review",IF(ABS(K3)<0.01,"Amount Match",IF(K3<0,"Captured Less Than Order","Captured More Than Order")))) -> Amount Match | N3: No Capture | O3: =COUNTIF($L$2:$L$6001,N3) -> 515 | P3: =SUMIF($L$2:$L$6001,N3,$F$2:$F$6001) -> 1873142 | Q3: =SUMIF($L$2:$L$6001,N3,$J$2:$J$6001) -> 0 | S3: Failed | T3: =COUNTIFS($G$2:$G$6001,S3,$L$2:$L$6001,"No Capture") -> 300 | U3: =SUMIFS($F$2:$F$6001,$G$2:$G$6001,S3,$L$2:$L$6001,"No Capture") -> 1088506
A4: ORD26000003 | B4: 46282 | C4: CUST81426 | D4: Kolkata | E4: Card | F4: 2098 | G4: Paid | H4: =UPPER(SUBSTITUTE(TRIM(A4),"-","")) -> ORD26000003 | I4: =COUNTIFS(PG_Transactions!$AK:$AK,$H4,PG_Transactions!$E:$E,"CAPTURE",PG_Transactions!$AQ:$AQ,1) -> 1 | J4: =SUMIFS(PG_Transactions!$G:$G,PG_Transactions!$AK:$AK,$H4,PG_Transactions!$E:$E,"CAPTURE",PG_Transactions!$AQ:$AQ,1) -> 2098 | K4: =ROUND(J4-F4,2) -> 0 | L4: =IF(I4=0,"No Capture",IF(I4>1,"Multiple Capture Rows - Review",IF(ABS(K4)<0.01,"Amount Match",IF(K4<0,"Captured Less Than Order","Captured More Than Order")))) -> Amount Match | N4: Multiple Capture Rows - Review | O4: =COUNTIF($L$2:$L$6001,N4) -> 6 | P4: =SUMIF($L$2:$L$6001,N4,$F$2:$F$6001) -> 25539 | Q4: =SUMIF($L$2:$L$6001,N4,$J$2:$J$6001) -> 51078 | S4: Refunded | T4: =COUNTIFS($G$2:$G$6001,S4,$L$2:$L$6001,"No Capture") -> 0 | U4: =SUMIFS($F$2:$F$6001,$G$2:$G$6001,S4,$L$2:$L$6001,"No Capture") -> 0
A5: ORD26000004 | B5: 46273 | C5: CUST30926 | D5: Kolkata | E5: UPI | F5: 3298 | G5: Paid | H5: =UPPER(SUBSTITUTE(TRIM(A5),"-","")) -> ORD26000004 | I5: =COUNTIFS(PG_Transactions!$AK:$AK,$H5,PG_Transactions!$E:$E,"CAPTURE",PG_Transactions!$AQ:$AQ,1) -> 1 | J5: =SUMIFS(PG_Transactions!$G:$G,PG_Transactions!$AK:$AK,$H5,PG_Transactions!$E:$E,"CAPTURE",PG_Transactions!$AQ:$AQ,1) -> 3298 | K5: =ROUND(J5-F5,2) -> 0 | L5: =IF(I5=0,"No Capture",IF(I5>1,"Multiple Capture Rows - Review",IF(ABS(K5)<0.01,"Amount Match",IF(K5<0,"Captured Less Than Order","Captured More Than Order")))) -> Amount Match | N5: Captured Less Than Order | O5: =COUNTIF($L$2:$L$6001,N5) -> 15 | P5: =SUMIF($L$2:$L$6001,N5,$F$2:$F$6001) -> 42825 | Q5: =SUMIF($L$2:$L$6001,N5,$J$2:$J$6001) -> 39680 | S5: Cancelled | T5: =COUNTIFS($G$2:$G$6001,S5,$L$2:$L$6001,"No Capture") -> 195 | U5: =SUMIFS($F$2:$F$6001,$G$2:$G$6001,S5,$L$2:$L$6001,"No Capture") -> 717019
A6: ORD26000005 | B6: 46276 | C6: CUST23396 | D6: Pune | E6: Card | F6: 499 | G6: Paid | H6: =UPPER(SUBSTITUTE(TRIM(A6),"-","")) -> ORD26000005 | I6: =COUNTIFS(PG_Transactions!$AK:$AK,$H6,PG_Transactions!$E:$E,"CAPTURE",PG_Transactions!$AQ:$AQ,1) -> 1 | J6: =SUMIFS(PG_Transactions!$G:$G,PG_Transactions!$AK:$AK,$H6,PG_Transactions!$E:$E,"CAPTURE",PG_Transactions!$AQ:$AQ,1) -> 499 | K6: =ROUND(J6-F6,2) -> 0 | L6: =IF(I6=0,"No Capture",IF(I6>1,"Multiple Capture Rows - Review",IF(ABS(K6)<0.01,"Amount Match",IF(K6<0,"Captured Less Than Order","Captured More Than Order")))) -> Amount Match | N6: Captured More Than Order | O6: =COUNTIF($L$2:$L$6001,N6) -> 0 | P6: =SUMIF($L$2:$L$6001,N6,$F$2:$F$6001) -> 0 | Q6: =SUMIF($L$2:$L$6001,N6,$J$2:$J$6001) -> 0
A7: ORD26000006 | B7: 46278 | C7: CUST15695 | D7: Ahmedabad | E7: Card | F7: 999 | G7: Paid | H7: =UPPER(SUBSTITUTE(TRIM(A7),"-","")) -> ORD26000006 | I7: =COUNTIFS(PG_Transactions!$AK:$AK,$H7,PG_Transactions!$E:$E,"CAPTURE",PG_Transactions!$AQ:$AQ,1) -> 1 | J7: =SUMIFS(PG_Transactions!$G:$G,PG_Transactions!$AK:$AK,$H7,PG_Transactions!$E:$E,"CAPTURE",PG_Transactions!$AQ:$AQ,1) -> 999 | K7: =ROUND(J7-F7,2) -> 0 | L7: =IF(I7=0,"No Capture",IF(I7>1,"Multiple Capture Rows - Review",IF(ABS(K7)<0.01,"Amount Match",IF(K7<0,"Captured Less Than Order","Captured More Than Order")))) -> Amount Match
A8: ORD26000007 | B8: 46283 | C8: CUST92397 | D8: Lucknow | E8: UPI | F8: 1299 | G8: Paid | H8: =UPPER(SUBSTITUTE(TRIM(A8),"-","")) -> ORD26000007 | I8: =COUNTIFS(PG_Transactions!$AK:$AK,$H8,PG_Transactions!$E:$E,"CAPTURE",PG_Transactions!$AQ:$AQ,1) -> 1 | J8: =SUMIFS(PG_Transactions!$G:$G,PG_Transactions!$AK:$AK,$H8,PG_Transactions!$E:$E,"CAPTURE",PG_Transactions!$AQ:$AQ,1) -> 1299 | K8: =ROUND(J8-F8,2) -> 0 | L8: =IF(I8=0,"No Capture",IF(I8>1,"Multiple Capture Rows - Review",IF(ABS(K8)<0.01,"Amount Match",IF(K8<0,"Captured Less Than Order","Captured More Than Order")))) -> Amount Match
A9: ORD26000008 | B9: 46294 | C9: CUST96673 | D9: Bengaluru | E9: UPI | F9: 2499 | G9: Paid | H9: =UPPER(SUBSTITUTE(TRIM(A9),"-","")) -> ORD26000008 | I9: =COUNTIFS(PG_Transactions!$AK:$AK,$H9,PG_Transactions!$E:$E,"CAPTURE",PG_Transactions!$AQ:$AQ,1) -> 1 | J9: =SUMIFS(PG_Transactions!$G:$G,PG_Transactions!$AK:$AK,$H9,PG_Transactions!$E:$E,"CAPTURE",PG_Transactions!$AQ:$AQ,1) -> 2499 | K9: =ROUND(J9-F9,2) -> 0 | L9: =IF(I9=0,"No Capture",IF(I9>1,"Multiple Capture Rows - Review",IF(ABS(K9)<0.01,"Amount Match",IF(K9<0,"Captured Less Than Order","Captured More Than Order")))) -> Amount Match
A10: ORD26000009 | B10: 46290 | C10: CUST59823 | D10: Hyderabad | E10: NetBanking | F10: 349 | G10: Paid | H10: =UPPER(SUBSTITUTE(TRIM(A10),"-","")) -> ORD26000009 | I10: =COUNTIFS(PG_Transactions!$AK:$AK,$H10,PG_Transactions!$E:$E,"CAPTURE",PG_Transactions!$AQ:$AQ,1) -> 1 | J10: =SUMIFS(PG_Transactions!$G:$G,PG_Transactions!$AK:$AK,$H10,PG_Transactions!$E:$E,"CAPTURE",PG_Transactions!$AQ:$AQ,1) -> 349 | K10: =ROUND(J10-F10,2) -> 0 | L10: =IF(I10=0,"No Capture",IF(I10>1,"Multiple Capture Rows - Review",IF(ABS(K10)<0.01,"Amount Match",IF(K10<0,"Captured Less Than Order","Captured More Than Order")))) -> Amount Match
A11: ORD26000010 | B11: 46280 | C11: CUST44993 | D11: Pune | E11: UPI | F11: 9497 | G11: Paid | H11: =UPPER(SUBSTITUTE(TRIM(A11),"-","")) -> ORD26000010 | I11: =COUNTIFS(PG_Transactions!$AK:$AK,$H11,PG_Transactions!$E:$E,"CAPTURE",PG_Transactions!$AQ:$AQ,1) -> 1 | J11: =SUMIFS(PG_Transactions!$G:$G,PG_Transactions!$AK:$AK,$H11,PG_Transactions!$E:$E,"CAPTURE",PG_Transactions!$AQ:$AQ,1) -> 9497 | K11: =ROUND(J11-F11,2) -> 0 | L11: =IF(I11=0,"No Capture",IF(I11>1,"Multiple Capture Rows - Review",IF(ABS(K11)<0.01,"Amount Match",IF(K11<0,"Captured Less Than Order","Captured More Than Order")))) -> Amount Match
A12: ORD26000011 | B12: 46285 | C12: CUST45382 | D12: Jaipur | E12: UPI | F12: 5797 | G12: Paid | H12: =UPPER(SUBSTITUTE(TRIM(A12),"-","")) -> ORD26000011 | I12: =COUNTIFS(PG_Transactions!$AK:$AK,$H12,PG_Transactions!$E:$E,"CAPTURE",PG_Transactions!$AQ:$AQ,1) -> 1 | J12: =SUMIFS(PG_Transactions!$G:$G,PG_Transactions!$AK:$AK,$H12,PG_Transactions!$E:$E,"CAPTURE",PG_Transactions!$AQ:$AQ,1) -> 5797 | K12: =ROUND(J12-F12,2) -> 0 | L12: =IF(I12=0,"No Capture",IF(I12>1,"Multiple Capture Rows - Review",IF(ABS(K12)<0.01,"Amount Match",IF(K12<0,"Captured Less Than Order","Captured More Than Order")))) -> Amount Match
A13: ORD26000012 | B13: 46273 | C13: CUST14207 | D13: Chennai | E13: UPI | F13: 13997 | G13: Paid | H13: =UPPER(SUBSTITUTE(TRIM(A13),"-","")) -> ORD26000012 | I13: =COUNTIFS(PG_Transactions!$AK:$AK,$H13,PG_Transactions!$E:$E,"CAPTURE",PG_Transactions!$AQ:$AQ,1) -> 1 | J13: =SUMIFS(PG_Transactions!$G:$G,PG_Transactions!$AK:$AK,$H13,PG_Transactions!$E:$E,"CAPTURE",PG_Transactions!$AQ:$AQ,1) -> 13997 | K13: =ROUND(J13-F13,2) -> 0 | L13: =IF(I13=0,"No Capture",IF(I13>1,"Multiple Capture Rows - Review",IF(ABS(K13)<0.01,"Amount Match",IF(K13<0,"Captured Less Than Order","Captured More Than Order")))) -> Amount Match
A14: ORD26000013 | B14: 46278 | C14: CUST51245 | D14: Bengaluru | E14: Wallet | F14: 349 | G14: Paid | H14: =UPPER(SUBSTITUTE(TRIM(A14),"-","")) -> ORD26000013 | I14: =COUNTIFS(PG_Transactions!$AK:$AK,$H14,PG_Transactions!$E:$E,"CAPTURE",PG_Transactions!$AQ:$AQ,1) -> 1 | J14: =SUMIFS(PG_Transactions!$G:$G,PG_Transactions!$AK:$AK,$H14,PG_Transactions!$E:$E,"CAPTURE",PG_Transactions!$AQ:$AQ,1) -> 349 | K14: =ROUND(J14-F14,2) -> 0 | L14: =IF(I14=0,"No Capture",IF(I14>1,"Multiple Capture Rows - Review",IF(ABS(K14)<0.01,"Amount Match",IF(K14<0,"Captured Less Than Order","Captured More Than Order")))) -> Amount Match
A15: ORD26000014 | B15: 46286 | C15: CUST42325 | D15: Jaipur | E15: UPI | F15: 4298 | G15: Paid | H15: =UPPER(SUBSTITUTE(TRIM(A15),"-","")) -> ORD26000014 | I15: =COUNTIFS(PG_Transactions!$AK:$AK,$H15,PG_Transactions!$E:$E,"CAPTURE",PG_Transactions!$AQ:$AQ,1) -> 1 | J15: =SUMIFS(PG_Transactions!$G:$G,PG_Transactions!$AK:$AK,$H15,PG_Transactions!$E:$E,"CAPTURE",PG_Transactions!$AQ:$AQ,1) -> 4298 | K15: =ROUND(J15-F15,2) -> 0 | L15: =IF(I15=0,"No Capture",IF(I15>1,"Multiple Capture Rows - Review",IF(ABS(K15)<0.01,"Amount Match",IF(K15<0,"Captured Less Than Order","Captured More Than Order")))) -> Amount Match
A16: ORD26000015 | B16: 46283 | C16: CUST62350 | D16: Chennai | E16: Wallet | F16: 3499 | G16: Paid | H16: =UPPER(SUBSTITUTE(TRIM(A16),"-","")) -> ORD26000015 | I16: =COUNTIFS(PG_Transactions!$AK:$AK,$H16,PG_Transactions!$E:$E,"CAPTURE",PG_Transactions!$AQ:$AQ,1) -> 1 | J16: =SUMIFS(PG_Transactions!$G:$G,PG_Transactions!$AK:$AK,$H16,PG_Transactions!$E:$E,"CAPTURE",PG_Transactions!$AQ:$AQ,1) -> 3499 | K16: =ROUND(J16-F16,2) -> 0 | L16: =IF(I16=0,"No Capture",IF(I16>1,"Multiple Capture Rows - Review",IF(ABS(K16)<0.01,"Amount Match",IF(K16<0,"Captured Less Than Order","Captured More Than Order")))) -> Amount Match
A17: ORD26000016 | B17: 46273 | C17: CUST24371 | D17: Delhi | E17: Card | F17: 1799 | G17: Paid | H17: =UPPER(SUBSTITUTE(TRIM(A17),"-","")) -> ORD26000016 | I17: =COUNTIFS(PG_Transactions!$AK:$AK,$H17,PG_Transactions!$E:$E,"CAPTURE",PG_Transactions!$AQ:$AQ,1) -> 1 | J17: =SUMIFS(PG_Transactions!$G:$G,PG_Transactions!$AK:$AK,$H17,PG_Transactions!$E:$E,"CAPTURE",PG_Transactions!$AQ:$AQ,1) -> 1799 | K17: =ROUND(J17-F17,2) -> 0 | L17: =IF(I17=0,"No Capture",IF(I17>1,"Multiple Capture Rows - Review",IF(ABS(K17)<0.01,"Amount Match",IF(K17<0,"Captured Less Than Order","Captured More Than Order")))) -> Amount Match
A18: ORD26000017 | B18: 46286 | C18: CUST60432 | D18: Kolkata | E18: Card | F18: 4999 | G18: Paid | H18: =UPPER(SUBSTITUTE(TRIM(A18),"-","")) -> ORD26000017 | I18: =COUNTIFS(PG_Transactions!$AK:$AK,$H18,PG_Transactions!$E:$E,"CAPTURE",PG_Transactions!$AQ:$AQ,1) -> 1 | J18: =SUMIFS(PG_Transactions!$G:$G,PG_Transactions!$AK:$AK,$H18,PG_Transactions!$E:$E,"CAPTURE",PG_Transactions!$AQ:$AQ,1) -> 4999 | K18: =ROUND(J18-F18,2) -> 0 | L18: =IF(I18=0,"No Capture",IF(I18>1,"Multiple Capture Rows - Review",IF(ABS(K18)<0.01,"Amount Match",IF(K18<0,"Captured Less Than Order","Captured More Than Order")))) -> Amount Match
... A80: ORD26000079 | B80: 46285 | C80: CUST76162 | D80: Kolkata | E80: Card | F80: 4999 | G80: Failed | H80: =UPPER(SUBSTITUTE(TRIM(A80),"-","")) -> ORD26000079 | I80: =COUNTIFS(PG_Transactions!$AK:$AK,$H80,PG_Transactions!$E:$E,"CAPTURE",PG_Transactions!$AQ:$AQ,1) -> 0 | J80: =SUMIFS(PG_Transactions!$G:$G,PG_Transactions!$AK:$AK,$H80,PG_Transactions!$E:$E,"CAPTURE",PG_Transactions!$AQ:$AQ,1) -> 0 | K80: =ROUND(J80-F80,2) -> -4999 | L80: =IF(I80=0,"No Capture",IF(I80>1,"Multiple Capture Rows - Review",IF(ABS(K80)<0.01,"Amount Match",IF(K80<0,"Captured Less Than Order","Captured More Than Order")))) -> No Capture
A81: ORD26000080 | B81: 46292 | C81: CUST43972 | E81: UPI | F81: 1998 | G81: Paid | H81: =UPPER(SUBSTITUTE(TRIM(A81),"-","")) -> ORD26000080 | I81: =COUNTIFS(PG_Transactions!$AK:$AK,$H81,PG_Transactions!$E:$E,"CAPTURE",PG_Transactions!$AQ:$AQ,1) -> 1 | J81: =SUMIFS(PG_Transactions!$G:$G,PG_Transactions!$AK:$AK,$H81,PG_Transactions!$E:$E,"CAPTURE",PG_Transactions!$AQ:$AQ,1) -> 1998 | K81: =ROUND(J81-F81,2) -> 0 | L81: =IF(I81=0,"No Capture",IF(I81>1,"Multiple Capture Rows - Review",IF(ABS(K81)<0.01,"Amount Match",IF(K81<0,"Captured Less Than Order","Captured More Than Order")))) -> Amount Match
A82: ORD26000081 | B82: 46292 | C82: CUST45992 | D82: Ahmedabad | E82: Card | F82: 10797 | G82: Paid | H82: =UPPER(SUBSTITUTE(TRIM(A82),"-","")) -> ORD26000081 | I82: =COUNTIFS(PG_Transactions!$AK:$AK,$H82,PG_Transactions!$E:$E,"CAPTURE",PG_Transactions!$AQ:$AQ,1) -> 1 | J82: =SUMIFS(PG_Transactions!$G:$G,PG_Transactions!$AK:$AK,$H82,PG_Transactions!$E:$E,"CAPTURE",PG_Transactions!$AQ:$AQ,1) -> 10797 | K82: =ROUND(J82-F82,2) -> 0 | L82: =IF(I82=0,"No Capture",IF(I82>1,"Multiple Capture Rows - Review",IF(ABS(K82)<0.01,"Amount Match",IF(K82<0,"Captured Less Than Order","Captured More Than Order")))) -> Amount Match
A83: ORD26000082 | B83: 46268 | C83: CUST20561 | D83: Delhi | E83: Wallet | F83: 2197 | G83: Paid | H83: =UPPER(SUBSTITUTE(TRIM(A83),"-","")) -> ORD26000082 | I83: =COUNTIFS(PG_Transactions!$AK:$AK,$H83,PG_Transactions!$E:$E,"CAPTURE",PG_Transactions!$AQ:$AQ,1) -> 1 | J83: =SUMIFS(PG_Transactions!$G:$G,PG_Transactions!$AK:$AK,$H83,PG_Transactions!$E:$E,"CAPTURE",PG_Transactions!$AQ:$AQ,1) -> 2197 | K83: =ROUND(J83-F83,2) -> 0 | L83: =IF(I83=0,"No Capture",IF(I83>1,"Multiple Capture Rows - Review",IF(ABS(K83)<0.01,"Amount Match",IF(K83<0,"Captured Less Than Order","Captured More Than Order")))) -> Amount Match
A84: ORD26000083 | B84: 46270 | C84: CUST18418 | D84: Kolkata | E84: Card | F84: 1299 | G84: Paid | H84: =UPPER(SUBSTITUTE(TRIM(A84),"-","")) -> ORD26000083 | I84: =COUNTIFS(PG_Transactions!$AK:$AK,$H84,PG_Transactions!$E:$E,"CAPTURE",PG_Transactions!$AQ:$AQ,1) -> 1 | J84: =SUMIFS(PG_Transactions!$G:$G,PG_Transactions!$AK:$AK,$H84,PG_Transactions!$E:$E,"CAPTURE",PG_Transactions!$AQ:$AQ,1) -> 1299 | K84: =ROUND(J84-F84,2) -> 0 | L84: =IF(I84=0,"No Capture",IF(I84>1,"Multiple Capture Rows - Review",IF(ABS(K84)<0.01,"Amount Match",IF(K84<0,"Captured Less Than Order","Captured More Than Order")))) -> Amount Match
A85: ORD26000084 | B85: 46279 | C85: CUST65069 | D85: Kolkata | E85: UPI | F85: 1799 | G85: Paid | H85: =UPPER(SUBSTITUTE(TRIM(A85),"-","")) -> ORD26000084 | I85: =COUNTIFS(PG_Transactions!$AK:$AK,$H85,PG_Transactions!$E:$E,"CAPTURE",PG_Transactions!$AQ:$AQ,1) -> 1 | J85: =SUMIFS(PG_Transactions!$G:$G,PG_Transactions!$AK:$AK,$H85,PG_Transactions!$E:$E,"CAPTURE",PG_Transactions!$AQ:$AQ,1) -> 1799 | K85: =ROUND(J85-F85,2) -> 0 | L85: =IF(I85=0,"No Capture",IF(I85>1,"Multiple Capture Rows - Review",IF(ABS(K85)<0.01,"Amount Match",IF(K85<0,"Captured Less Than Order","Captured More Than Order")))) -> Amount Match
A86: ORD26000085 | B86: 46294 | C86: CUST59857 | D86: Ahmedabad | E86: Card | F86: 3798 | G86: Paid | H86: =UPPER(SUBSTITUTE(TRIM(A86),"-","")) -> ORD26000085 | I86: =COUNTIFS(PG_Transactions!$AK:$AK,$H86,PG_Transactions!$E:$E,"CAPTURE",PG_Transactions!$AQ:$AQ,1) -> 1 | J86: =SUMIFS(PG_Transactions!$G:$G,PG_Transactions!$AK:$AK,$H86,PG_Transactions!$E:$E,"CAPTURE",PG_Transactions!$AQ:$AQ,1) -> 3798 | K86: =ROUND(J86-F86,2) -> 0 | L86: =IF(I86=0,"No Capture",IF(I86>1,"Multiple Capture Rows - Review",IF(ABS(K86)<0.01,"Amount Match",IF(K86<0,"Captured Less Than Order","Captured More Than Order")))) -> Amount Match
A87: ORD26000086 | B87: 46266 | C87: CUST64921 | D87: Jaipur | E87: NetBanking | F87: 799 | G87: Paid | H87: =UPPER(SUBSTITUTE(TRIM(A87),"-","")) -> ORD26000086 | I87: =COUNTIFS(PG_Transactions!$AK:$AK,$H87,PG_Transactions!$E:$E,"CAPTURE",PG_Transactions!$AQ:$AQ,1) -> 1 | J87: =SUMIFS(PG_Transactions!$G:$G,PG_Transactions!$AK:$AK,$H87,PG_Transactions!$E:$E,"CAPTURE",PG_Transactions!$AQ:$AQ,1) -> 799 | K87: =ROUND(J87-F87,2) -> 0 | L87: =IF(I87=0,"No Capture",IF(I87>1,"Multiple Capture Rows - Review",IF(ABS(K87)<0.01,"Amount Match",IF(K87<0,"Captured Less Than Order","Captured More Than Order")))) -> Amount Match
A88: ORD26000087 | B88: 46289 | C88: CUST45774 | D88: Kolkata | E88: UPI | F88: 9297 | G88: Failed | H88: =UPPER(SUBSTITUTE(TRIM(A88),"-","")) -> ORD26000087 | I88: =COUNTIFS(PG_Transactions!$AK:$AK,$H88,PG_Transactions!$E:$E,"CAPTURE",PG_Transactions!$AQ:$AQ,1) -> 0 | J88: =SUMIFS(PG_Transactions!$G:$G,PG_Transactions!$AK:$AK,$H88,PG_Transactions!$E:$E,"CAPTURE",PG_Transactions!$AQ:$AQ,1) -> 0 | K88: =ROUND(J88-F88,2) -> -9297 | L88: =IF(I88=0,"No Capture",IF(I88>1,"Multiple Capture Rows - Review",IF(ABS(K88)<0.01,"Amount Match",IF(K88<0,"Captured Less Than Order","Captured More Than Order")))) -> No Capture
A89: ORD26000088 | B89: 46281 | C89: CUST62994 | D89: Delhi | E89: Card | F89: 1299 | G89: Paid | H89: =UPPER(SUBSTITUTE(TRIM(A89),"-","")) -> ORD26000088 | I89: =COUNTIFS(PG_Transactions!$AK:$AK,$H89,PG_Transactions!$E:$E,"CAPTURE",PG_Transactions!$AQ:$AQ,1) -> 1 | J89: =SUMIFS(PG_Transactions!$G:$G,PG_Transactions!$AK:$AK,$H89,PG_Transactions!$E:$E,"CAPTURE",PG_Transactions!$AQ:$AQ,1) -> 1299 | K89: =ROUND(J89-F89,2) -> 0 | L89: =IF(I89=0,"No Capture",IF(I89>1,"Multiple Capture Rows - Review",IF(ABS(K89)<0.01,"Amount Match",IF(K89<0,"Captured Less Than Order","Captured More Than Order")))) -> Amount Match
A90: ORD26000089 | B90: 46292 | C90: CUST87580 | D90: Lucknow | E90: Wallet | F90: 2998 | G90: Paid | H90: =UPPER(SUBSTITUTE(TRIM(A90),"-","")) -> ORD26000089 | I90: =COUNTIFS(PG_Transactions!$AK:$AK,$H90,PG_Transactions!$E:$E,"CAPTURE",PG_Transactions!$AQ:$AQ,1) -> 1 | J90: =SUMIFS(PG_Transactions!$G:$G,PG_Transactions!$AK:$AK,$H90,PG_Transactions!$E:$E,"CAPTURE",PG_Transactions!$AQ:$AQ,1) -> 2998 | K90: =ROUND(J90-F90,2) -> 0 | L90: =IF(I90=0,"No Capture",IF(I90>1,"Multiple Capture Rows - Review",IF(ABS(K90)<0.01,"Amount Match",IF(K90<0,"Captured Less Than Order","Captured More Than Order")))) -> Amount Match
A91: ORD26000090 | B91: 46287 | C91: CUST70515 | D91: Delhi | E91: UPI | F91: 349 | G91: Paid | H91: =UPPER(SUBSTITUTE(TRIM(A91),"-","")) -> ORD26000090 | I91: =COUNTIFS(PG_Transactions!$AK:$AK,$H91,PG_Transactions!$E:$E,"CAPTURE",PG_Transactions!$AQ:$AQ,1) -> 1 | J91: =SUMIFS(PG_Transactions!$G:$G,PG_Transactions!$AK:$AK,$H91,PG_Transactions!$E:$E,"CAPTURE",PG_Transactions!$AQ:$AQ,1) -> 349 | K91: =ROUND(J91-F91,2) -> 0 | L91: =IF(I91=0,"No Capture",IF(I91>1,"Multiple Capture Rows - Review",IF(ABS(K91)<0.01,"Amount Match",IF(K91<0,"Captured Less Than Order","Captured More Than Order")))) -> Amount Match
A92: ORD26000091 | B92: 46267 | C92: CUST54236 | D92: Kolkata | E92: UPI | F92: 1299 | G92: Paid | H92: =UPPER(SUBSTITUTE(TRIM(A92),"-","")) -> ORD26000091 | I92: =COUNTIFS(PG_Transactions!$AK:$AK,$H92,PG_Transactions!$E:$E,"CAPTURE",PG_Transactions!$AQ:$AQ,1) -> 1 | J92: =SUMIFS(PG_Transactions!$G:$G,PG_Transactions!$AK:$AK,$H92,PG_Transactions!$E:$E,"CAPTURE",PG_Transactions!$AQ:$AQ,1) -> 1299 | K92: =ROUND(J92-F92,2) -> 0 | L92: =IF(I92=0,"No Capture",IF(I92>1,"Multiple Capture Rows - Review",IF(ABS(K92)<0.01,"Amount Match",IF(K92<0,"Captured Less Than Order","Captured More Than Order")))) -> Amount Match
A93: ORD26000092 | B93: 46274 | C93: CUST80702 | D93: Mumbai | E93: UPI | F93: 8798 | G93: Paid | H93: =UPPER(SUBSTITUTE(TRIM(A93),"-","")) -> ORD26000092 | I93: =COUNTIFS(PG_Transactions!$AK:$AK,$H93,PG_Transactions!$E:$E,"CAPTURE",PG_Transactions!$AQ:$AQ,1) -> 1 | J93: =SUMIFS(PG_Transactions!$G:$G,PG_Transactions!$AK:$AK,$H93,PG_Transactions!$E:$E,"CAPTURE",PG_Transactions!$AQ:$AQ,1) -> 8798 | K93: =ROUND(J93-F93,2) -> 0 | L93: =IF(I93=0,"No Capture",IF(I93>1,"Multiple Capture Rows - Review",IF(ABS(K93)<0.01,"Amount Match",IF(K93<0,"Captured Less Than Order","Captured More Than Order")))) -> Amount Match
... A126: ORD26000125 | B126: 46269 | C126: CUST28643 | D126: Pune | E126: UPI | F126: 3598 | G126: Paid | H126: =UPPER(SUBSTITUTE(TRIM(A126),"-","")) -> ORD26000125 | I126: =COUNTIFS(PG_Transactions!$AK:$AK,$H126,PG_Transactions!$E:$E,"CAPTURE",PG_Transactions!$AQ:$AQ,1) -> 1 | J126: =SUMIFS(PG_Transactions!$G:$G,PG_Transactions!$AK:$AK,$H126,PG_Transactions!$E:$E,"CAPTURE",PG_Transactions!$AQ:$AQ,1) -> 3598 | K126: =ROUND(J126-F126,2) -> 0 | L126: =IF(I126=0,"No Capture",IF(I126>1,"Multiple Capture Rows - Review",IF(ABS(K126)<0.01,"Amount Match",IF(K126<0,"Captured Less Than Order","Captured More Than Order")))) -> Amount Match
A127: ORD26000126 | B127: 46267 | C127: CUST84607 | E127: Card | F127: 4999 | G127: Paid | H127: =UPPER(SUBSTITUTE(TRIM(A127),"-","")) -> ORD26000126 | I127: =COUNTIFS(PG_Transactions!$AK:$AK,$H127,PG_Transactions!$E:$E,"CAPTURE",PG_Transactions!$AQ:$AQ,1) -> 1 | J127: =SUMIFS(PG_Transactions!$G:$G,PG_Transactions!$AK:$AK,$H127,PG_Transactions!$E:$E,"CAPTURE",PG_Transactions!$AQ:$AQ,1) -> 4999 | K127: =ROUND(J127-F127,2) -> 0 | L127: =IF(I127=0,"No Capture",IF(I127>1,"Multiple Capture Rows - Review",IF(ABS(K127)<0.01,"Amount Match",IF(K127<0,"Captured Less Than Order","Captured More Than Order")))) -> Amount Match
A128: ORD26000127 | B128: 46280 | C128: CUST45683 | D128: Jaipur | E128: Card | F128: 1499 | G128: Paid | H128: =UPPER(SUBSTITUTE(TRIM(A128),"-","")) -> ORD26000127 | I128: =COUNTIFS(PG_Transactions!$AK:$AK,$H128,PG_Transactions!$E:$E,"CAPTURE",PG_Transactions!$AQ:$AQ,1) -> 1 | J128: =SUMIFS(PG_Transactions!$G:$G,PG_Transactions!$AK:$AK,$H128,PG_Transactions!$E:$E,"CAPTURE",PG_Transactions!$AQ:$AQ,1) -> 1499 | K128: =ROUND(J128-F128,2) -> 0 | L128: =IF(I128=0,"No Capture",IF(I128>1,"Multiple Capture Rows - Review",IF(ABS(K128)<0.01,"Amount Match",IF(K128<0,"Captured Less Than Order","Captured More Than Order")))) -> Amount Match
A129: ORD26000128 | B129: 46283 | C129: CUST52247 | D129: Lucknow | E129: Wallet | F129: 1848 | G129: Paid | H129: =UPPER(SUBSTITUTE(TRIM(A129),"-","")) -> ORD26000128 | I129: =COUNTIFS(PG_Transactions!$AK:$AK,$H129,PG_Transactions!$E:$E,"CAPTURE",PG_Transactions!$AQ:$AQ,1) -> 1 | J129: =SUMIFS(PG_Transactions!$G:$G,PG_Transactions!$AK:$AK,$H129,PG_Transactions!$E:$E,"CAPTURE",PG_Transactions!$AQ:$AQ,1) -> 1848 | K129: =ROUND(J129-F129,2) -> 0 | L129: =IF(I129=0,"No Capture",IF(I129>1,"Multiple Capture Rows - Review",IF(ABS(K129)<0.01,"Amount Match",IF(K129<0,"Captured Less Than Order","Captured More Than Order")))) -> Amount Match
A130: ORD26000129 | B130: 46274 | C130: CUST85392 | D130: Lucknow | E130: Card | F130: 349 | G130: Paid | H130: =UPPER(SUBSTITUTE(TRIM(A130),"-","")) -> ORD26000129 | I130: =COUNTIFS(PG_Transactions!$AK:$AK,$H130,PG_Transactions!$E:$E,"CAPTURE",PG_Transactions!$AQ:$AQ,1) -> 1 | J130: =SUMIFS(PG_Transactions!$G:$G,PG_Transactions!$AK:$AK,$H130,PG_Transactions!$E:$E,"CAPTURE",PG_Transactions!$AQ:$AQ,1) -> 349 | K130: =ROUND(J130-F130,2) -> 0 | L130: =IF(I130=0,"No Capture",IF(I130>1,"Multiple Capture Rows - Review",IF(ABS(K130)<0.01,"Amount Match",IF(K130<0,"Captured Less Than Order","Captured More Than Order")))) -> Amount Match
A131: ORD26000130 | B131: 46266 | C131: CUST71669 | D131: Jaipur | E131: Card | F131: 11297 | G131: Paid | H131: =UPPER(SUBSTITUTE(TRIM(A131),"-","")) -> ORD26000130 | I131: =COUNTIFS(PG_Transactions!$AK:$AK,$H131,PG_Transactions!$E:$E,"CAPTURE",PG_Transactions!$AQ:$AQ,1) -> 1 | J131: =SUMIFS(PG_Transactions!$G:$G,PG_Transactions!$AK:$AK,$H131,PG_Transactions!$E:$E,"CAPTURE",PG_Transactions!$AQ:$AQ,1) -> 11297 | K131: =ROUND(J131-F131,2) -> 0 | L131: =IF(I131=0,"No Capture",IF(I131>1,"Multiple Capture Rows - Review",IF(ABS(K131)<0.01,"Amount Match",IF(K131<0,"Captured Less Than Order","Captured More Than Order")))) -> Amount Match
A132: ORD26000131 | B132: 46286 | C132: CUST74451 | D132: Pune | E132: UPI | F132: 1298 | G132: Refunded | H132: =UPPER(SUBSTITUTE(TRIM(A132),"-","")) -> ORD26000131 | I132: =COUNTIFS(PG_Transactions!$AK:$AK,$H132,PG_Transactions!$E:$E,"CAPTURE",PG_Transactions!$AQ:$AQ,1) -> 1 | J132: =SUMIFS(PG_Transactions!$G:$G,PG_Transactions!$AK:$AK,$H132,PG_Transactions!$E:$E,"CAPTURE",PG_Transactions!$AQ:$AQ,1) -> 1298 | K132: =ROUND(J132-F132,2) -> 0 | L132: =IF(I132=0,"No Capture",IF(I132>1,"Multiple Capture Rows - Review",IF(ABS(K132)<0.01,"Amount Match",IF(K132<0,"Captured Less Than Order","Captured More Than Order")))) -> Amount Match
A133: ORD26000132 | B133: 46281 | C133: CUST31079 | D133: Chennai | E133: Card | F133: 1299 | G133: Paid | H133: =UPPER(SUBSTITUTE(TRIM(A133),"-","")) -> ORD26000132 | I133: =COUNTIFS(PG_Transactions!$AK:$AK,$H133,PG_Transactions!$E:$E,"CAPTURE",PG_Transactions!$AQ:$AQ,1) -> 1 | J133: =SUMIFS(PG_Transactions!$G:$G,PG_Transactions!$AK:$AK,$H133,PG_Transactions!$E:$E,"CAPTURE",PG_Transactions!$AQ:$AQ,1) -> 1299 | K133: =ROUND(J133-F133,2) -> 0 | L133: =IF(I133=0,"No Capture",IF(I133>1,"Multiple Capture Rows - Review",IF(ABS(K133)<0.01,"Amount Match",IF(K133<0,"Captured Less Than Order","Captured More Than Order")))) -> Amount Match
A134: ORD26000133 | B134: 46279 | C134: CUST82102 | D134: Mumbai | E134: NetBanking | F134: 5297 | G134: Cancelled | H134: =UPPER(SUBSTITUTE(TRIM(A134),"-","")) -> ORD26000133 | I134: =COUNTIFS(PG_Transactions!$AK:$AK,$H134,PG_Transactions!$E:$E,"CAPTURE",PG_Transactions!$AQ:$AQ,1) -> 0 | J134: =SUMIFS(PG_Transactions!$G:$G,PG_Transactions!$AK:$AK,$H134,PG_Transactions!$E:$E,"CAPTURE",PG_Transactions!$AQ:$AQ,1) -> 0 | K134: =ROUND(J134-F134,2) -> -5297 | L134: =IF(I134=0,"No Capture",IF(I134>1,"Multiple Capture Rows - Review",IF(ABS(K134)<0.01,"Amount Match",IF(K134<0,"Captured Less Than Order","Captured More Than Order")))) -> No Capture
A135: ORD26000134 | B135: 46280 | C135: CUST62976 | D135: Jaipur | E135: UPI | F135: 999 | G135: Paid | H135: =UPPER(SUBSTITUTE(TRIM(A135),"-","")) -> ORD26000134 | I135: =COUNTIFS(PG_Transactions!$AK:$AK,$H135,PG_Transactions!$E:$E,"CAPTURE",PG_Transactions!$AQ:$AQ,1) -> 1 | J135: =SUMIFS(PG_Transactions!$G:$G,PG_Transactions!$AK:$AK,$H135,PG_Transactions!$E:$E,"CAPTURE",PG_Transactions!$AQ:$AQ,1) -> 999 | K135: =ROUND(J135-F135,2) -> 0 | L135: =IF(I135=0,"No Capture",IF(I135>1,"Multiple Capture Rows - Review",IF(ABS(K135)<0.01,"Amount Match",IF(K135<0,"Captured Less Than Order","Captured More Than Order")))) -> Amount Match
A136: ORD26000135 | B136: 46292 | C136: CUST17104 | D136: Bengaluru | E136: UPI | F136: 2999 | G136: Paid | H136: =UPPER(SUBSTITUTE(TRIM(A136),"-","")) -> ORD26000135 | I136: =COUNTIFS(PG_Transactions!$AK:$AK,$H136,PG_Transactions!$E:$E,"CAPTURE",PG_Transactions!$AQ:$AQ,1) -> 1 | J136: =SUMIFS(PG_Transactions!$G:$G,PG_Transactions!$AK:$AK,$H136,PG_Transactions!$E:$E,"CAPTURE",PG_Transactions!$AQ:$AQ,1) -> 2999 | K136: =ROUND(J136-F136,2) -> 0 | L136: =IF(I136=0,"No Capture",IF(I136>1,"Multiple Capture Rows - Review",IF(ABS(K136)<0.01,"Amount Match",IF(K136<0,"Captured Less Than Order","Captured More Than Order")))) -> Amount Match
A137: ORD26000136 | B137: 46282 | C137: CUST16764 | D137: Bengaluru | E137: Card | F137: 2499 | G137: Paid | H137: =UPPER(SUBSTITUTE(TRIM(A137),"-","")) -> ORD26000136 | I137: =COUNTIFS(PG_Transactions!$AK:$AK,$H137,PG_Transactions!$E:$E,"CAPTURE",PG_Transactions!$AQ:$AQ,1) -> 1 | J137: =SUMIFS(PG_Transactions!$G:$G,PG_Transactions!$AK:$AK,$H137,PG_Transactions!$E:$E,"CAPTURE",PG_Transactions!$AQ:$AQ,1) -> 2499 | K137: =ROUND(J137-F137,2) -> 0 | L137: =IF(I137=0,"No Capture",IF(I137>1,"Multiple Capture Rows - Review",IF(ABS(K137)<0.01,"Amount Match",IF(K137<0,"Captured Less Than Order","Captured More Than Order")))) -> Amount Match
A138: ORD26000137 | B138: 46274 | C138: CUST25915 | E138: Card | F138: 1298 | G138: Paid | H138: =UPPER(SUBSTITUTE(TRIM(A138),"-","")) -> ORD26000137 | I138: =COUNTIFS(PG_Transactions!$AK:$AK,$H138,PG_Transactions!$E:$E,"CAPTURE",PG_Transactions!$AQ:$AQ,1) -> 1 | J138: =SUMIFS(PG_Transactions!$G:$G,PG_Transactions!$AK:$AK,$H138,PG_Transactions!$E:$E,"CAPTURE",PG_Transactions!$AQ:$AQ,1) -> 1298 | K138: =ROUND(J138-F138,2) -> 0 | L138: =IF(I138=0,"No Capture",IF(I138>1,"Multiple Capture Rows - Review",IF(ABS(K138)<0.01,"Amount Match",IF(K138<0,"Captured Less Than Order","Captured More Than Order")))) -> Amount Match
A139: ORD26000138 | B139: 46286 | C139: CUST11792 | D139: Jaipur | E139: UPI | F139: 5598 | G139: Paid | H139: =UPPER(SUBSTITUTE(TRIM(A139),"-","")) -> ORD26000138 | I139: =COUNTIFS(PG_Transactions!$AK:$AK,$H139,PG_Transactions!$E:$E,"CAPTURE",PG_Transactions!$AQ:$AQ,1) -> 1 | J139: =SUMIFS(PG_Transactions!$G:$G,PG_Transactions!$AK:$AK,$H139,PG_Transactions!$E:$E,"CAPTURE",PG_Transactions!$AQ:$AQ,1) -> 5598 | K139: =ROUND(J139-F139,2) -> 0 | L139: =IF(I139=0,"No Capture",IF(I139>1,"Multiple Capture Rows - Review",IF(ABS(K139)<0.01,"Amount Match",IF(K139<0,"Captured Less Than Order","Captured More Than Order")))) -> Amount Match
A140: ORD26000139 | B140: 46279 | C140: CUST70482 | D140: Pune | E140: Wallet | F140: 599 | G140: Refunded | H140: =UPPER(SUBSTITUTE(TRIM(A140),"-","")) -> ORD26000139 | I140: =COUNTIFS(PG_Transactions!$AK:$AK,$H140,PG_Transactions!$E:$E,"CAPTURE",PG_Transactions!$AQ:$AQ,1) -> 1 | J140: =SUMIFS(PG_Transactions!$G:$G,PG_Transactions!$AK:$AK,$H140,PG_Transactions!$E:$E,"CAPTURE",PG_Transactions!$AQ:$AQ,1) -> 599 | K140: =ROUND(J140-F140,2) -> 0 | L140: =IF(I140=0,"No Capture",IF(I140>1,"Multiple Capture Rows - Review",IF(ABS(K140)<0.01,"Amount Match",IF(K140<0,"Captured Less Than Order","Captured More Than Order")))) -> Amount Match
A141: ORD26000140 | B141: 46286 | C141: CUST45838 | D141: Kolkata | E141: UPI | F141: 1499 | G141: Cancelled | H141: =UPPER(SUBSTITUTE(TRIM(A141),"-","")) -> ORD26000140 | I141: =COUNTIFS(PG_Transactions!$AK:$AK,$H141,PG_Transactions!$E:$E,"CAPTURE",PG_Transactions!$AQ:$AQ,1) -> 0 | J141: =SUMIFS(PG_Transactions!$G:$G,PG_Transactions!$AK:$AK,$H141,PG_Transactions!$E:$E,"CAPTURE",PG_Transactions!$AQ:$AQ,1) -> 0 | K141: =ROUND(J141-F141,2) -> -1499 | L141: =IF(I141=0,"No Capture",IF(I141>1,"Multiple Capture Rows - Review",IF(ABS(K141)<0.01,"Amount Match",IF(K141<0,"Captured Less Than Order","Captured More Than Order")))) -> No Capture
A142: ORD26000141 | B142: 46292 | C142: CUST34983 | D142: Lucknow | E142: UPI | F142: 2098 | G142: Paid | H142: =UPPER(SUBSTITUTE(TRIM(A142),"-","")) -> ORD26000141 | I142: =COUNTIFS(PG_Transactions!$AK:$AK,$H142,PG_Transactions!$E:$E,"CAPTURE",PG_Transactions!$AQ:$AQ,1) -> 1 | J142: =SUMIFS(PG_Transactions!$G:$G,PG_Transactions!$AK:$AK,$H142,PG_Transactions!$E:$E,"CAPTURE",PG_Transactions!$AQ:$AQ,1) -> 2098 | K142: =ROUND(J142-F142,2) -> 0 | L142: =IF(I142=0,"No Capture",IF(I142>1,"Multiple Capture Rows - Review",IF(ABS(K142)<0.01,"Amount Match",IF(K142<0,"Captured Less Than Order","Captured More Than Order")))) -> Amount Match
A143: ORD26000142 | B143: 46282 | C143: CUST64387 | D143: Chennai | E143: Card | F143: 8847 | G143: Paid | H143: =UPPER(SUBSTITUTE(TRIM(A143),"-","")) -> ORD26000142 | I143: =COUNTIFS(PG_Transactions!$AK:$AK,$H143,PG_Transactions!$E:$E,"CAPTURE",PG_Transactions!$AQ:$AQ,1) -> 1 | J143: =SUMIFS(PG_Transactions!$G:$G,PG_Transactions!$AK:$AK,$H143,PG_Transactions!$E:$E,"CAPTURE",PG_Transactions!$AQ:$AQ,1) -> 8847 | K143: =ROUND(J143-F143,2) -> 0 | L143: =IF(I143=0,"No Capture",IF(I143>1,"Multiple Capture Rows - Review",IF(ABS(K143)<0.01,"Amount Match",IF(K143<0,"Captured Less Than Order","Captured More Than Order")))) -> Amount Match
A144: ORD26000143 | B144: 46295 | C144: CUST86931 | D144: Lucknow | E144: Card | F144: 8798 | G144: Paid | H144: =UPPER(SUBSTITUTE(TRIM(A144),"-","")) -> ORD26000143 | I144: =COUNTIFS(PG_Transactions!$AK:$AK,$H144,PG_Transactions!$E:$E,"CAPTURE",PG_Transactions!$AQ:$AQ,1) -> 1 | J144: =SUMIFS(PG_Transactions!$G:$G,PG_Transactions!$AK:$AK,$H144,PG_Transactions!$E:$E,"CAPTURE",PG_Transactions!$AQ:$AQ,1) -> 8798 | K144: =ROUND(J144-F144,2) -> 0 | L144: =IF(I144=0,"No Capture",IF(I144>1,"Multiple Capture Rows - Review",IF(ABS(K144)<0.01,"Amount Match",IF(K144<0,"Captured Less Than Order","Captured More Than Order")))) -> Amount Match
A145: ORD26000144 | B145: 46287 | C145: CUST53573 | D145: Jaipur | E145: UPI | F145: 8498 | G145: Paid | H145: =UPPER(SUBSTITUTE(TRIM(A145),"-","")) -> ORD26000144 | I145: =COUNTIFS(PG_Transactions!$AK:$AK,$H145,PG_Transactions!$E:$E,"CAPTURE",PG_Transactions!$AQ:$AQ,1) -> 1 | J145: =SUMIFS(PG_Transactions!$G:$G,PG_Transactions!$AK:$AK,$H145,PG_Transactions!$E:$E,"CAPTURE",PG_Transactions!$AQ:$AQ,1) -> 8498 | K145: =ROUND(J145-F145,2) -> 0 | L145: =IF(I145=0,"No Capture",IF(I145>1,"Multiple Capture Rows - Review",IF(ABS(K145)<0.01,"Amount Match",IF(K145<0,"Captured Less Than Order","Captured More Than Order")))) -> Amount Match
A146: ORD26000145 | B146: 46290 | C146: CUST41300 | D146: Lucknow | E146: NetBanking | F146: 2798 | G146: Cancelled | H146: =UPPER(SUBSTITUTE(TRIM(A146),"-","")) -> ORD26000145 | I146: =COUNTIFS(PG_Transactions!$AK:$AK,$H146,PG_Transactions!$E:$E,"CAPTURE",PG_Transactions!$AQ:$AQ,1) -> 0 | J146: =SUMIFS(PG_Transactions!$G:$G,PG_Transactions!$AK:$AK,$H146,PG_Transactions!$E:$E,"CAPTURE",PG_Transactions!$AQ:$AQ,1) -> 0 | K146: =ROUND(J146-F146,2) -> -2798 | L146: =IF(I146=0,"No Capture",IF(I146>1,"Multiple Capture Rows - Review",IF(ABS(K146)<0.01,"Amount Match",IF(K146<0,"Captured Less Than Order","Captured More Than Order")))) -> No Capture
A147: ORD26000146 | B147: 46278 | C147: CUST71993 | D147: Kolkata | E147: UPI | F147: 7999 | G147: Paid | H147: =UPPER(SUBSTITUTE(TRIM(A147),"-","")) -> ORD26000146 | I147: =COUNTIFS(PG_Transactions!$AK:$AK,$H147,PG_Transactions!$E:$E,"CAPTURE",PG_Transactions!$AQ:$AQ,1) -> 1 | J147: =SUMIFS(PG_Transactions!$G:$G,PG_Transactions!$AK:$AK,$H147,PG_Transactions!$E:$E,"CAPTURE",PG_Transactions!$AQ:$AQ,1) -> 7999 | K147: =ROUND(J147-F147,2) -> 0 | L147: =IF(I147=0,"No Capture",IF(I147>1,"Multiple Capture Rows - Review",IF(ABS(K147)<0.01,"Amount Match",IF(K147<0,"Captured Less Than Order","Captured More Than Order")))) -> Amount Match
A148: ORD26000147 | B148: 46278 | C148: CUST14852 | D148: Delhi | E148: UPI | F148: 15997 | G148: Refunded | H148: =UPPER(SUBSTITUTE(TRIM(A148),"-","")) -> ORD26000147 | I148: =COUNTIFS(PG_Transactions!$AK:$AK,$H148,PG_Transactions!$E:$E,"CAPTURE",PG_Transactions!$AQ:$AQ,1) -> 1 | J148: =SUMIFS(PG_Transactions!$G:$G,PG_Transactions!$AK:$AK,$H148,PG_Transactions!$E:$E,"CAPTURE",PG_Transactions!$AQ:$AQ,1) -> 15997 | K148: =ROUND(J148-F148,2) -> 0 | L148: =IF(I148=0,"No Capture",IF(I148>1,"Multiple Capture Rows - Review",IF(ABS(K148)<0.01,"Amount Match",IF(K148<0,"Captured Less Than Order","Captured More Than Order")))) -> Amount Match
A149: ORD26000148 | B149: 46282 | C149: CUST23069 | E149: NetBanking | F149: 8998 | G149: Paid | H149: =UPPER(SUBSTITUTE(TRIM(A149),"-","")) -> ORD26000148 | I149: =COUNTIFS(PG_Transactions!$AK:$AK,$H149,PG_Transactions!$E:$E,"CAPTURE",PG_Transactions!$AQ:$AQ,1) -> 1 | J149: =SUMIFS(PG_Transactions!$G:$G,PG_Transactions!$AK:$AK,$H149,PG_Transactions!$E:$E,"CAPTURE",PG_Transactions!$AQ:$AQ,1) -> 8998 | K149: =ROUND(J149-F149,2) -> 0 | L149: =IF(I149=0,"No Capture",IF(I149>1,"Multiple Capture Rows - Review",IF(ABS(K149)<0.01,"Amount Match",IF(K149<0,"Captured Less Than Order","Captured More Than Order")))) -> Amount Match
A150: ORD26000149 | B150: 46295 | C150: CUST30232 | D150: Pune | E150: NetBanking | F150: 3798 | G150: Paid | H150: =UPPER(SUBSTITUTE(TRIM(A150),"-","")) -> ORD26000149 | I150: =COUNTIFS(PG_Transactions!$AK:$AK,$H150,PG_Transactions!$E:$E,"CAPTURE",PG_Transactions!$AQ:$AQ,1) -> 1 | J150: =SUMIFS(PG_Transactions!$G:$G,PG_Transactions!$AK:$AK,$H150,PG_Transactions!$E:$E,"CAPTURE",PG_Transactions!$AQ:$AQ,1) -> 3798 | K150: =ROUND(J150-F150,2) -> 0 | L150: =IF(I150=0,"No Capture",IF(I150>1,"Multiple Capture Rows - Review",IF(ABS(K150)<0.01,"Amount Match",IF(K150<0,"Captured Less Than Order","Captured More Than Order")))) -> Amount Match
A151: ORD26000150 | B151: 46281 | C151: CUST20527 | D151: Chennai | E151: UPI | F151: 999 | G151: Paid | H151: =UPPER(SUBSTITUTE(TRIM(A151),"-","")) -> ORD26000150 | I151: =COUNTIFS(PG_Transactions!$AK:$AK,$H151,PG_Transactions!$E:$E,"CAPTURE",PG_Transactions!$AQ:$AQ,1) -> 1 | J151: =SUMIFS(PG_Transactions!$G:$G,PG_Transactions!$AK:$AK,$H151,PG_Transactions!$E:$E,"CAPTURE",PG_Transactions!$AQ:$AQ,1) -> 999 | K151: =ROUND(J151-F151,2) -> 0 | L151: =IF(I151=0,"No Capture",IF(I151>1,"Multiple Capture Rows - Review",IF(ABS(K151)<0.01,"Amount Match",IF(K151<0,"Captured Less Than Order","Captured More Than Order")))) -> Amount Match
A152: ORD26000151 | B152: 46293 | C152: CUST73956 | D152: Jaipur | E152: Card | F152: 11097 | G152: Cancelled | H152: =UPPER(SUBSTITUTE(TRIM(A152),"-","")) -> ORD26000151 | I152: =COUNTIFS(PG_Transactions!$AK:$AK,$H152,PG_Transactions!$E:$E,"CAPTURE",PG_Transactions!$AQ:$AQ,1) -> 0 | J152: =SUMIFS(PG_Transactions!$G:$G,PG_Transactions!$AK:$AK,$H152,PG_Transactions!$E:$E,"CAPTURE",PG_Transactions!$AQ:$AQ,1) -> 0 | K152: =ROUND(J152-F152,2) -> -11097 | L152: =IF(I152=0,"No Capture",IF(I152>1,"Multiple Capture Rows - Review",IF(ABS(K152)<0.01,"Amount Match",IF(K152<0,"Captured Less Than Order","Captured More Than Order")))) -> No Capture
A153: ORD26000152 | B153: 46267 | C153: CUST39817 | D153: Pune | E153: Wallet | F153: 948 | G153: Paid | H153: =UPPER(SUBSTITUTE(TRIM(A153),"-","")) -> ORD26000152 | I153: =COUNTIFS(PG_Transactions!$AK:$AK,$H153,PG_Transactions!$E:$E,"CAPTURE",PG_Transactions!$AQ:$AQ,1) -> 1 | J153: =SUMIFS(PG_Transactions!$G:$G,PG_Transactions!$AK:$AK,$H153,PG_Transactions!$E:$E,"CAPTURE",PG_Transactions!$AQ:$AQ,1) -> 948 | K153: =ROUND(J153-F153,2) -> 0 | L153: =IF(I153=0,"No Capture",IF(I153>1,"Multiple Capture Rows - Review",IF(ABS(K153)<0.01,"Amount Match",IF(K153<0,"Captured Less Than Order","Captured More Than Order")))) -> Amount Match
A154: ORD26000153 | B154: 46279 | C154: CUST68153 | D154: Delhi | E154: NetBanking | F154: 4999 | G154: Paid | H154: =UPPER(SUBSTITUTE(TRIM(A154),"-","")) -> ORD26000153 | I154: =COUNTIFS(PG_Transactions!$AK:$AK,$H154,PG_Transactions!$E:$E,"CAPTURE",PG_Transactions!$AQ:$AQ,1) -> 1 | J154: =SUMIFS(PG_Transactions!$G:$G,PG_Transactions!$AK:$AK,$H154,PG_Transactions!$E:$E,"CAPTURE",PG_Transactions!$AQ:$AQ,1) -> 4999 | K154: =ROUND(J154-F154,2) -> 0 | L154: =IF(I154=0,"No Capture",IF(I154>1,"Multiple Capture Rows - Review",IF(ABS(K154)<0.01,"Amount Match",IF(K154<0,"Captured Less Than Order","Captured More Than Order")))) -> Amount Match
A155: ORD26000154 | B155: 46288 | C155: CUST48452 | D155: Chennai | E155: Card | F155: 299 | G155: Paid | H155: =UPPER(SUBSTITUTE(TRIM(A155),"-","")) -> ORD26000154 | I155: =COUNTIFS(PG_Transactions!$AK:$AK,$H155,PG_Transactions!$E:$E,"CAPTURE",PG_Transactions!$AQ:$AQ,1) -> 1 | J155: =SUMIFS(PG_Transactions!$G:$G,PG_Transactions!$AK:$AK,$H155,PG_Transactions!$E:$E,"CAPTURE",PG_Transactions!$AQ:$AQ,1) -> 299 | K155: =ROUND(J155-F155,2) -> 0 | L155: =IF(I155=0,"No Capture",IF(I155>1,"Multiple Capture Rows - Review",IF(ABS(K155)<0.01,"Amount Match",IF(K155<0,"Captured Less Than Order","Captured More Than Order")))) -> Amount Match
A156: ORD26000155 | B156: 46277 | C156: CUST33600 | D156: Delhi | E156: Card | F156: 1098 | G156: Paid | H156: =UPPER(SUBSTITUTE(TRIM(A156),"-","")) -> ORD26000155 | I156: =COUNTIFS(PG_Transactions!$AK:$AK,$H156,PG_Transactions!$E:$E,"CAPTURE",PG_Transactions!$AQ:$AQ,1) -> 1 | J156: =SUMIFS(PG_Transactions!$G:$G,PG_Transactions!$AK:$AK,$H156,PG_Transactions!$E:$E,"CAPTURE",PG_Transactions!$AQ:$AQ,1) -> 1098 | K156: =ROUND(J156-F156,2) -> 0 | L156: =IF(I156=0,"No Capture",IF(I156>1,"Multiple Capture Rows - Review",IF(ABS(K156)<0.01,"Amount Match",IF(K156<0,"Captured Less Than Order","Captured More Than Order")))) -> Amount Match
A157: ORD26000156 | B157: 46271 | C157: CUST41566 | D157: Ahmedabad | E157: Card | F157: 2499 | G157: Paid | H157: =UPPER(SUBSTITUTE(TRIM(A157),"-","")) -> ORD26000156 | I157: =COUNTIFS(PG_Transactions!$AK:$AK,$H157,PG_Transactions!$E:$E,"CAPTURE",PG_Transactions!$AQ:$AQ,1) -> 1 | J157: =SUMIFS(PG_Transactions!$G:$G,PG_Transactions!$AK:$AK,$H157,PG_Transactions!$E:$E,"CAPTURE",PG_Transactions!$AQ:$AQ,1) -> 2499 | K157: =ROUND(J157-F157,2) -> 0 | L157: =IF(I157=0,"No Capture",IF(I157>1,"Multiple Capture Rows - Review",IF(ABS(K157)<0.01,"Amount Match",IF(K157<0,"Captured Less Than Order","Captured More Than Order")))) -> Amount Match
A158: ORD26000157 | B158: 46295 | C158: CUST43466 | D158: Mumbai | E158: UPI | F158: 1098 | G158: Paid | H158: =UPPER(SUBSTITUTE(TRIM(A158),"-","")) -> ORD26000157 | I158: =COUNTIFS(PG_Transactions!$AK:$AK,$H158,PG_Transactions!$E:$E,"CAPTURE",PG_Transactions!$AQ:$AQ,1) -> 1 | J158: =SUMIFS(PG_Transactions!$G:$G,PG_Transactions!$AK:$AK,$H158,PG_Transactions!$E:$E,"CAPTURE",PG_Transactions!$AQ:$AQ,1) -> 1098 | K158: =ROUND(J158-F158,2) -> 0 | L158: =IF(I158=0,"No Capture",IF(I158>1,"Multiple Capture Rows - Review",IF(ABS(K158)<0.01,"Amount Match",IF(K158<0,"Captured Less Than Order","Captured More Than Order")))) -> Amount Match
A159: ORD26000158 | B159: 46294 | C159: CUST55293 | D159: Lucknow | E159: UPI | F159: 3798 | G159: Paid | H159: =UPPER(SUBSTITUTE(TRIM(A159),"-","")) -> ORD26000158 | I159: =COUNTIFS(PG_Transactions!$AK:$AK,$H159,PG_Transactions!$E:$E,"CAPTURE",PG_Transactions!$AQ:$AQ,1) -> 1 | J159: =SUMIFS(PG_Transactions!$G:$G,PG_Transactions!$AK:$AK,$H159,PG_Transactions!$E:$E,"CAPTURE",PG_Transactions!$AQ:$AQ,1) -> 3798 | K159: =ROUND(J159-F159,2) -> 0 | L159: =IF(I159=0,"No Capture",IF(I159>1,"Multiple Capture Rows - Review",IF(ABS(K159)<0.01,"Amount Match",IF(K159<0,"Captured Less Than Order","Captured More Than Order")))) -> Amount Match
A160: ORD26000159 | B160: 46275 | C160: CUST60422 | D160: Ahmedabad | E160: UPI | F160: 5597 | G160: Paid | H160: =UPPER(SUBSTITUTE(TRIM(A160),"-","")) -> ORD26000159 | I160: =COUNTIFS(PG_Transactions!$AK:$AK,$H160,PG_Transactions!$E:$E,"CAPTURE",PG_Transactions!$AQ:$AQ,1) -> 1 | J160: =SUMIFS(PG_Transactions!$G:$G,PG_Transactions!$AK:$AK,$H160,PG_Transactions!$E:$E,"CAPTURE",PG_Transactions!$AQ:$AQ,1) -> 5597 | K160: =ROUND(J160-F160,2) -> 0 | L160: =IF(I160=0,"No Capture",IF(I160>1,"Multiple Capture Rows - Review",IF(ABS(K160)<0.01,"Amount Match",IF(K160<0,"Captured Less Than Order","Captured More Than Order")))) -> Amount Match
A161: ORD26000160 | B161: 46269 | C161: CUST48696 | D161: Mumbai | E161: Card | F161: 1299 | G161: Paid | H161: =UPPER(SUBSTITUTE(TRIM(A161),"-","")) -> ORD26000160 | I161: =COUNTIFS(PG_Transactions!$AK:$AK,$H161,PG_Transactions!$E:$E,"CAPTURE",PG_Transactions!$AQ:$AQ,1) -> 1 | J161: =SUMIFS(PG_Transactions!$G:$G,PG_Transactions!$AK:$AK,$H161,PG_Transactions!$E:$E,"CAPTURE",PG_Transactions!$AQ:$AQ,1) -> 1299 | K161: =ROUND(J161-F161,2) -> 0 | L161: =IF(I161=0,"No Capture",IF(I161>1,"Multiple Capture Rows - Review",IF(ABS(K161)<0.01,"Amount Match",IF(K161<0,"Captured Less Than Order","Captured More Than Order")))) -> Amount Match
A162: ORD26000161 | B162: 46292 | C162: CUST16428 | D162: Lucknow | E162: Card | F162: 2397 | G162: Paid | H162: =UPPER(SUBSTITUTE(TRIM(A162),"-","")) -> ORD26000161 | I162: =COUNTIFS(PG_Transactions!$AK:$AK,$H162,PG_Transactions!$E:$E,"CAPTURE",PG_Transactions!$AQ:$AQ,1) -> 1 | J162: =SUMIFS(PG_Transactions!$G:$G,PG_Transactions!$AK:$AK,$H162,PG_Transactions!$E:$E,"CAPTURE",PG_Transactions!$AQ:$AQ,1) -> 2397 | K162: =ROUND(J162-F162,2) -> 0 | L162: =IF(I162=0,"No Capture",IF(I162>1,"Multiple Capture Rows - Review",IF(ABS(K162)<0.01,"Amount Match",IF(K162<0,"Captured Less Than Order","Captured More Than Order")))) -> Amount Match
A163: ORD26000162 | B163: 46289 | C163: CUST56179 | E163: UPI | F163: 8798 | G163: Paid | H163: =UPPER(SUBSTITUTE(TRIM(A163),"-","")) -> ORD26000162 | I163: =COUNTIFS(PG_Transactions!$AK:$AK,$H163,PG_Transactions!$E:$E,"CAPTURE",PG_Transactions!$AQ:$AQ,1) -> 1 | J163: =SUMIFS(PG_Transactions!$G:$G,PG_Transactions!$AK:$AK,$H163,PG_Transactions!$E:$E,"CAPTURE",PG_Transactions!$AQ:$AQ,1) -> 8798 | K163: =ROUND(J163-F163,2) -> 0 | L163: =IF(I163=0,"No Capture",IF(I163>1,"Multiple Capture Rows - Review",IF(ABS(K163)<0.01,"Amount Match",IF(K163<0,"Captured Less Than Order","Captured More Than Order")))) -> Amount Match
A164: ORD26000163 | B164: 46286 | C164: CUST96400 | D164: Delhi | E164: Card | F164: 2499 | G164: Paid | H164: =UPPER(SUBSTITUTE(TRIM(A164),"-","")) -> ORD26000163 | I164: =COUNTIFS(PG_Transactions!$AK:$AK,$H164,PG_Transactions!$E:$E,"CAPTURE",PG_Transactions!$AQ:$AQ,1) -> 1 | J164: =SUMIFS(PG_Transactions!$G:$G,PG_Transactions!$AK:$AK,$H164,PG_Transactions!$E:$E,"CAPTURE",PG_Transactions!$AQ:$AQ,1) -> 2499 | K164: =ROUND(J164-F164,2) -> 0 | L164: =IF(I164=0,"No Capture",IF(I164>1,"Multiple Capture Rows - Review",IF(ABS(K164)<0.01,"Amount Match",IF(K164<0,"Captured Less Than Order","Captured More Than Order")))) -> Amount Match
A165: ORD26000164 | B165: 46286 | C165: CUST67779 | D165: Mumbai | E165: UPI | F165: 2999 | G165: Paid | H165: =UPPER(SUBSTITUTE(TRIM(A165),"-","")) -> ORD26000164 | I165: =COUNTIFS(PG_Transactions!$AK:$AK,$H165,PG_Transactions!$E:$E,"CAPTURE",PG_Transactions!$AQ:$AQ,1) -> 1 | J165: =SUMIFS(PG_Transactions!$G:$G,PG_Transactions!$AK:$AK,$H165,PG_Transactions!$E:$E,"CAPTURE",PG_Transactions!$AQ:$AQ,1) -> 2999 | K165: =ROUND(J165-F165,2) -> 0 | L165: =IF(I165=0,"No Capture",IF(I165>1,"Multiple Capture Rows - Review",IF(ABS(K165)<0.01,"Amount Match",IF(K165<0,"Captured Less Than Order","Captured More Than Order")))) -> Amount Match
A166: ORD26000165 | B166: 46284 | C166: CUST52823 | D166: Kolkata | E166: Wallet | F166: 3499 | G166: Paid | H166: =UPPER(SUBSTITUTE(TRIM(A166),"-","")) -> ORD26000165 | I166: =COUNTIFS(PG_Transactions!$AK:$AK,$H166,PG_Transactions!$E:$E,"CAPTURE",PG_Transactions!$AQ:$AQ,1) -> 1 | J166: =SUMIFS(PG_Transactions!$G:$G,PG_Transactions!$AK:$AK,$H166,PG_Transactions!$E:$E,"CAPTURE",PG_Transactions!$AQ:$AQ,1) -> 3499 | K166: =ROUND(J166-F166,2) -> 0 | L166: =IF(I166=0,"No Capture",IF(I166>1,"Multiple Capture Rows - Review",IF(ABS(K166)<0.01,"Amount Match",IF(K166<0,"Captured Less Than Order","Captured More Than Order")))) -> Amount Match
A167: ORD26000166 | B167: 46271 | C167: CUST57953 | D167: Jaipur | E167: NetBanking | F167: 499 | G167: Paid | H167: =UPPER(SUBSTITUTE(TRIM(A167),"-","")) -> ORD26000166 | I167: =COUNTIFS(PG_Transactions!$AK:$AK,$H167,PG_Transactions!$E:$E,"CAPTURE",PG_Transactions!$AQ:$AQ,1) -> 1 | J167: =SUMIFS(PG_Transactions!$G:$G,PG_Transactions!$AK:$AK,$H167,PG_Transactions!$E:$E,"CAPTURE",PG_Transactions!$AQ:$AQ,1) -> 499 | K167: =ROUND(J167-F167,2) -> 0 | L167: =IF(I167=0,"No Capture",IF(I167>1,"Multiple Capture Rows - Review",IF(ABS(K167)<0.01,"Amount Match",IF(K167<0,"Captured Less Than Order","Captured More Than Order")))) -> Amount Match
A168: ORD26000167 | B168: 46282 | C168: CUST73156 | D168: Hyderabad | E168: Wallet | F168: 7999 | G168: Paid | H168: =UPPER(SUBSTITUTE(TRIM(A168),"-","")) -> ORD26000167 | I168: =COUNTIFS(PG_Transactions!$AK:$AK,$H168,PG_Transactions!$E:$E,"CAPTURE",PG_Transactions!$AQ:$AQ,1) -> 1 | J168: =SUMIFS(PG_Transactions!$G:$G,PG_Transactions!$AK:$AK,$H168,PG_Transactions!$E:$E,"CAPTURE",PG_Transactions!$AQ:$AQ,1) -> 7999 | K168: =ROUND(J168-F168,2) -> 0 | L168: =IF(I168=0,"No Capture",IF(I168>1,"Multiple Capture Rows - Review",IF(ABS(K168)<0.01,"Amount Match",IF(K168<0,"Captured Less Than Order","Captured More Than Order")))) -> Amount Match
A169: ORD26000168 | B169: 46289 | C169: CUST28449 | D169: Bengaluru | E169: Wallet | F169: 4999 | G169: Paid | H169: =UPPER(SUBSTITUTE(TRIM(A169),"-","")) -> ORD26000168 | I169: =COUNTIFS(PG_Transactions!$AK:$AK,$H169,PG_Transactions!$E:$E,"CAPTURE",PG_Transactions!$AQ:$AQ,1) -> 1 | J169: =SUMIFS(PG_Transactions!$G:$G,PG_Transactions!$AK:$AK,$H169,PG_Transactions!$E:$E,"CAPTURE",PG_Transactions!$AQ:$AQ,1) -> 4999 | K169: =ROUND(J169-F169,2) -> 0 | L169: =IF(I169=0,"No Capture",IF(I169>1,"Multiple Capture Rows - Review",IF(ABS(K169)<0.01,"Amount Match",IF(K169<0,"Captured Less Than Order","Captured More Than Order")))) -> Amount Match
A170: ORD26000169 | B170: 46293 | C170: CUST57942 | D170: Pune | E170: NetBanking | F170: 7797 | G170: Refunded | H170: =UPPER(SUBSTITUTE(TRIM(A170),"-","")) -> ORD26000169 | I170: =COUNTIFS(PG_Transactions!$AK:$AK,$H170,PG_Transactions!$E:$E,"CAPTURE",PG_Transactions!$AQ:$AQ,1) -> 1 | J170: =SUMIFS(PG_Transactions!$G:$G,PG_Transactions!$AK:$AK,$H170,PG_Transactions!$E:$E,"CAPTURE",PG_Transactions!$AQ:$AQ,1) -> 7797 | K170: =ROUND(J170-F170,2) -> 0 | L170: =IF(I170=0,"No Capture",IF(I170>1,"Multiple Capture Rows - Review",IF(ABS(K170)<0.01,"Amount Match",IF(K170<0,"Captured Less Than Order","Captured More Than Order")))) -> Amount Match
A171: ORD26000170 | B171: 46291 | C171: CUST98188 | E171: UPI | F171: 1098 | G171: Paid | H171: =UPPER(SUBSTITUTE(TRIM(A171),"-","")) -> ORD26000170 | I171: =COUNTIFS(PG_Transactions!$AK:$AK,$H171,PG_Transactions!$E:$E,"CAPTURE",PG_Transactions!$AQ:$AQ,1) -> 1 | J171: =SUMIFS(PG_Transactions!$G:$G,PG_Transactions!$AK:$AK,$H171,PG_Transactions!$E:$E,"CAPTURE",PG_Transactions!$AQ:$AQ,1) -> 1098 | K171: =ROUND(J171-F171,2) -> 0 | L171: =IF(I171=0,"No Capture",IF(I171>1,"Multiple Capture Rows - Review",IF(ABS(K171)<0.01,"Amount Match",IF(K171<0,"Captured Less Than Order","Captured More Than Order")))) -> Amount Match
A172: ORD26000171 | B172: 46284 | C172: CUST40647 | D172: Ahmedabad | E172: UPI | F172: 10998 | G172: Cancelled | H172: =UPPER(SUBSTITUTE(TRIM(A172),"-","")) -> ORD26000171 | I172: =COUNTIFS(PG_Transactions!$AK:$AK,$H172,PG_Transactions!$E:$E,"CAPTURE",PG_Transactions!$AQ:$AQ,1) -> 0 | J172: =SUMIFS(PG_Transactions!$G:$G,PG_Transactions!$AK:$AK,$H172,PG_Transactions!$E:$E,"CAPTURE",PG_Transactions!$AQ:$AQ,1) -> 0 | K172: =ROUND(J172-F172,2) -> -10998 | L172: =IF(I172=0,"No Capture",IF(I172>1,"Multiple Capture Rows - Review",IF(ABS(K172)<0.01,"Amount Match",IF(K172<0,"Captured Less Than Order","Captured More Than Order")))) -> No Capture
A173: ORD26000172 | B173: 46266 | C173: CUST18285 | D173: Ahmedabad | E173: UPI | F173: 2798 | G173: Failed | H173: =UPPER(SUBSTITUTE(TRIM(A173),"-","")) -> ORD26000172 | I173: =COUNTIFS(PG_Transactions!$AK:$AK,$H173,PG_Transactions!$E:$E,"CAPTURE",PG_Transactions!$AQ:$AQ,1) -> 0 | J173: =SUMIFS(PG_Transactions!$G:$G,PG_Transactions!$AK:$AK,$H173,PG_Transactions!$E:$E,"CAPTURE",PG_Transactions!$AQ:$AQ,1) -> 0 | K173: =ROUND(J173-F173,2) -> -2798 | L173: =IF(I173=0,"No Capture",IF(I173>1,"Multiple Capture Rows - Review",IF(ABS(K173)<0.01,"Amount Match",IF(K173<0,"Captured Less Than Order","Captured More Than Order")))) -> No Capture
A174: ORD26000173 | B174: 46295 | C174: CUST14877 | D174: Hyderabad | E174: UPI | F174: 5097 | G174: Paid | H174: =UPPER(SUBSTITUTE(TRIM(A174),"-","")) -> ORD26000173 | I174: =COUNTIFS(PG_Transactions!$AK:$AK,$H174,PG_Transactions!$E:$E,"CAPTURE",PG_Transactions!$AQ:$AQ,1) -> 1 | J174: =SUMIFS(PG_Transactions!$G:$G,PG_Transactions!$AK:$AK,$H174,PG_Transactions!$E:$E,"CAPTURE",PG_Transactions!$AQ:$AQ,1) -> 5097 | K174: =ROUND(J174-F174,2) -> 0 | L174: =IF(I174=0,"No Capture",IF(I174>1,"Multiple Capture Rows - Review",IF(ABS(K174)<0.01,"Amount Match",IF(K174<0,"Captured Less Than Order","Captured More Than Order")))) -> Amount Match
A175: ORD26000174 | B175: 46281 | C175: CUST60940 | D175: Ahmedabad | E175: UPI | F175: 349 | G175: Paid | H175: =UPPER(SUBSTITUTE(TRIM(A175),"-","")) -> ORD26000174 | I175: =COUNTIFS(PG_Transactions!$AK:$AK,$H175,PG_Transactions!$E:$E,"CAPTURE",PG_Transactions!$AQ:$AQ,1) -> 1 | J175: =SUMIFS(PG_Transactions!$G:$G,PG_Transactions!$AK:$AK,$H175,PG_Transactions!$E:$E,"CAPTURE",PG_Transactions!$AQ:$AQ,1) -> 349 | K175: =ROUND(J175-F175,2) -> 0 | L175: =IF(I175=0,"No Capture",IF(I175>1,"Multiple Capture Rows - Review",IF(ABS(K175)<0.01,"Amount Match",IF(K175<0,"Captured Less Than Order","Captured More Than Order")))) -> Amount Match
A176: ORD26000175 | B176: 46277 | C176: CUST30253 | D176: Kolkata | E176: Card | F176: 8797 | G176: Paid | H176: =UPPER(SUBSTITUTE(TRIM(A176),"-","")) -> ORD26000175 | I176: =COUNTIFS(PG_Transactions!$AK:$AK,$H176,PG_Transactions!$E:$E,"CAPTURE",PG_Transactions!$AQ:$AQ,1) -> 1 | J176: =SUMIFS(PG_Transactions!$G:$G,PG_Transactions!$AK:$AK,$H176,PG_Transactions!$E:$E,"CAPTURE",PG_Transactions!$AQ:$AQ,1) -> 8797 | K176: =ROUND(J176-F176,2) -> 0 | L176: =IF(I176=0,"No Capture",IF(I176>1,"Multiple Capture Rows - Review",IF(ABS(K176)<0.01,"Amount Match",IF(K176<0,"Captured Less Than Order","Captured More Than Order")))) -> Amount Match
A177: ORD26000176 | B177: 46286 | C177: CUST46666 | D177: Mumbai | E177: UPI | F177: 7999 | G177: Paid | H177: =UPPER(SUBSTITUTE(TRIM(A177),"-","")) -> ORD26000176 | I177: =COUNTIFS(PG_Transactions!$AK:$AK,$H177,PG_Transactions!$E:$E,"CAPTURE",PG_Transactions!$AQ:$AQ,1) -> 1 | J177: =SUMIFS(PG_Transactions!$G:$G,PG_Transactions!$AK:$AK,$H177,PG_Transactions!$E:$E,"CAPTURE",PG_Transactions!$AQ:$AQ,1) -> 7999 | K177: =ROUND(J177-F177,2) -> 0 | L177: =IF(I177=0,"No Capture",IF(I177>1,"Multiple Capture Rows - Review",IF(ABS(K177)<0.01,"Amount Match",IF(K177<0,"Captured Less Than Order","Captured More Than Order")))) -> Amount Match
A178: ORD26000177 | B178: 46288 | C178: CUST57537 | D178: Pune | E178: Wallet | F178: 599 | G178: Paid | H178: =UPPER(SUBSTITUTE(TRIM(A178),"-","")) -> ORD26000177 | I178: =COUNTIFS(PG_Transactions!$AK:$AK,$H178,PG_Transactions!$E:$E,"CAPTURE",PG_Transactions!$AQ:$AQ,1) -> 1 | J178: =SUMIFS(PG_Transactions!$G:$G,PG_Transactions!$AK:$AK,$H178,PG_Transactions!$E:$E,"CAPTURE",PG_Transactions!$AQ:$AQ,1) -> 599 | K178: =ROUND(J178-F178,2) -> 0 | L178: =IF(I178=0,"No Capture",IF(I178>1,"Multiple Capture Rows - Review",IF(ABS(K178)<0.01,"Amount Match",IF(K178<0,"Captured Less Than Order","Captured More Than Order")))) -> Amount Match
A179: ORD26000178 | B179: 46287 | C179: CUST17936 | D179: Kolkata | E179: Card | F179: 1799 | G179: Failed | H179: =UPPER(SUBSTITUTE(TRIM(A179),"-","")) -> ORD26000178 | I179: =COUNTIFS(PG_Transactions!$AK:$AK,$H179,PG_Transactions!$E:$E,"CAPTURE",PG_Transactions!$AQ:$AQ,1) -> 0 | J179: =SUMIFS(PG_Transactions!$G:$G,PG_Transactions!$AK:$AK,$H179,PG_Transactions!$E:$E,"CAPTURE",PG_Transactions!$AQ:$AQ,1) -> 0 | K179: =ROUND(J179-F179,2) -> -1799 | L179: =IF(I179=0,"No Capture",IF(I179>1,"Multiple Capture Rows - Review",IF(ABS(K179)<0.01,"Amount Match",IF(K179<0,"Captured Less Than Order","Captured More Than Order")))) -> No Capture
A180: ORD26000179 | B180: 46274 | C180: CUST22015 | D180: Bengaluru | E180: NetBanking | F180: 349 | G180: Cancelled | H180: =UPPER(SUBSTITUTE(TRIM(A180),"-","")) -> ORD26000179 | I180: =COUNTIFS(PG_Transactions!$AK:$AK,$H180,PG_Transactions!$E:$E,"CAPTURE",PG_Transactions!$AQ:$AQ,1) -> 0 | J180: =SUMIFS(PG_Transactions!$G:$G,PG_Transactions!$AK:$AK,$H180,PG_Transactions!$E:$E,"CAPTURE",PG_Transactions!$AQ:$AQ,1) -> 0 | K180: =ROUND(J180-F180,2) -> -349 | L180: =IF(I180=0,"No Capture",IF(I180>1,"Multiple Capture Rows - Review",IF(ABS(K180)<0.01,"Amount Match",IF(K180<0,"Captured Less Than Order","Captured More Than Order")))) -> No Capture
A181: ORD26000180 | B181: 46286 | C181: CUST26505 | E181: UPI | F181: 3097 | G181: Paid | H181: =UPPER(SUBSTITUTE(TRIM(A181),"-","")) -> ORD26000180 | I181: =COUNTIFS(PG_Transactions!$AK:$AK,$H181,PG_Transactions!$E:$E,"CAPTURE",PG_Transactions!$AQ:$AQ,1) -> 1 | J181: =SUMIFS(PG_Transactions!$G:$G,PG_Transactions!$AK:$AK,$H181,PG_Transactions!$E:$E,"CAPTURE",PG_Transactions!$AQ:$AQ,1) -> 3097 | K181: =ROUND(J181-F181,2) -> 0 | L181: =IF(I181=0,"No Capture",IF(I181>1,"Multiple Capture Rows - Review",IF(ABS(K181)<0.01,"Amount Match",IF(K181<0,"Captured Less Than Order","Captured More Than Order")))) -> Amount Match
A182: ORD26000181 | B182: 46272 | C182: CUST38305 | D182: Bengaluru | E182: UPI | F182: 7999 | G182: Paid | H182: =UPPER(SUBSTITUTE(TRIM(A182),"-","")) -> ORD26000181 | I182: =COUNTIFS(PG_Transactions!$AK:$AK,$H182,PG_Transactions!$E:$E,"CAPTURE",PG_Transactions!$AQ:$AQ,1) -> 1 | J182: =SUMIFS(PG_Transactions!$G:$G,PG_Transactions!$AK:$AK,$H182,PG_Transactions!$E:$E,"CAPTURE",PG_Transactions!$AQ:$AQ,1) -> 7999 | K182: =ROUND(J182-F182,2) -> 0 | L182: =IF(I182=0,"No Capture",IF(I182>1,"Multiple Capture Rows - Review",IF(ABS(K182)<0.01,"Amount Match",IF(K182<0,"Captured Less Than Order","Captured More Than Order")))) -> Amount Match
A183: ORD26000182 | B183: 46276 | C183: CUST28964 | D183: Delhi | E183: UPI | F183: 4999 | G183: Failed | H183: =UPPER(SUBSTITUTE(TRIM(A183),"-","")) -> ORD26000182 | I183: =COUNTIFS(PG_Transactions!$AK:$AK,$H183,PG_Transactions!$E:$E,"CAPTURE",PG_Transactions!$AQ:$AQ,1) -> 0 | J183: =SUMIFS(PG_Transactions!$G:$G,PG_Transactions!$AK:$AK,$H183,PG_Transactions!$E:$E,"CAPTURE",PG_Transactions!$AQ:$AQ,1) -> 0 | K183: =ROUND(J183-F183,2) -> -4999 | L183: =IF(I183=0,"No Capture",IF(I183>1,"Multiple Capture Rows - Review",IF(ABS(K183)<0.01,"Amount Match",IF(K183<0,"Captured Less Than Order","Captured More Than Order")))) -> No Capture
A184: ORD26000183 | B184: 46283 | C184: CUST13379 | D184: Delhi | E184: Card | F184: 4999 | G184: Paid | H184: =UPPER(SUBSTITUTE(TRIM(A184),"-","")) -> ORD26000183 | I184: =COUNTIFS(PG_Transactions!$AK:$AK,$H184,PG_Transactions!$E:$E,"CAPTURE",PG_Transactions!$AQ:$AQ,1) -> 1 | J184: =SUMIFS(PG_Transactions!$G:$G,PG_Transactions!$AK:$AK,$H184,PG_Transactions!$E:$E,"CAPTURE",PG_Transactions!$AQ:$AQ,1) -> 4999 | K184: =ROUND(J184-F184,2) -> 0 | L184: =IF(I184=0,"No Capture",IF(I184>1,"Multiple Capture Rows - Review",IF(ABS(K184)<0.01,"Amount Match",IF(K184<0,"Captured Less Than Order","Captured More Than Order")))) -> Amount Match
A185: ORD26000184 | B185: 46266 | C185: CUST12068 | D185: Delhi | E185: Card | F185: 4999 | G185: Paid | H185: =UPPER(SUBSTITUTE(TRIM(A185),"-","")) -> ORD26000184 | I185: =COUNTIFS(PG_Transactions!$AK:$AK,$H185,PG_Transactions!$E:$E,"CAPTURE",PG_Transactions!$AQ:$AQ,1) -> 1 | J185: =SUMIFS(PG_Transactions!$G:$G,PG_Transactions!$AK:$AK,$H185,PG_Transactions!$E:$E,"CAPTURE",PG_Transactions!$AQ:$AQ,1) -> 4999 | K185: =ROUND(J185-F185,2) -> 0 | L185: =IF(I185=0,"No Capture",IF(I185>1,"Multiple Capture Rows - Review",IF(ABS(K185)<0.01,"Amount Match",IF(K185<0,"Captured Less Than Order","Captured More Than Order")))) -> Amount Match
A186: ORD26000185 | B186: 46274 | C186: CUST18330 | D186: Ahmedabad | E186: UPI | F186: 499 | G186: Paid | H186: =UPPER(SUBSTITUTE(TRIM(A186),"-","")) -> ORD26000185 | I186: =COUNTIFS(PG_Transactions!$AK:$AK,$H186,PG_Transactions!$E:$E,"CAPTURE",PG_Transactions!$AQ:$AQ,1) -> 1 | J186: =SUMIFS(PG_Transactions!$G:$G,PG_Transactions!$AK:$AK,$H186,PG_Transactions!$E:$E,"CAPTURE",PG_Transactions!$AQ:$AQ,1) -> 499 | K186: =ROUND(J186-F186,2) -> 0 | L186: =IF(I186=0,"No Capture",IF(I186>1,"Multiple Capture Rows - Review",IF(ABS(K186)<0.01,"Amount Match",IF(K186<0,"Captured Less Than Order","Captured More Than Order")))) -> Amount Match
A187: ORD26000186 | B187: 46280 | C187: CUST39038 | D187: Lucknow | E187: UPI | F187: 1799 | G187: Paid | H187: =UPPER(SUBSTITUTE(TRIM(A187),"-","")) -> ORD26000186 | I187: =COUNTIFS(PG_Transactions!$AK:$AK,$H187,PG_Transactions!$E:$E,"CAPTURE",PG_Transactions!$AQ:$AQ,1) -> 1 | J187: =SUMIFS(PG_Transactions!$G:$G,PG_Transactions!$AK:$AK,$H187,PG_Transactions!$E:$E,"CAPTURE",PG_Transactions!$AQ:$AQ,1) -> 1799 | K187: =ROUND(J187-F187,2) -> 0 | L187: =IF(I187=0,"No Capture",IF(I187>1,"Multiple Capture Rows - Review",IF(ABS(K187)<0.01,"Amount Match",IF(K187<0,"Captured Less Than Order","Captured More Than Order")))) -> Amount Match
A188: ORD26000187 | B188: 46267 | C188: CUST14082 | D188: Mumbai | E188: UPI | F188: 15997 | G188: Paid | H188: =UPPER(SUBSTITUTE(TRIM(A188),"-","")) -> ORD26000187 | I188: =COUNTIFS(PG_Transactions!$AK:$AK,$H188,PG_Transactions!$E:$E,"CAPTURE",PG_Transactions!$AQ:$AQ,1) -> 1 | J188: =SUMIFS(PG_Transactions!$G:$G,PG_Transactions!$AK:$AK,$H188,PG_Transactions!$E:$E,"CAPTURE",PG_Transactions!$AQ:$AQ,1) -> 15997 | K188: =ROUND(J188-F188,2) -> 0 | L188: =IF(I188=0,"No Capture",IF(I188>1,"Multiple Capture Rows - Review",IF(ABS(K188)<0.01,"Amount Match",IF(K188<0,"Captured Less Than Order","Captured More Than Order")))) -> Amount Match
A189: ORD26000188 | B189: 46281 | C189: CUST68138 | D189: Pune | E189: Card | F189: 4298 | G189: Paid | H189: =UPPER(SUBSTITUTE(TRIM(A189),"-","")) -> ORD26000188 | I189: =COUNTIFS(PG_Transactions!$AK:$AK,$H189,PG_Transactions!$E:$E,"CAPTURE",PG_Transactions!$AQ:$AQ,1) -> 1 | J189: =SUMIFS(PG_Transactions!$G:$G,PG_Transactions!$AK:$AK,$H189,PG_Transactions!$E:$E,"CAPTURE",PG_Transactions!$AQ:$AQ,1) -> 4298 | K189: =ROUND(J189-F189,2) -> 0 | L189: =IF(I189=0,"No Capture",IF(I189>1,"Multiple Capture Rows - Review",IF(ABS(K189)<0.01,"Amount Match",IF(K189<0,"Captured Less Than Order","Captured More Than Order")))) -> Amount Match
A190: ORD26000189 | B190: 46294 | C190: CUST46046 | D190: Lucknow | E190: UPI | F190: 999 | G190: Paid | H190: =UPPER(SUBSTITUTE(TRIM(A190),"-","")) -> ORD26000189 | I190: =COUNTIFS(PG_Transactions!$AK:$AK,$H190,PG_Transactions!$E:$E,"CAPTURE",PG_Transactions!$AQ:$AQ,1) -> 1 | J190: =SUMIFS(PG_Transactions!$G:$G,PG_Transactions!$AK:$AK,$H190,PG_Transactions!$E:$E,"CAPTURE",PG_Transactions!$AQ:$AQ,1) -> 999 | K190: =ROUND(J190-F190,2) -> 0 | L190: =IF(I190=0,"No Capture",IF(I190>1,"Multiple Capture Rows - Review",IF(ABS(K190)<0.01,"Amount Match",IF(K190<0,"Captured Less Than Order","Captured More Than Order")))) -> Amount Match
A191: ORD26000190 | B191: 46286 | C191: CUST79541 | D191: Hyderabad | E191: Wallet | F191: 5298 | G191: Paid | H191: =UPPER(SUBSTITUTE(TRIM(A191),"-","")) -> ORD26000190 | I191: =COUNTIFS(PG_Transactions!$AK:$AK,$H191,PG_Transactions!$E:$E,"CAPTURE",PG_Transactions!$AQ:$AQ,1) -> 1 | J191: =SUMIFS(PG_Transactions!$G:$G,PG_Transactions!$AK:$AK,$H191,PG_Transactions!$E:$E,"CAPTURE",PG_Transactions!$AQ:$AQ,1) -> 5298 | K191: =ROUND(J191-F191,2) -> 0 | L191: =IF(I191=0,"No Capture",IF(I191>1,"Multiple Capture Rows - Review",IF(ABS(K191)<0.01,"Amount Match",IF(K191<0,"Captured Less Than Order","Captured More Than Order")))) -> Amount Match
A192: ORD26000191 | B192: 46280 | C192: CUST95814 | D192: Jaipur | E192: Card | F192: 3798 | G192: Paid | H192: =UPPER(SUBSTITUTE(TRIM(A192),"-","")) -> ORD26000191 | I192: =COUNTIFS(PG_Transactions!$AK:$AK,$H192,PG_Transactions!$E:$E,"CAPTURE",PG_Transactions!$AQ:$AQ,1) -> 1 | J192: =SUMIFS(PG_Transactions!$G:$G,PG_Transactions!$AK:$AK,$H192,PG_Transactions!$E:$E,"CAPTURE",PG_Transactions!$AQ:$AQ,1) -> 3798 | K192: =ROUND(J192-F192,2) -> 0 | L192: =IF(I192=0,"No Capture",IF(I192>1,"Multiple Capture Rows - Review",IF(ABS(K192)<0.01,"Amount Match",IF(K192<0,"Captured Less Than Order","Captured More Than Order")))) -> Amount Match
A193: ORD26000192 | B193: 46289 | C193: CUST54424 | D193: Ahmedabad | E193: UPI | F193: 1299 | G193: Paid | H193: =UPPER(SUBSTITUTE(TRIM(A193),"-","")) -> ORD26000192 | I193: =COUNTIFS(PG_Transactions!$AK:$AK,$H193,PG_Transactions!$E:$E,"CAPTURE",PG_Transactions!$AQ:$AQ,1) -> 1 | J193: =SUMIFS(PG_Transactions!$G:$G,PG_Transactions!$AK:$AK,$H193,PG_Transactions!$E:$E,"CAPTURE",PG_Transactions!$AQ:$AQ,1) -> 1299 | K193: =ROUND(J193-F193,2) -> 0 | L193: =IF(I193=0,"No Capture",IF(I193>1,"Multiple Capture Rows - Review",IF(ABS(K193)<0.01,"Amount Match",IF(K193<0,"Captured Less Than Order","Captured More Than Order")))) -> Amount Match
...

Sheet PG_Transactions
A1: pg_txn_id | B1: original_payment_id | C1: merchant_order_ref | D1: txn_date | E1: txn_type | F1: payment_method | G1: gross_amount | H1: mdr_fee | I1: gst_on_fee | J1: net_amount | K1: settlement_date | L1: settlement_batch_id | M1: Duplicate_Count | N1: Order_Match_Check | O1: Unmatched_Count | P1: Normalized_Match | Q1: Normalized_Unmatched_Count | R1: Transaction_Category | S1: Capture_Count_By_Reference | T1: Transaction Category | U1: Count | V1: Expected_MDR_Pct | W1: Expected_MDR_Fee | X1: Expected_GST | Y1: MDR_Fee_Variance | Z1: GST_Variance | AA1: Rows_With_Duplicate_IDs\ | AB1: Fee Summary | AD1: Distinct_Duplicate_IDs | AE1: Bank_Batch_Match | AF1: Original_Payment_Check | AG1: Refund_Original_Status | AH1: Missing_Original_Capture_Count | AI1: Original_Capture_Amount | AJ1: Refund_Amount_Check | AK1: Normalized_Order_Ref | AL1: Order_Match_Count | AN1: Order Matching Summary | AP1: Capture_Review_Status | AQ1: First_ID_Record | AR1: Refund_Reference_Check
A2: pay_420000065 | C2: ORD26000066 | D2: 46266 | E2: CAPTURE | F2: Wallet | G2: 6798 | H2: 163.15 | I2: 29.37 | J2: 6605.48 | K2: 46268 | L2: STL-20260903 | M2: =COUNTIF($A:$A,A2) -> 1 | N2: =COUNTIF(Orders!$A:$A,C2) -> 1 | O2: =COUNTIF(N2:N5753,0) -> 651 | P2: =COUNTIF(Orders!$H:$H,UPPER(SUBSTITUTE(TRIM(C2),"-",""))) -> 1 | Q2: =COUNTIF(P2:P5753,0) -> 8 | R2: =IF(E2="REFUND","Refund",IF(P2=0,"Unmatched Order Reference","Matched Order Reference")) -> Matched Order Reference | S2: =COUNTIFS($C$2:$C$5753,C2,$E$2:$E$5753,"CAPTURE") -> 1 | T2: Matched Order Reference | U2: =COUNTIF(R2:R5753,T2) -> 5501 | V2: {=IF(E2<>"CAPTURE",0,SUMPRODUCT((MDR_Rates!$A$2:$A$10=F2)*(G2>MDR_Rates!$B$2:$B$10)*((MDR_Rates!$C$2:$C$10="")+(G2<=MDR_Rates!$C$2:$C$10))*MDR_Rates!$D$2:$D$10))} -> 1.7 | W2: =IF(E2<>"CAPTURE",0,ROUND(G2*V2/100,2)) -> 115.57 | X2: =IF(E2<>"CAPTURE",0,ROUND(W2*18/100,2)) -> 20.8 | Y2: =IF(E2<>"CAPTURE",0,ROUND(H2-W2,2)) -> 47.58 | Z2: =IF(E2<>"CAPTURE",0,ROUND(I2-X2,2)) -> 8.57 | AA2: =COUNTIF(M2:M5753,">1") -> 20 | AB2: Total MDR Variance | AC2: =SUM(Y2:Y5753) -> 1004.42 | AD2: {=SUMPRODUCT((M2:M5753>1)/M2:M5753)} -> 10 | AF2: =COUNTIF($A:$A,"pay_420002554") -> 1 | AG2: =IF(E2<>"REFUND","",IF(COUNTIFS($A:$A,B2,$E:$E,"CAPTURE")=0,"Missing Original Capture","Original Capture Found")) | AH2: =COUNTIF(AG2:AG5753,"Missing Original Capture") -> 0 | AI2: =IF(E2="REFUND",_xlfn.MAXIFS($G:$G,$A:$A,B2,$E:$E,"CAPTURE"),"") | AJ2: =IF(E2<>"REFUND","",IF(G2>AI2,"Refund Exceeds Capture",IF(ABS(G2-AI2)<0.01,"Full Refund","Partial Refund"))) | AK2: =UPPER(SUBSTITUTE(TRIM(C2),"-","")) -> ORD26000066 | AL2: =IF(E2<>"CAPTURE","",COUNTIF(Orders!$H:$H,AK2)) -> 1 | AM2: =COUNTIF(E2:E5753,"REFUND") -> 243 | AN2: Capture rows matched to one order | AO2: =COUNTIFS($E$2:$E$5753,"CAPTURE",$AL$2:$AL$5753,1) -> 5501 | AP2: =IF(E2<>"CAPTURE","",IF(M2>1,"Duplicate ID - Review",IF(AL2=0,"Unmatched Order",IF(AL2=1,"Matched to Order","Multiple Order Matches")))) -> Matched to Order | AQ2: =IF(COUNTIF($A$2:A2,A2)=1,1,0) -> 1 | AR2: =COUNTIF($B:$B,"pay_420000300") -> 0
A3: pay_420000121 | C3: ORD-26000130 | D3: 46266 | E3: CAPTURE | F3: Card | G3: 11297 | H3: 180.75 | I3: 32.54 | J3: 11083.71 | K3: 46268 | L3: STL-20260903 | M3: =COUNTIF($A:$A,A3) -> 1 | N3: =COUNTIF(Orders!$A:$A,C3) -> 0 | P3: =COUNTIF(Orders!$H:$H,UPPER(SUBSTITUTE(TRIM(C3),"-",""))) -> 1 | R3: =IF(E3="REFUND","Refund",IF(P3=0,"Unmatched Order Reference","Matched Order Reference")) -> Matched Order Reference | S3: =COUNTIFS($C$2:$C$5753,C3,$E$2:$E$5753,"CAPTURE") -> 1 | T3: Unmatched Order Reference | U3: =COUNTIF(R2:R5753,T3) -> 8 | V3: {=IF(E3<>"CAPTURE",0,SUMPRODUCT((MDR_Rates!$A$2:$A$10=F3)*(G3>MDR_Rates!$B$2:$B$10)*((MDR_Rates!$C$2:$C$10="")+(G3<=MDR_Rates!$C$2:$C$10))*MDR_Rates!$D$2:$D$10))} -> 1.6 | W3: =IF(E3<>"CAPTURE",0,ROUND(G3*V3/100,2)) -> 180.75 | X3: =IF(E3<>"CAPTURE",0,ROUND(W3*18/100,2)) -> 32.54 | Y3: =IF(E3<>"CAPTURE",0,ROUND(H3-W3,2)) -> 0 | Z3: =IF(E3<>"CAPTURE",0,ROUND(I3-X3,2)) -> 0 | AB3: Total GST Variance | AC3: =SUM(Z2:Z5753) -> 180.78 | AF3: =COUNTIFS($A:$A,"pay_420002554",$E:$E,"CAPTURE") -> 1 | AG3: =IF(E3<>"REFUND","",IF(COUNTIFS($A:$A,B3,$E:$E,"CAPTURE")=0,"Missing Original Capture","Original Capture Found")) | AI3: =IF(E3="REFUND",_xlfn.MAXIFS($G:$G,$A:$A,B3,$E:$E,"CAPTURE"),"") | AJ3: =IF(E3<>"REFUND","",IF(G3>AI3,"Refund Exceeds Capture",IF(ABS(G3-AI3)<0.01,"Full Refund","Partial Refund"))) | AK3: =UPPER(SUBSTITUTE(TRIM(C3),"-","")) -> ORD26000130 | AL3: =IF(E3<>"CAPTURE","",COUNTIF(Orders!$H:$H,AK3)) -> 1 | AM3: =SUMIF(E2:E5753,"REFUND",G2:G5753) -> 893888 | AN3: Unmatched capture rows | AO3: =COUNTIFS($E$2:$E$5753,"CAPTURE",$AL$2:$AL$5753,0) -> 8 | AP3: =IF(E3<>"CAPTURE","",IF(M3>1,"Duplicate ID - Review",IF(AL3=0,"Unmatched Order",IF(AL3=1,"Matched to Order","Multiple Order Matches")))) -> Matched to Order | AQ3: =IF(COUNTIF($A$2:A3,A3)=1,1,0) -> 1
A4: pay_420000170 | C4: ORD26000184 | D4: 46266 | E4: CAPTURE | F4: Card | G4: 4999 | H4: 79.98 | I4: 14.4 | J4: 4904.62 | K4: 46268 | L4: STL-20260903 | M4: =COUNTIF($A:$A,A4) -> 1 | N4: =COUNTIF(Orders!$A:$A,C4) -> 1 | P4: =COUNTIF(Orders!$H:$H,UPPER(SUBSTITUTE(TRIM(C4),"-",""))) -> 1 | R4: =IF(E4="REFUND","Refund",IF(P4=0,"Unmatched Order Reference","Matched Order Reference")) -> Matched Order Reference | S4: =COUNTIFS($C$2:$C$5753,C4,$E$2:$E$5753,"CAPTURE") -> 1 | T4: Refund | U4: =COUNTIF(R2:R5753,T4) -> 243 | V4: {=IF(E4<>"CAPTURE",0,SUMPRODUCT((MDR_Rates!$A$2:$A$10=F4)*(G4>MDR_Rates!$B$2:$B$10)*((MDR_Rates!$C$2:$C$10="")+(G4<=MDR_Rates!$C$2:$C$10))*MDR_Rates!$D$2:$D$10))} -> 1.6 | W4: =IF(E4<>"CAPTURE",0,ROUND(G4*V4/100,2)) -> 79.98 | X4: =IF(E4<>"CAPTURE",0,ROUND(W4*18/100,2)) -> 14.4 | Y4: =IF(E4<>"CAPTURE",0,ROUND(H4-W4,2)) -> 0 | Z4: =IF(E4<>"CAPTURE",0,ROUND(I4-X4,2)) -> 0 | AF4: =SUMIFS($G:$G,$A:$A,"pay_420002554",$E:$E,"CAPTURE") -> 1799 | AG4: =IF(E4<>"REFUND","",IF(COUNTIFS($A:$A,B4,$E:$E,"CAPTURE")=0,"Missing Original Capture","Original Capture Found")) | AI4: =IF(E4="REFUND",_xlfn.MAXIFS($G:$G,$A:$A,B4,$E:$E,"CAPTURE"),"") | AJ4: =IF(E4<>"REFUND","",IF(G4>AI4,"Refund Exceeds Capture",IF(ABS(G4-AI4)<0.01,"Full Refund","Partial Refund"))) | AK4: =UPPER(SUBSTITUTE(TRIM(C4),"-","")) -> ORD26000184 | AL4: =IF(E4<>"CAPTURE","",COUNTIF(Orders!$H:$H,AK4)) -> 1 | AM4: =COUNTIF(AJ2:AJ5753,"Refund Exceeds Capture") -> 0 | AN4: Capture rows matching multiple orders | AO4: =COUNTIFS($E$2:$E$5753,"CAPTURE",$AL$2:$AL$5753,">1") -> 0 | AP4: =IF(E4<>"CAPTURE","",IF(M4>1,"Duplicate ID - Review",IF(AL4=0,"Unmatched Order",IF(AL4=1,"Matched to Order","Multiple Order Matches")))) -> Matched to Order | AQ4: =IF(COUNTIF($A$2:A4,A4)=1,1,0) -> 1
A5: pay_420000229 | C5: ORD26000244 | D5: 46266 | E5: CAPTURE | F5: Card | G5: 349 | H5: 6.28 | I5: 1.13 | J5: 341.59 | K5: 46268 | L5: STL-20260903 | M5: =COUNTIF($A:$A,A5) -> 1 | N5: =COUNTIF(Orders!$A:$A,C5) -> 1 | P5: =COUNTIF(Orders!$H:$H,UPPER(SUBSTITUTE(TRIM(C5),"-",""))) -> 1 | Q5: =COUNTIF(P2:P5753,0) -> 8 | R5: =IF(E5="REFUND","Refund",IF(P5=0,"Unmatched Order Reference","Matched Order Reference")) -> Matched Order Reference | S5: =COUNTIFS($C$2:$C$5753,C5,$E$2:$E$5753,"CAPTURE") -> 1 | V5: {=IF(E5<>"CAPTURE",0,SUMPRODUCT((MDR_Rates!$A$2:$A$10=F5)*(G5>MDR_Rates!$B$2:$B$10)*((MDR_Rates!$C$2:$C$10="")+(G5<=MDR_Rates!$C$2:$C$10))*MDR_Rates!$D$2:$D$10))} -> 1.8 | W5: =IF(E5<>"CAPTURE",0,ROUND(G5*V5/100,2)) -> 6.28 | X5: =IF(E5<>"CAPTURE",0,ROUND(W5*18/100,2)) -> 1.13 | Y5: =IF(E5<>"CAPTURE",0,ROUND(H5-W5,2)) -> 0 | Z5: =IF(E5<>"CAPTURE",0,ROUND(I5-X5,2)) -> 0 | AG5: =IF(E5<>"REFUND","",IF(COUNTIFS($A:$A,B5,$E:$E,"CAPTURE")=0,"Missing Original Capture","Original Capture Found")) | AI5: =IF(E5="REFUND",_xlfn.MAXIFS($G:$G,$A:$A,B5,$E:$E,"CAPTURE"),"") | AJ5: =IF(E5<>"REFUND","",IF(G5>AI5,"Refund Exceeds Capture",IF(ABS(G5-AI5)<0.01,"Full Refund","Partial Refund"))) | AK5: =UPPER(SUBSTITUTE(TRIM(C5),"-","")) -> ORD26000244 | AL5: =IF(E5<>"CAPTURE","",COUNTIF(Orders!$H:$H,AK5)) -> 1 | AP5: =IF(E5<>"CAPTURE","",IF(M5>1,"Duplicate ID - Review",IF(AL5=0,"Unmatched Order",IF(AL5=1,"Matched to Order","Multiple Order Matches")))) -> Matched to Order | AQ5: =IF(COUNTIF($A$2:A5,A5)=1,1,0) -> 1
A6: pay_420000236 | C6: ORD26000252 | D6: 46266 | E6: CAPTURE | F6: UPI | G6: 9498 | H6: 28.49 | I6: 5.13 | J6: 9464.38 | K6: 46268 | L6: STL-20260903 | M6: =COUNTIF($A:$A,A6) -> 1 | N6: =COUNTIF(Orders!$A:$A,C6) -> 1 | P6: =COUNTIF(Orders!$H:$H,UPPER(SUBSTITUTE(TRIM(C6),"-",""))) -> 1 | R6: =IF(E6="REFUND","Refund",IF(P6=0,"Unmatched Order Reference","Matched Order Reference")) -> Matched Order Reference | S6: =COUNTIFS($C$2:$C$5753,C6,$E$2:$E$5753,"CAPTURE") -> 1 | T6: Unmatched Gross Amount | U6: =SUMIF(P2:P5753,0,G2:G5753) -> 24992 | V6: {=IF(E6<>"CAPTURE",0,SUMPRODUCT((MDR_Rates!$A$2:$A$10=F6)*(G6>MDR_Rates!$B$2:$B$10)*((MDR_Rates!$C$2:$C$10="")+(G6<=MDR_Rates!$C$2:$C$10))*MDR_Rates!$D$2:$D$10))} -> 0.3 | W6: =IF(E6<>"CAPTURE",0,ROUND(G6*V6/100,2)) -> 28.49 | X6: =IF(E6<>"CAPTURE",0,ROUND(W6*18/100,2)) -> 5.13 | Y6: =IF(E6<>"CAPTURE",0,ROUND(H6-W6,2)) -> 0 | Z6: =IF(E6<>"CAPTURE",0,ROUND(I6-X6,2)) -> 0 | AG6: =IF(E6<>"REFUND","",IF(COUNTIFS($A:$A,B6,$E:$E,"CAPTURE")=0,"Missing Original Capture","Original Capture Found")) | AI6: =IF(E6="REFUND",_xlfn.MAXIFS($G:$G,$A:$A,B6,$E:$E,"CAPTURE"),"") | AJ6: =IF(E6<>"REFUND","",IF(G6>AI6,"Refund Exceeds Capture",IF(ABS(G6-AI6)<0.01,"Full Refund","Partial Refund"))) | AK6: =UPPER(SUBSTITUTE(TRIM(C6),"-","")) -> ORD26000252 | AL6: =IF(E6<>"CAPTURE","",COUNTIF(Orders!$H:$H,AK6)) -> 1 | AP6: =IF(E6<>"CAPTURE","",IF(M6>1,"Duplicate ID - Review",IF(AL6=0,"Unmatched Order",IF(AL6=1,"Matched to Order","Multiple Order Matches")))) -> Matched to Order | AQ6: =IF(COUNTIF($A$2:A6,A6)=1,1,0) -> 1
A7: pay_420000249 | C7: ORD26000266 | D7: 46266 | E7: CAPTURE | F7: Card | G7: 7999 | H7: 127.98 | I7: 23.04 | J7: 7847.98 | K7: 46268 | L7: STL-20260903 | M7: =COUNTIF($A:$A,A7) -> 1 | N7: =COUNTIF(Orders!$A:$A,C7) -> 1 | P7: =COUNTIF(Orders!$H:$H,UPPER(SUBSTITUTE(TRIM(C7),"-",""))) -> 1 | R7: =IF(E7="REFUND","Refund",IF(P7=0,"Unmatched Order Reference","Matched Order Reference")) -> Matched Order Reference | S7: =COUNTIFS($C$2:$C$5753,C7,$E$2:$E$5753,"CAPTURE") -> 1 | V7: {=IF(E7<>"CAPTURE",0,SUMPRODUCT((MDR_Rates!$A$2:$A$10=F7)*(G7>MDR_Rates!$B$2:$B$10)*((MDR_Rates!$C$2:$C$10="")+(G7<=MDR_Rates!$C$2:$C$10))*MDR_Rates!$D$2:$D$10))} -> 1.6 | W7: =IF(E7<>"CAPTURE",0,ROUND(G7*V7/100,2)) -> 127.98 | X7: =IF(E7<>"CAPTURE",0,ROUND(W7*18/100,2)) -> 23.04 | Y7: =IF(E7<>"CAPTURE",0,ROUND(H7-W7,2)) -> 0 | Z7: =IF(E7<>"CAPTURE",0,ROUND(I7-X7,2)) -> 0 | AG7: =IF(E7<>"REFUND","",IF(COUNTIFS($A:$A,B7,$E:$E,"CAPTURE")=0,"Missing Original Capture","Original Capture Found")) | AI7: =IF(E7="REFUND",_xlfn.MAXIFS($G:$G,$A:$A,B7,$E:$E,"CAPTURE"),"") | AJ7: =IF(E7<>"REFUND","",IF(G7>AI7,"Refund Exceeds Capture",IF(ABS(G7-AI7)<0.01,"Full Refund","Partial Refund"))) | AK7: =UPPER(SUBSTITUTE(TRIM(C7),"-","")) -> ORD26000266 | AL7: =IF(E7<>"CAPTURE","",COUNTIF(Orders!$H:$H,AK7)) -> 1 | AP7: =IF(E7<>"CAPTURE","",IF(M7>1,"Duplicate ID - Review",IF(AL7=0,"Unmatched Order",IF(AL7=1,"Matched to Order","Multiple Order Matches")))) -> Matched to Order | AQ7: =IF(COUNTIF($A$2:A7,A7)=1,1,0) -> 1
A8: pay_420000316 | C8: ORD26000331 | D8: 46266 | E8: CAPTURE | F8: Card | G8: 1299 | H8: 23.38 | I8: 4.21 | J8: 1271.41 | K8: 46268 | L8: STL-20260903 | M8: =COUNTIF($A:$A,A8) -> 1 | N8: =COUNTIF(Orders!$A:$A,C8) -> 1 | P8: =COUNTIF(Orders!$H:$H,UPPER(SUBSTITUTE(TRIM(C8),"-",""))) -> 1 | R8: =IF(E8="REFUND","Refund",IF(P8=0,"Unmatched Order Reference","Matched Order Reference")) -> Matched Order Reference | S8: =COUNTIFS($C$2:$C$5753,C8,$E$2:$E$5753,"CAPTURE") -> 1 | V8: {=IF(E8<>"CAPTURE",0,SUMPRODUCT((MDR_Rates!$A$2:$A$10=F8)*(G8>MDR_Rates!$B$2:$B$10)*((MDR_Rates!$C$2:$C$10="")+(G8<=MDR_Rates!$C$2:$C$10))*MDR_Rates!$D$2:$D$10))} -> 1.8 | W8: =IF(E8<>"CAPTURE",0,ROUND(G8*V8/100,2)) -> 23.38 | X8: =IF(E8<>"CAPTURE",0,ROUND(W8*18/100,2)) -> 4.21 | Y8: =IF(E8<>"CAPTURE",0,ROUND(H8-W8,2)) -> 0 | Z8: =IF(E8<>"CAPTURE",0,ROUND(I8-X8,2)) -> 0 | AG8: =IF(E8<>"REFUND","",IF(COUNTIFS($A:$A,B8,$E:$E,"CAPTURE")=0,"Missing Original Capture","Original Capture Found")) | AI8: =IF(E8="REFUND",_xlfn.MAXIFS($G:$G,$A:$A,B8,$E:$E,"CAPTURE"),"") | AJ8: =IF(E8<>"REFUND","",IF(G8>AI8,"Refund Exceeds Capture",IF(ABS(G8-AI8)<0.01,"Full Refund","Partial Refund"))) | AK8: =UPPER(SUBSTITUTE(TRIM(C8),"-","")) -> ORD26000331 | AL8: =IF(E8<>"CAPTURE","",COUNTIF(Orders!$H:$H,AK8)) -> 1 | AP8: =IF(E8<>"CAPTURE","",IF(M8>1,"Duplicate ID - Review",IF(AL8=0,"Unmatched Order",IF(AL8=1,"Matched to Order","Multiple Order Matches")))) -> Matched to Order | AQ8: =IF(COUNTIF($A$2:A8,A8)=1,1,0) -> 1
A9: pay_420000355 | C9: ORD26000373 | D9: 46266 | E9: CAPTURE | F9: UPI | G9: 1799 | H9: 0 | I9: 0 | J9: 1799 | K9: 46268 | L9: STL-20260903 | M9: =COUNTIF($A:$A,A9) -> 1 | N9: =COUNTIF(Orders!$A:$A,C9) -> 1 | P9: =COUNTIF(Orders!$H:$H,UPPER(SUBSTITUTE(TRIM(C9),"-",""))) -> 1 | R9: =IF(E9="REFUND","Refund",IF(P9=0,"Unmatched Order Reference","Matched Order Reference")) -> Matched Order Reference | S9: =COUNTIFS($C$2:$C$5753,C9,$E$2:$E$5753,"CAPTURE") -> 1 | V9: {=IF(E9<>"CAPTURE",0,SUMPRODUCT((MDR_Rates!$A$2:$A$10=F9)*(G9>MDR_Rates!$B$2:$B$10)*((MDR_Rates!$C$2:$C$10="")+(G9<=MDR_Rates!$C$2:$C$10))*MDR_Rates!$D$2:$D$10))} -> 0 | W9: =IF(E9<>"CAPTURE",0,ROUND(G9*V9/100,2)) -> 0 | X9: =IF(E9<>"CAPTURE",0,ROUND(W9*18/100,2)) -> 0 | Y9: =IF(E9<>"CAPTURE",0,ROUND(H9-W9,2)) -> 0 | Z9: =IF(E9<>"CAPTURE",0,ROUND(I9-X9,2)) -> 0 | AG9: =IF(E9<>"REFUND","",IF(COUNTIFS($A:$A,B9,$E:$E,"CAPTURE")=0,"Missing Original Capture","Original Capture Found")) | AI9: =IF(E9="REFUND",_xlfn.MAXIFS($G:$G,$A:$A,B9,$E:$E,"CAPTURE"),"") | AJ9: =IF(E9<>"REFUND","",IF(G9>AI9,"Refund Exceeds Capture",IF(ABS(G9-AI9)<0.01,"Full Refund","Partial Refund"))) | AK9: =UPPER(SUBSTITUTE(TRIM(C9),"-","")) -> ORD26000373 | AL9: =IF(E9<>"CAPTURE","",COUNTIF(Orders!$H:$H,AK9)) -> 1 | AP9: =IF(E9<>"CAPTURE","",IF(M9>1,"Duplicate ID - Review",IF(AL9=0,"Unmatched Order",IF(AL9=1,"Matched to Order","Multiple Order Matches")))) -> Matched to Order | AQ9: =IF(COUNTIF($A$2:A9,A9)=1,1,0) -> 1
A10: pay_420000357 | C10: ORD26000375 | D10: 46266 | E10: CAPTURE | F10: UPI | G10: 4298 | H10: 12.89 | I10: 2.32 | J10: 4282.79 | K10: 46268 | L10: STL-20260903 | M10: =COUNTIF($A:$A,A10) -> 1 | N10: =COUNTIF(Orders!$A:$A,C10) -> 1 | P10: =COUNTIF(Orders!$H:$H,UPPER(SUBSTITUTE(TRIM(C10),"-",""))) -> 1 | R10: =IF(E10="REFUND","Refund",IF(P10=0,"Unmatched Order Reference","Matched Order Reference")) -> Matched Order Reference | S10: =COUNTIFS($C$2:$C$5753,C10,$E$2:$E$5753,"CAPTURE") -> 1 | V10: {=IF(E10<>"CAPTURE",0,SUMPRODUCT((MDR_Rates!$A$2:$A$10=F10)*(G10>MDR_Rates!$B$2:$B$10)*((MDR_Rates!$C$2:$C$10="")+(G10<=MDR_Rates!$C$2:$C$10))*MDR_Rates!$D$2:$D$10))} -> 0.3 | W10: =IF(E10<>"CAPTURE",0,ROUND(G10*V10/100,2)) -> 12.89 | X10: =IF(E10<>"CAPTURE",0,ROUND(W10*18/100,2)) -> 2.32 | Y10: =IF(E10<>"CAPTURE",0,ROUND(H10-W10,2)) -> 0 | Z10: =IF(E10<>"CAPTURE",0,ROUND(I10-X10,2)) -> 0 | AG10: =IF(E10<>"REFUND","",IF(COUNTIFS($A:$A,B10,$E:$E,"CAPTURE")=0,"Missing Original Capture","Original Capture Found")) | AI10: =IF(E10="REFUND",_xlfn.MAXIFS($G:$G,$A:$A,B10,$E:$E,"CAPTURE"),"") | AJ10: =IF(E10<>"REFUND","",IF(G10>AI10,"Refund Exceeds Capture",IF(ABS(G10-AI10)<0.01,"Full Refund","Partial Refund"))) | AK10: =UPPER(SUBSTITUTE(TRIM(C10),"-","")) -> ORD26000375 | AL10: =IF(E10<>"CAPTURE","",COUNTIF(Orders!$H:$H,AK10)) -> 1 | AP10: =IF(E10<>"CAPTURE","",IF(M10>1,"Duplicate ID - Review",IF(AL10=0,"Unmatched Order",IF(AL10=1,"Matched to Order","Multiple Order Matches")))) -> Matched to Order | AQ10: =IF(COUNTIF($A$2:A10,A10)=1,1,0) -> 1
A11: pay_420000392 | C11: ORD26000410 | D11: 46266 | E11: CAPTURE | F11: Card | G11: 799 | H11: 14.38 | I11: 2.59 | J11: 782.03 | K11: 46268 | L11: STL-20260903 | M11: =COUNTIF($A:$A,A11) -> 1 | N11: =COUNTIF(Orders!$A:$A,C11) -> 1 | P11: =COUNTIF(Orders!$H:$H,UPPER(SUBSTITUTE(TRIM(C11),"-",""))) -> 1 | R11: =IF(E11="REFUND","Refund",IF(P11=0,"Unmatched Order Reference","Matched Order Reference")) -> Matched Order Reference | S11: =COUNTIFS($C$2:$C$5753,C11,$E$2:$E$5753,"CAPTURE") -> 1 | V11: {=IF(E11<>"CAPTURE",0,SUMPRODUCT((MDR_Rates!$A$2:$A$10=F11)*(G11>MDR_Rates!$B$2:$B$10)*((MDR_Rates!$C$2:$C$10="")+(G11<=MDR_Rates!$C$2:$C$10))*MDR_Rates!$D$2:$D$10))} -> 1.8 | W11: =IF(E11<>"CAPTURE",0,ROUND(G11*V11/100,2)) -> 14.38 | X11: =IF(E11<>"CAPTURE",0,ROUND(W11*18/100,2)) -> 2.59 | Y11: =IF(E11<>"CAPTURE",0,ROUND(H11-W11,2)) -> 0 | Z11: =IF(E11<>"CAPTURE",0,ROUND(I11-X11,2)) -> 0 | AG11: =IF(E11<>"REFUND","",IF(COUNTIFS($A:$A,B11,$E:$E,"CAPTURE")=0,"Missing Original Capture","Original Capture Found")) | AI11: =IF(E11="REFUND",_xlfn.MAXIFS($G:$G,$A:$A,B11,$E:$E,"CAPTURE"),"") | AJ11: =IF(E11<>"REFUND","",IF(G11>AI11,"Refund Exceeds Capture",IF(ABS(G11-AI11)<0.01,"Full Refund","Partial Refund"))) | AK11: =UPPER(SUBSTITUTE(TRIM(C11),"-","")) -> ORD26000410 | AL11: =IF(E11<>"CAPTURE","",COUNTIF(Orders!$H:$H,AK11)) -> 1 | AP11: =IF(E11<>"CAPTURE","",IF(M11>1,"Duplicate ID - Review",IF(AL11=0,"Unmatched Order",IF(AL11=1,"Matched to Order","Multiple Order Matches")))) -> Matched to Order | AQ11: =IF(COUNTIF($A$2:A11,A11)=1,1,0) -> 1
A12: pay_420000449 | C12: ORD26000470 | D12: 46266 | E12: CAPTURE | F12: Wallet | G12: 4297 | H12: 73.05 | I12: 13.15 | J12: 4210.8 | K12: 46268 | L12: STL-20260903 | M12: =COUNTIF($A:$A,A12) -> 1 | N12: =COUNTIF(Orders!$A:$A,C12) -> 1 | P12: =COUNTIF(Orders!$H:$H,UPPER(SUBSTITUTE(TRIM(C12),"-",""))) -> 1 | R12: =IF(E12="REFUND","Refund",IF(P12=0,"Unmatched Order Reference","Matched Order Reference")) -> Matched Order Reference | S12: =COUNTIFS($C$2:$C$5753,C12,$E$2:$E$5753,"CAPTURE") -> 1 | V12: {=IF(E12<>"CAPTURE",0,SUMPRODUCT((MDR_Rates!$A$2:$A$10=F12)*(G12>MDR_Rates!$B$2:$B$10)*((MDR_Rates!$C$2:$C$10="")+(G12<=MDR_Rates!$C$2:$C$10))*MDR_Rates!$D$2:$D$10))} -> 1.7 | W12: =IF(E12<>"CAPTURE",0,ROUND(G12*V12/100,2)) -> 73.05 | X12: =IF(E12<>"CAPTURE",0,ROUND(W12*18/100,2)) -> 13.15 | Y12: =IF(E12<>"CAPTURE",0,ROUND(H12-W12,2)) -> 0 | Z12: =IF(E12<>"CAPTURE",0,ROUND(I12-X12,2)) -> 0 | AG12: =IF(E12<>"REFUND","",IF(COUNTIFS($A:$A,B12,$E:$E,"CAPTURE")=0,"Missing Original Capture","Original Capture Found")) | AI12: =IF(E12="REFUND",_xlfn.MAXIFS($G:$G,$A:$A,B12,$E:$E,"CAPTURE"),"") | AJ12: =IF(E12<>"REFUND","",IF(G12>AI12,"Refund Exceeds Capture",IF(ABS(G12-AI12)<0.01,"Full Refund","Partial Refund"))) | AK12: =UPPER(SUBSTITUTE(TRIM(C12),"-","")) -> ORD26000470 | AL12: =IF(E12<>"CAPTURE","",COUNTIF(Orders!$H:$H,AK12)) -> 1 | AP12: =IF(E12<>"CAPTURE","",IF(M12>1,"Duplicate ID - Review",IF(AL12=0,"Unmatched Order",IF(AL12=1,"Matched to Order","Multiple Order Matches")))) -> Matched to Order | AQ12: =IF(COUNTIF($A$2:A12,A12)=1,1,0) -> 1
A13: pay_420000460 | C13: ORD26000483 | D13: 46266 | E13: CAPTURE | F13: Card | G13: 898 | H13: 16.16 | I13: 2.91 | J13: 878.93 | K13: 46268 | L13: STL-20260903 | M13: =COUNTIF($A:$A,A13) -> 1 | N13: =COUNTIF(Orders!$A:$A,C13) -> 1 | P13: =COUNTIF(Orders!$H:$H,UPPER(SUBSTITUTE(TRIM(C13),"-",""))) -> 1 | R13: =IF(E13="REFUND","Refund",IF(P13=0,"Unmatched Order Reference","Matched Order Reference")) -> Matched Order Reference | S13: =COUNTIFS($C$2:$C$5753,C13,$E$2:$E$5753,"CAPTURE") -> 1 | V13: {=IF(E13<>"CAPTURE",0,SUMPRODUCT((MDR_Rates!$A$2:$A$10=F13)*(G13>MDR_Rates!$B$2:$B$10)*((MDR_Rates!$C$2:$C$10="")+(G13<=MDR_Rates!$C$2:$C$10))*MDR_Rates!$D$2:$D$10))} -> 1.8 | W13: =IF(E13<>"CAPTURE",0,ROUND(G13*V13/100,2)) -> 16.16 | X13: =IF(E13<>"CAPTURE",0,ROUND(W13*18/100,2)) -> 2.91 | Y13: =IF(E13<>"CAPTURE",0,ROUND(H13-W13,2)) -> 0 | Z13: =IF(E13<>"CAPTURE",0,ROUND(I13-X13,2)) -> 0 | AG13: =IF(E13<>"REFUND","",IF(COUNTIFS($A:$A,B13,$E:$E,"CAPTURE")=0,"Missing Original Capture","Original Capture Found")) | AI13: =IF(E13="REFUND",_xlfn.MAXIFS($G:$G,$A:$A,B13,$E:$E,"CAPTURE"),"") | AJ13: =IF(E13<>"REFUND","",IF(G13>AI13,"Refund Exceeds Capture",IF(ABS(G13-AI13)<0.01,"Full Refund","Partial Refund"))) | AK13: =UPPER(SUBSTITUTE(TRIM(C13),"-","")) -> ORD26000483 | AL13: =IF(E13<>"CAPTURE","",COUNTIF(Orders!$H:$H,AK13)) -> 1 | AP13: =IF(E13<>"CAPTURE","",IF(M13>1,"Duplicate ID - Review",IF(AL13=0,"Unmatched Order",IF(AL13=1,"Matched to Order","Multiple Order Matches")))) -> Matched to Order | AQ13: =IF(COUNTIF($A$2:A13,A13)=1,1,0) -> 1
A14: pay_420000471 | C14: ORD26000494 | D14: 46266 | E14: CAPTURE | F14: Card | G14: 9498 | H14: 151.97 | I14: 27.35 | J14: 9318.68 | K14: 46268 | L14: STL-20260903 | M14: =COUNTIF($A:$A,A14) -> 1 | N14: =COUNTIF(Orders!$A:$A,C14) -> 1 | P14: =COUNTIF(Orders!$H:$H,UPPER(SUBSTITUTE(TRIM(C14),"-",""))) -> 1 | R14: =IF(E14="REFUND","Refund",IF(P14=0,"Unmatched Order Reference","Matched Order Reference")) -> Matched Order Reference | S14: =COUNTIFS($C$2:$C$5753,C14,$E$2:$E$5753,"CAPTURE") -> 1 | V14: {=IF(E14<>"CAPTURE",0,SUMPRODUCT((MDR_Rates!$A$2:$A$10=F14)*(G14>MDR_Rates!$B$2:$B$10)*((MDR_Rates!$C$2:$C$10="")+(G14<=MDR_Rates!$C$2:$C$10))*MDR_Rates!$D$2:$D$10))} -> 1.6 | W14: =IF(E14<>"CAPTURE",0,ROUND(G14*V14/100,2)) -> 151.97 | X14: =IF(E14<>"CAPTURE",0,ROUND(W14*18/100,2)) -> 27.35 | Y14: =IF(E14<>"CAPTURE",0,ROUND(H14-W14,2)) -> 0 | Z14: =IF(E14<>"CAPTURE",0,ROUND(I14-X14,2)) -> 0 | AG14: =IF(E14<>"REFUND","",IF(COUNTIFS($A:$A,B14,$E:$E,"CAPTURE")=0,"Missing Original Capture","Original Capture Found")) | AI14: =IF(E14="REFUND",_xlfn.MAXIFS($G:$G,$A:$A,B14,$E:$E,"CAPTURE"),"") | AJ14: =IF(E14<>"REFUND","",IF(G14>AI14,"Refund Exceeds Capture",IF(ABS(G14-AI14)<0.01,"Full Refund","Partial Refund"))) | AK14: =UPPER(SUBSTITUTE(TRIM(C14),"-","")) -> ORD26000494 | AL14: =IF(E14<>"CAPTURE","",COUNTIF(Orders!$H:$H,AK14)) -> 1 | AP14: =IF(E14<>"CAPTURE","",IF(M14>1,"Duplicate ID - Review",IF(AL14=0,"Unmatched Order",IF(AL14=1,"Matched to Order","Multiple Order Matches")))) -> Matched to Order | AQ14: =IF(COUNTIF($A$2:A14,A14)=1,1,0) -> 1
A15: pay_420000489 | C15: ORD26000512 | D15: 46266 | E15: CAPTURE | F15: Card | G15: 1798 | H15: 32.36 | I15: 5.82 | J15: 1759.82 | K15: 46268 | L15: STL-20260903 | M15: =COUNTIF($A:$A,A15) -> 1 | N15: =COUNTIF(Orders!$A:$A,C15) -> 1 | P15: =COUNTIF(Orders!$H:$H,UPPER(SUBSTITUTE(TRIM(C15),"-",""))) -> 1 | R15: =IF(E15="REFUND","Refund",IF(P15=0,"Unmatched Order Reference","Matched Order Reference")) -> Matched Order Reference | S15: =COUNTIFS($C$2:$C$5753,C15,$E$2:$E$5753,"CAPTURE") -> 1 | V15: {=IF(E15<>"CAPTURE",0,SUMPRODUCT((MDR_Rates!$A$2:$A$10=F15)*(G15>MDR_Rates!$B$2:$B$10)*((MDR_Rates!$C$2:$C$10="")+(G15<=MDR_Rates!$C$2:$C$10))*MDR_Rates!$D$2:$D$10))} -> 1.8 | W15: =IF(E15<>"CAPTURE",0,ROUND(G15*V15/100,2)) -> 32.36 | X15: =IF(E15<>"CAPTURE",0,ROUND(W15*18/100,2)) -> 5.82 | Y15: =IF(E15<>"CAPTURE",0,ROUND(H15-W15,2)) -> 0 | Z15: =IF(E15<>"CAPTURE",0,ROUND(I15-X15,2)) -> 0 | AG15: =IF(E15<>"REFUND","",IF(COUNTIFS($A:$A,B15,$E:$E,"CAPTURE")=0,"Missing Original Capture","Original Capture Found")) | AI15: =IF(E15="REFUND",_xlfn.MAXIFS($G:$G,$A:$A,B15,$E:$E,"CAPTURE"),"") | AJ15: =IF(E15<>"REFUND","",IF(G15>AI15,"Refund Exceeds Capture",IF(ABS(G15-AI15)<0.01,"Full Refund","Partial Refund"))) | AK15: =UPPER(SUBSTITUTE(TRIM(C15),"-","")) -> ORD26000512 | AL15: =IF(E15<>"CAPTURE","",COUNTIF(Orders!$H:$H,AK15)) -> 1 | AP15: =IF(E15<>"CAPTURE","",IF(M15>1,"Duplicate ID - Review",IF(AL15=0,"Unmatched Order",IF(AL15=1,"Matched to Order","Multiple Order Matches")))) -> Matched to Order | AQ15: =IF(COUNTIF($A$2:A15,A15)=1,1,0) -> 1
A16: pay_420000525 | C16: ORD26000550 | D16: 46266 | E16: CAPTURE | F16: UPI | G16: 7999 | H16: 24 | I16: 4.32 | J16: 7970.68 | K16: 46268 | L16: STL-20260903 | M16: =COUNTIF($A:$A,A16) -> 1 | N16: =COUNTIF(Orders!$A:$A,C16) -> 1 | P16: =COUNTIF(Orders!$H:$H,UPPER(SUBSTITUTE(TRIM(C16),"-",""))) -> 1 | R16: =IF(E16="REFUND","Refund",IF(P16=0,"Unmatched Order Reference","Matched Order Reference")) -> Matched Order Reference | S16: =COUNTIFS($C$2:$C$5753,C16,$E$2:$E$5753,"CAPTURE") -> 1 | V16: {=IF(E16<>"CAPTURE",0,SUMPRODUCT((MDR_Rates!$A$2:$A$10=F16)*(G16>MDR_Rates!$B$2:$B$10)*((MDR_Rates!$C$2:$C$10="")+(G16<=MDR_Rates!$C$2:$C$10))*MDR_Rates!$D$2:$D$10))} -> 0.3 | W16: =IF(E16<>"CAPTURE",0,ROUND(G16*V16/100,2)) -> 24 | X16: =IF(E16<>"CAPTURE",0,ROUND(W16*18/100,2)) -> 4.32 | Y16: =IF(E16<>"CAPTURE",0,ROUND(H16-W16,2)) -> 0 | Z16: =IF(E16<>"CAPTURE",0,ROUND(I16-X16,2)) -> 0 | AG16: =IF(E16<>"REFUND","",IF(COUNTIFS($A:$A,B16,$E:$E,"CAPTURE")=0,"Missing Original Capture","Original Capture Found")) | AI16: =IF(E16="REFUND",_xlfn.MAXIFS($G:$G,$A:$A,B16,$E:$E,"CAPTURE"),"") | AJ16: =IF(E16<>"REFUND","",IF(G16>AI16,"Refund Exceeds Capture",IF(ABS(G16-AI16)<0.01,"Full Refund","Partial Refund"))) | AK16: =UPPER(SUBSTITUTE(TRIM(C16),"-","")) -> ORD26000550 | AL16: =IF(E16<>"CAPTURE","",COUNTIF(Orders!$H:$H,AK16)) -> 1 | AP16: =IF(E16<>"CAPTURE","",IF(M16>1,"Duplicate ID - Review",IF(AL16=0,"Unmatched Order",IF(AL16=1,"Matched to Order","Multiple Order Matches")))) -> Matched to Order | AQ16: =IF(COUNTIF($A$2:A16,A16)=1,1,0) -> 1
A17: pay_420000584 | C17: ORD26000606 | D17: 46266 | E17: CAPTURE | F17: UPI | G17: 11997 | H17: 35.99 | I17: 6.48 | J17: 11954.53 | K17: 46268 | L17: STL-20260903 | M17: =COUNTIF($A:$A,A17) -> 1 | N17: =COUNTIF(Orders!$A:$A,C17) -> 1 | P17: =COUNTIF(Orders!$H:$H,UPPER(SUBSTITUTE(TRIM(C17),"-",""))) -> 1 | R17: =IF(E17="REFUND","Refund",IF(P17=0,"Unmatched Order Reference","Matched Order Reference")) -> Matched Order Reference | S17: =COUNTIFS($C$2:$C$5753,C17,$E$2:$E$5753,"CAPTURE") -> 1 | V17: {=IF(E17<>"CAPTURE",0,SUMPRODUCT((MDR_Rates!$A$2:$A$10=F17)*(G17>MDR_Rates!$B$2:$B$10)*((MDR_Rates!$C$2:$C$10="")+(G17<=MDR_Rates!$C$2:$C$10))*MDR_Rates!$D$2:$D$10))} -> 0.3 | W17: =IF(E17<>"CAPTURE",0,ROUND(G17*V17/100,2)) -> 35.99 | X17: =IF(E17<>"CAPTURE",0,ROUND(W17*18/100,2)) -> 6.48 | Y17: =IF(E17<>"CAPTURE",0,ROUND(H17-W17,2)) -> 0 | Z17: =IF(E17<>"CAPTURE",0,ROUND(I17-X17,2)) -> 0 | AG17: =IF(E17<>"REFUND","",IF(COUNTIFS($A:$A,B17,$E:$E,"CAPTURE")=0,"Missing Original Capture","Original Capture Found")) | AI17: =IF(E17="REFUND",_xlfn.MAXIFS($G:$G,$A:$A,B17,$E:$E,"CAPTURE"),"") | AJ17: =IF(E17<>"REFUND","",IF(G17>AI17,"Refund Exceeds Capture",IF(ABS(G17-AI17)<0.01,"Full Refund","Partial Refund"))) | AK17: =UPPER(SUBSTITUTE(TRIM(C17),"-","")) -> ORD26000606 | AL17: =IF(E17<>"CAPTURE","",COUNTIF(Orders!$H:$H,AK17)) -> 1 | AP17: =IF(E17<>"CAPTURE","",IF(M17>1,"Duplicate ID - Review",IF(AL17=0,"Unmatched Order",IF(AL17=1,"Matched to Order","Multiple Order Matches")))) -> Matched to Order | AQ17: =IF(COUNTIF($A$2:A17,A17)=1,1,0) -> 1
A18: pay_420000597 | C18: ORD26000619 | D18: 46266 | E18: CAPTURE | F18: Wallet | G18: 999 | H18: 18.98 | I18: 3.42 | J18: 976.6 | K18: 46268 | L18: STL-20260903 | M18: =COUNTIF($A:$A,A18) -> 1 | N18: =COUNTIF(Orders!$A:$A,C18) -> 1 | P18: =COUNTIF(Orders!$H:$H,UPPER(SUBSTITUTE(TRIM(C18),"-",""))) -> 1 | R18: =IF(E18="REFUND","Refund",IF(P18=0,"Unmatched Order Reference","Matched Order Reference")) -> Matched Order Reference | S18: =COUNTIFS($C$2:$C$5753,C18,$E$2:$E$5753,"CAPTURE") -> 1 | V18: {=IF(E18<>"CAPTURE",0,SUMPRODUCT((MDR_Rates!$A$2:$A$10=F18)*(G18>MDR_Rates!$B$2:$B$10)*((MDR_Rates!$C$2:$C$10="")+(G18<=MDR_Rates!$C$2:$C$10))*MDR_Rates!$D$2:$D$10))} -> 1.9 | W18: =IF(E18<>"CAPTURE",0,ROUND(G18*V18/100,2)) -> 18.98 | X18: =IF(E18<>"CAPTURE",0,ROUND(W18*18/100,2)) -> 3.42 | Y18: =IF(E18<>"CAPTURE",0,ROUND(H18-W18,2)) -> 0 | Z18: =IF(E18<>"CAPTURE",0,ROUND(I18-X18,2)) -> 0 | AG18: =IF(E18<>"REFUND","",IF(COUNTIFS($A:$A,B18,$E:$E,"CAPTURE")=0,"Missing Original Capture","Original Capture Found")) | AI18: =IF(E18="REFUND",_xlfn.MAXIFS($G:$G,$A:$A,B18,$E:$E,"CAPTURE"),"") | AJ18: =IF(E18<>"REFUND","",IF(G18>AI18,"Refund Exceeds Capture",IF(ABS(G18-AI18)<0.01,"Full Refund","Partial Refund"))) | AK18: =UPPER(SUBSTITUTE(TRIM(C18),"-","")) -> ORD26000619 | AL18: =IF(E18<>"CAPTURE","",COUNTIF(Orders!$H:$H,AK18)) -> 1 | AP18: =IF(E18<>"CAPTURE","",IF(M18>1,"Duplicate ID - Review",IF(AL18=0,"Unmatched Order",IF(AL18=1,"Matched to Order","Multiple Order Matches")))) -> Matched to Order | AQ18: =IF(COUNTIF($A$2:A18,A18)=1,1,0) -> 1
... A329: pay_420005677 | C329: ORD26005942 | D329: 46267 | E329: CAPTURE | F329: Wallet | G329: 1499 | H329: 28.48 | I329: 5.13 | J329: 1465.39 | K329: 46269 | L329: STL-20260904 | M329: =COUNTIF($A:$A,A329) -> 1 | N329: =COUNTIF(Orders!$A:$A,C329) -> 1 | P329: =COUNTIF(Orders!$H:$H,UPPER(SUBSTITUTE(TRIM(C329),"-",""))) -> 1 | R329: =IF(E329="REFUND","Refund",IF(P329=0,"Unmatched Order Reference","Matched Order Reference")) -> Matched Order Reference | S329: =COUNTIFS($C$2:$C$5753,C329,$E$2:$E$5753,"CAPTURE") -> 1 | V329: {=IF(E329<>"CAPTURE",0,SUMPRODUCT((MDR_Rates!$A$2:$A$10=F329)*(G329>MDR_Rates!$B$2:$B$10)*((MDR_Rates!$C$2:$C$10="")+(G329<=MDR_Rates!$C$2:$C$10))*MDR_Rates!$D$2:$D$10))} -> 1.9 | W329: =IF(E329<>"CAPTURE",0,ROUND(G329*V329/100,2)) -> 28.48 | X329: =IF(E329<>"CAPTURE",0,ROUND(W329*18/100,2)) -> 5.13 | Y329: =IF(E329<>"CAPTURE",0,ROUND(H329-W329,2)) -> 0 | Z329: =IF(E329<>"CAPTURE",0,ROUND(I329-X329,2)) -> 0 | AG329: =IF(E329<>"REFUND","",IF(COUNTIFS($A:$A,B329,$E:$E,"CAPTURE")=0,"Missing Original Capture","Original Capture Found")) | AI329: =IF(E329="REFUND",_xlfn.MAXIFS($G:$G,$A:$A,B329,$E:$E,"CAPTURE"),"") | AJ329: =IF(E329<>"REFUND","",IF(G329>AI329,"Refund Exceeds Capture",IF(ABS(G329-AI329)<0.01,"Full Refund","Partial Refund"))) | AK329: =UPPER(SUBSTITUTE(TRIM(C329),"-","")) -> ORD26005942 | AL329: =IF(E329<>"CAPTURE","",COUNTIF(Orders!$H:$H,AK329)) -> 1 | AP329: =IF(E329<>"CAPTURE","",IF(M329>1,"Duplicate ID - Review",IF(AL329=0,"Unmatched Order",IF(AL329=1,"Matched to Order","Multiple Order Matches")))) -> Matched to Order | AQ329: =IF(COUNTIF($A$2:A329,A329)=1,1,0) -> 1
A330: rfnd_BDDX8L3AAXM0 | B330: pay_420002554 | D330: 46267 | E330: REFUND | F330: Wallet | G330: 1799 | H330: 0 | I330: 0 | J330: -1799 | K330: 46269 | L330: STL-20260904 | M330: =COUNTIF($A:$A,A330) -> 1 | N330: =COUNTIF(Orders!$A:$A,C330) -> 0 | P330: =COUNTIF(Orders!$H:$H,UPPER(SUBSTITUTE(TRIM(C330),"-",""))) -> 1042575 | R330: =IF(E330="REFUND","Refund",IF(P330=0,"Unmatched Order Reference","Matched Order Reference")) -> Refund | S330: =COUNTIFS($C$2:$C$5753,C330,$E$2:$E$5753,"CAPTURE") -> 0 | V330: {=IF(E330<>"CAPTURE",0,SUMPRODUCT((MDR_Rates!$A$2:$A$10=F330)*(G330>MDR_Rates!$B$2:$B$10)*((MDR_Rates!$C$2:$C$10="")+(G330<=MDR_Rates!$C$2:$C$10))*MDR_Rates!$D$2:$D$10))} -> 0 | W330: =IF(E330<>"CAPTURE",0,ROUND(G330*V330/100,2)) -> 0 | X330: =IF(E330<>"CAPTURE",0,ROUND(W330*18/100,2)) -> 0 | Y330: =IF(E330<>"CAPTURE",0,ROUND(H330-W330,2)) -> 0 | Z330: =IF(E330<>"CAPTURE",0,ROUND(I330-X330,2)) -> 0 | AG330: =IF(E330<>"REFUND","",IF(COUNTIFS($A:$A,B330,$E:$E,"CAPTURE")=0,"Missing Original Capture","Original Capture Found")) -> Original Capture Found | AI330: =IF(E330="REFUND",_xlfn.MAXIFS($G:$G,$A:$A,B330,$E:$E,"CAPTURE"),"") -> 1799 | AJ330: =IF(E330<>"REFUND","",IF(G330>AI330,"Refund Exceeds Capture",IF(ABS(G330-AI330)<0.01,"Full Refund","Partial Refund"))) -> Full Refund | AK330: =UPPER(SUBSTITUTE(TRIM(C330),"-","")) | AL330: =IF(E330<>"CAPTURE","",COUNTIF(Orders!$H:$H,AK330)) | AP330: =IF(E330<>"CAPTURE","",IF(M330>1,"Duplicate ID - Review",IF(AL330=0,"Unmatched Order",IF(AL330=1,"Matched to Order","Multiple Order Matches")))) | AQ330: =IF(COUNTIF($A$2:A330,A330)=1,1,0) -> 1
A331: rfnd_W6UU5WJWSTPB | B331: pay_420004896 | D331: 46267 | E331: REFUND | F331: NetBanking | G331: 599 | H331: 0 | I331: 0 | J331: -599 | K331: 46269 | L331: STL-20260904 | M331: =COUNTIF($A:$A,A331) -> 1 | N331: =COUNTIF(Orders!$A:$A,C331) -> 0 | P331: =COUNTIF(Orders!$H:$H,UPPER(SUBSTITUTE(TRIM(C331),"-",""))) -> 1042575 | R331: =IF(E331="REFUND","Refund",IF(P331=0,"Unmatched Order Reference","Matched Order Reference")) -> Refund | S331: =COUNTIFS($C$2:$C$5753,C331,$E$2:$E$5753,"CAPTURE") -> 0 | V331: {=IF(E331<>"CAPTURE",0,SUMPRODUCT((MDR_Rates!$A$2:$A$10=F331)*(G331>MDR_Rates!$B$2:$B$10)*((MDR_Rates!$C$2:$C$10="")+(G331<=MDR_Rates!$C$2:$C$10))*MDR_Rates!$D$2:$D$10))} -> 0 | W331: =IF(E331<>"CAPTURE",0,ROUND(G331*V331/100,2)) -> 0 | X331: =IF(E331<>"CAPTURE",0,ROUND(W331*18/100,2)) -> 0 | Y331: =IF(E331<>"CAPTURE",0,ROUND(H331-W331,2)) -> 0 | Z331: =IF(E331<>"CAPTURE",0,ROUND(I331-X331,2)) -> 0 | AG331: =IF(E331<>"REFUND","",IF(COUNTIFS($A:$A,B331,$E:$E,"CAPTURE")=0,"Missing Original Capture","Original Capture Found")) -> Original Capture Found | AI331: =IF(E331="REFUND",_xlfn.MAXIFS($G:$G,$A:$A,B331,$E:$E,"CAPTURE"),"") -> 599 | AJ331: =IF(E331<>"REFUND","",IF(G331>AI331,"Refund Exceeds Capture",IF(ABS(G331-AI331)<0.01,"Full Refund","Partial Refund"))) -> Full Refund | AK331: =UPPER(SUBSTITUTE(TRIM(C331),"-","")) | AL331: =IF(E331<>"CAPTURE","",COUNTIF(Orders!$H:$H,AK331)) | AP331: =IF(E331<>"CAPTURE","",IF(M331>1,"Duplicate ID - Review",IF(AL331=0,"Unmatched Order",IF(AL331=1,"Matched to Order","Multiple Order Matches")))) | AQ331: =IF(COUNTIF($A$2:A331,A331)=1,1,0) -> 1
A332: pay_420000041 | C332: ORD26000042 | D332: 46268 | E332: CAPTURE | F332: Card | G332: 349 | H332: 6.28 | I332: 1.13 | J332: 341.59 | K332: 46270 | L332: STL-20260905 | M332: =COUNTIF($A:$A,A332) -> 1 | N332: =COUNTIF(Orders!$A:$A,C332) -> 1 | P332: =COUNTIF(Orders!$H:$H,UPPER(SUBSTITUTE(TRIM(C332),"-",""))) -> 1 | R332: =IF(E332="REFUND","Refund",IF(P332=0,"Unmatched Order Reference","Matched Order Reference")) -> Matched Order Reference | S332: =COUNTIFS($C$2:$C$5753,C332,$E$2:$E$5753,"CAPTURE") -> 1 | V332: {=IF(E332<>"CAPTURE",0,SUMPRODUCT((MDR_Rates!$A$2:$A$10=F332)*(G332>MDR_Rates!$B$2:$B$10)*((MDR_Rates!$C$2:$C$10="")+(G332<=MDR_Rates!$C$2:$C$10))*MDR_Rates!$D$2:$D$10))} -> 1.8 | W332: =IF(E332<>"CAPTURE",0,ROUND(G332*V332/100,2)) -> 6.28 | X332: =IF(E332<>"CAPTURE",0,ROUND(W332*18/100,2)) -> 1.13 | Y332: =IF(E332<>"CAPTURE",0,ROUND(H332-W332,2)) -> 0 | Z332: =IF(E332<>"CAPTURE",0,ROUND(I332-X332,2)) -> 0 | AG332: =IF(E332<>"REFUND","",IF(COUNTIFS($A:$A,B332,$E:$E,"CAPTURE")=0,"Missing Original Capture","Original Capture Found")) | AI332: =IF(E332="REFUND",_xlfn.MAXIFS($G:$G,$A:$A,B332,$E:$E,"CAPTURE"),"") | AJ332: =IF(E332<>"REFUND","",IF(G332>AI332,"Refund Exceeds Capture",IF(ABS(G332-AI332)<0.01,"Full Refund","Partial Refund"))) | AK332: =UPPER(SUBSTITUTE(TRIM(C332),"-","")) -> ORD26000042 | AL332: =IF(E332<>"CAPTURE","",COUNTIF(Orders!$H:$H,AK332)) -> 1 | AP332: =IF(E332<>"CAPTURE","",IF(M332>1,"Duplicate ID - Review",IF(AL332=0,"Unmatched Order",IF(AL332=1,"Matched to Order","Multiple Order Matches")))) -> Matched to Order | AQ332: =IF(COUNTIF($A$2:A332,A332)=1,1,0) -> 1
A333: pay_420000078 | C333: ORD26000082 | D333: 46268 | E333: CAPTURE | F333: Wallet | G333: 2197 | H333: 37.35 | I333: 6.72 | J333: 2152.93 | K333: 46270 | L333: STL-20260905 | M333: =COUNTIF($A:$A,A333) -> 1 | N333: =COUNTIF(Orders!$A:$A,C333) -> 1 | P333: =COUNTIF(Orders!$H:$H,UPPER(SUBSTITUTE(TRIM(C333),"-",""))) -> 1 | R333: =IF(E333="REFUND","Refund",IF(P333=0,"Unmatched Order Reference","Matched Order Reference")) -> Matched Order Reference | S333: =COUNTIFS($C$2:$C$5753,C333,$E$2:$E$5753,"CAPTURE") -> 1 | V333: {=IF(E333<>"CAPTURE",0,SUMPRODUCT((MDR_Rates!$A$2:$A$10=F333)*(G333>MDR_Rates!$B$2:$B$10)*((MDR_Rates!$C$2:$C$10="")+(G333<=MDR_Rates!$C$2:$C$10))*MDR_Rates!$D$2:$D$10))} -> 1.7 | W333: =IF(E333<>"CAPTURE",0,ROUND(G333*V333/100,2)) -> 37.35 | X333: =IF(E333<>"CAPTURE",0,ROUND(W333*18/100,2)) -> 6.72 | Y333: =IF(E333<>"CAPTURE",0,ROUND(H333-W333,2)) -> 0 | Z333: =IF(E333<>"CAPTURE",0,ROUND(I333-X333,2)) -> 0 | AG333: =IF(E333<>"REFUND","",IF(COUNTIFS($A:$A,B333,$E:$E,"CAPTURE")=0,"Missing Original Capture","Original Capture Found")) | AI333: =IF(E333="REFUND",_xlfn.MAXIFS($G:$G,$A:$A,B333,$E:$E,"CAPTURE"),"") | AJ333: =IF(E333<>"REFUND","",IF(G333>AI333,"Refund Exceeds Capture",IF(ABS(G333-AI333)<0.01,"Full Refund","Partial Refund"))) | AK333: =UPPER(SUBSTITUTE(TRIM(C333),"-","")) -> ORD26000082 | AL333: =IF(E333<>"CAPTURE","",COUNTIF(Orders!$H:$H,AK333)) -> 1 | AP333: =IF(E333<>"CAPTURE","",IF(M333>1,"Duplicate ID - Review",IF(AL333=0,"Unmatched Order",IF(AL333=1,"Matched to Order","Multiple Order Matches")))) -> Matched to Order | AQ333: =IF(COUNTIF($A$2:A333,A333)=1,1,0) -> 1
A334: pay_420000101 | C334: ORD26000109 | D334: 46268 | E334: CAPTURE | F334: UPI | G334: 599 | H334: 0 | I334: 0 | J334: 599 | K334: 46270 | L334: STL-20260905 | M334: =COUNTIF($A:$A,A334) -> 1 | N334: =COUNTIF(Orders!$A:$A,C334) -> 1 | P334: =COUNTIF(Orders!$H:$H,UPPER(SUBSTITUTE(TRIM(C334),"-",""))) -> 1 | R334: =IF(E334="REFUND","Refund",IF(P334=0,"Unmatched Order Reference","Matched Order Reference")) -> Matched Order Reference | S334: =COUNTIFS($C$2:$C$5753,C334,$E$2:$E$5753,"CAPTURE") -> 1 | V334: {=IF(E334<>"CAPTURE",0,SUMPRODUCT((MDR_Rates!$A$2:$A$10=F334)*(G334>MDR_Rates!$B$2:$B$10)*((MDR_Rates!$C$2:$C$10="")+(G334<=MDR_Rates!$C$2:$C$10))*MDR_Rates!$D$2:$D$10))} -> 0 | W334: =IF(E334<>"CAPTURE",0,ROUND(G334*V334/100,2)) -> 0 | X334: =IF(E334<>"CAPTURE",0,ROUND(W334*18/100,2)) -> 0 | Y334: =IF(E334<>"CAPTURE",0,ROUND(H334-W334,2)) -> 0 | Z334: =IF(E334<>"CAPTURE",0,ROUND(I334-X334,2)) -> 0 | AG334: =IF(E334<>"REFUND","",IF(COUNTIFS($A:$A,B334,$E:$E,"CAPTURE")=0,"Missing Original Capture","Original Capture Found")) | AI334: =IF(E334="REFUND",_xlfn.MAXIFS($G:$G,$A:$A,B334,$E:$E,"CAPTURE"),"") | AJ334: =IF(E334<>"REFUND","",IF(G334>AI334,"Refund Exceeds Capture",IF(ABS(G334-AI334)<0.01,"Full Refund","Partial Refund"))) | AK334: =UPPER(SUBSTITUTE(TRIM(C334),"-","")) -> ORD26000109 | AL334: =IF(E334<>"CAPTURE","",COUNTIF(Orders!$H:$H,AK334)) -> 1 | AP334: =IF(E334<>"CAPTURE","",IF(M334>1,"Duplicate ID - Review",IF(AL334=0,"Unmatched Order",IF(AL334=1,"Matched to Order","Multiple Order Matches")))) -> Matched to Order | AQ334: =IF(COUNTIF($A$2:A334,A334)=1,1,0) -> 1
A335: pay_420000111 | C335: ORD26000119 | D335: 46268 | E335: CAPTURE | F335: UPI | G335: 349 | H335: 0 | I335: 0 | J335: 349 | K335: 46270 | L335: STL-20260905 | M335: =COUNTIF($A:$A,A335) -> 1 | N335: =COUNTIF(Orders!$A:$A,C335) -> 1 | P335: =COUNTIF(Orders!$H:$H,UPPER(SUBSTITUTE(TRIM(C335),"-",""))) -> 1 | R335: =IF(E335="REFUND","Refund",IF(P335=0,"Unmatched Order Reference","Matched Order Reference")) -> Matched Order Reference | S335: =COUNTIFS($C$2:$C$5753,C335,$E$2:$E$5753,"CAPTURE") -> 1 | V335: {=IF(E335<>"CAPTURE",0,SUMPRODUCT((MDR_Rates!$A$2:$A$10=F335)*(G335>MDR_Rates!$B$2:$B$10)*((MDR_Rates!$C$2:$C$10="")+(G335<=MDR_Rates!$C$2:$C$10))*MDR_Rates!$D$2:$D$10))} -> 0 | W335: =IF(E335<>"CAPTURE",0,ROUND(G335*V335/100,2)) -> 0 | X335: =IF(E335<>"CAPTURE",0,ROUND(W335*18/100,2)) -> 0 | Y335: =IF(E335<>"CAPTURE",0,ROUND(H335-W335,2)) -> 0 | Z335: =IF(E335<>"CAPTURE",0,ROUND(I335-X335,2)) -> 0 | AG335: =IF(E335<>"REFUND","",IF(COUNTIFS($A:$A,B335,$E:$E,"CAPTURE")=0,"Missing Original Capture","Original Capture Found")) | AI335: =IF(E335="REFUND",_xlfn.MAXIFS($G:$G,$A:$A,B335,$E:$E,"CAPTURE"),"") | AJ335: =IF(E335<>"REFUND","",IF(G335>AI335,"Refund Exceeds Capture",IF(ABS(G335-AI335)<0.01,"Full Refund","Partial Refund"))) | AK335: =UPPER(SUBSTITUTE(TRIM(C335),"-","")) -> ORD26000119 | AL335: =IF(E335<>"CAPTURE","",COUNTIF(Orders!$H:$H,AK335)) -> 1 | AP335: =IF(E335<>"CAPTURE","",IF(M335>1,"Duplicate ID - Review",IF(AL335=0,"Unmatched Order",IF(AL335=1,"Matched to Order","Multiple Order Matches")))) -> Matched to Order | AQ335: =IF(COUNTIF($A$2:A335,A335)=1,1,0) -> 1
A336: pay_420000115 | C336: ORD26000124 | D336: 46268 | E336: CAPTURE | F336: Card | G336: 6397 | H336: 102.35 | I336: 18.42 | J336: 6276.23 | K336: 46270 | L336: STL-20260905 | M336: =COUNTIF($A:$A,A336) -> 1 | N336: =COUNTIF(Orders!$A:$A,C336) -> 1 | P336: =COUNTIF(Orders!$H:$H,UPPER(SUBSTITUTE(TRIM(C336),"-",""))) -> 1 | R336: =IF(E336="REFUND","Refund",IF(P336=0,"Unmatched Order Reference","Matched Order Reference")) -> Matched Order Reference | S336: =COUNTIFS($C$2:$C$5753,C336,$E$2:$E$5753,"CAPTURE") -> 1 | V336: {=IF(E336<>"CAPTURE",0,SUMPRODUCT((MDR_Rates!$A$2:$A$10=F336)*(G336>MDR_Rates!$B$2:$B$10)*((MDR_Rates!$C$2:$C$10="")+(G336<=MDR_Rates!$C$2:$C$10))*MDR_Rates!$D$2:$D$10))} -> 1.6 | W336: =IF(E336<>"CAPTURE",0,ROUND(G336*V336/100,2)) -> 102.35 | X336: =IF(E336<>"CAPTURE",0,ROUND(W336*18/100,2)) -> 18.42 | Y336: =IF(E336<>"CAPTURE",0,ROUND(H336-W336,2)) -> 0 | Z336: =IF(E336<>"CAPTURE",0,ROUND(I336-X336,2)) -> 0 | AG336: =IF(E336<>"REFUND","",IF(COUNTIFS($A:$A,B336,$E:$E,"CAPTURE")=0,"Missing Original Capture","Original Capture Found")) | AI336: =IF(E336="REFUND",_xlfn.MAXIFS($G:$G,$A:$A,B336,$E:$E,"CAPTURE"),"") | AJ336: =IF(E336<>"REFUND","",IF(G336>AI336,"Refund Exceeds Capture",IF(ABS(G336-AI336)<0.01,"Full Refund","Partial Refund"))) | AK336: =UPPER(SUBSTITUTE(TRIM(C336),"-","")) -> ORD26000124 | AL336: =IF(E336<>"CAPTURE","",COUNTIF(Orders!$H:$H,AK336)) -> 1 | AP336: =IF(E336<>"CAPTURE","",IF(M336>1,"Duplicate ID - Review",IF(AL336=0,"Unmatched Order",IF(AL336=1,"Matched to Order","Multiple Order Matches")))) -> Matched to Order | AQ336: =IF(COUNTIF($A$2:A336,A336)=1,1,0) -> 1
A337: pay_420000228 | C337: ORD26000243 | D337: 46268 | E337: CAPTURE | F337: Wallet | G337: 2798 | H337: 47.57 | I337: 8.56 | J337: 2741.87 | K337: 46270 | L337: STL-20260905 | M337: =COUNTIF($A:$A,A337) -> 1 | N337: =COUNTIF(Orders!$A:$A,C337) -> 1 | P337: =COUNTIF(Orders!$H:$H,UPPER(SUBSTITUTE(TRIM(C337),"-",""))) -> 1 | R337: =IF(E337="REFUND","Refund",IF(P337=0,"Unmatched Order Reference","Matched Order Reference")) -> Matched Order Reference | S337: =COUNTIFS($C$2:$C$5753,C337,$E$2:$E$5753,"CAPTURE") -> 1 | V337: {=IF(E337<>"CAPTURE",0,SUMPRODUCT((MDR_Rates!$A$2:$A$10=F337)*(G337>MDR_Rates!$B$2:$B$10)*((MDR_Rates!$C$2:$C$10="")+(G337<=MDR_Rates!$C$2:$C$10))*MDR_Rates!$D$2:$D$10))} -> 1.7 | W337: =IF(E337<>"CAPTURE",0,ROUND(G337*V337/100,2)) -> 47.57 | X337: =IF(E337<>"CAPTURE",0,ROUND(W337*18/100,2)) -> 8.56 | Y337: =IF(E337<>"CAPTURE",0,ROUND(H337-W337,2)) -> 0 | Z337: =IF(E337<>"CAPTURE",0,ROUND(I337-X337,2)) -> 0 | AG337: =IF(E337<>"REFUND","",IF(COUNTIFS($A:$A,B337,$E:$E,"CAPTURE")=0,"Missing Original Capture","Original Capture Found")) | AI337: =IF(E337="REFUND",_xlfn.MAXIFS($G:$G,$A:$A,B337,$E:$E,"CAPTURE"),"") | AJ337: =IF(E337<>"REFUND","",IF(G337>AI337,"Refund Exceeds Capture",IF(ABS(G337-AI337)<0.01,"Full Refund","Partial Refund"))) | AK337: =UPPER(SUBSTITUTE(TRIM(C337),"-","")) -> ORD26000243 | AL337: =IF(E337<>"CAPTURE","",COUNTIF(Orders!$H:$H,AK337)) -> 1 | AP337: =IF(E337<>"CAPTURE","",IF(M337>1,"Duplicate ID - Review",IF(AL337=0,"Unmatched Order",IF(AL337=1,"Matched to Order","Multiple Order Matches")))) -> Matched to Order | AQ337: =IF(COUNTIF($A$2:A337,A337)=1,1,0) -> 1
A338: pay_420000250 | C338: ORD26000267 | D338: 46268 | E338: CAPTURE | F338: UPI | G338: 4999 | H338: 15 | I338: 2.7 | J338: 4981.3 | K338: 46270 | L338: STL-20260905 | M338: =COUNTIF($A:$A,A338) -> 1 | N338: =COUNTIF(Orders!$A:$A,C338) -> 1 | P338: =COUNTIF(Orders!$H:$H,UPPER(SUBSTITUTE(TRIM(C338),"-",""))) -> 1 | R338: =IF(E338="REFUND","Refund",IF(P338=0,"Unmatched Order Reference","Matched Order Reference")) -> Matched Order Reference | S338: =COUNTIFS($C$2:$C$5753,C338,$E$2:$E$5753,"CAPTURE") -> 1 | V338: {=IF(E338<>"CAPTURE",0,SUMPRODUCT((MDR_Rates!$A$2:$A$10=F338)*(G338>MDR_Rates!$B$2:$B$10)*((MDR_Rates!$C$2:$C$10="")+(G338<=MDR_Rates!$C$2:$C$10))*MDR_Rates!$D$2:$D$10))} -> 0.3 | W338: =IF(E338<>"CAPTURE",0,ROUND(G338*V338/100,2)) -> 15 | X338: =IF(E338<>"CAPTURE",0,ROUND(W338*18/100,2)) -> 2.7 | Y338: =IF(E338<>"CAPTURE",0,ROUND(H338-W338,2)) -> 0 | Z338: =IF(E338<>"CAPTURE",0,ROUND(I338-X338,2)) -> 0 | AG338: =IF(E338<>"REFUND","",IF(COUNTIFS($A:$A,B338,$E:$E,"CAPTURE")=0,"Missing Original Capture","Original Capture Found")) | AI338: =IF(E338="REFUND",_xlfn.MAXIFS($G:$G,$A:$A,B338,$E:$E,"CAPTURE"),"") | AJ338: =IF(E338<>"REFUND","",IF(G338>AI338,"Refund Exceeds Capture",IF(ABS(G338-AI338)<0.01,"Full Refund","Partial Refund"))) | AK338: =UPPER(SUBSTITUTE(TRIM(C338),"-","")) -> ORD26000267 | AL338: =IF(E338<>"CAPTURE","",COUNTIF(Orders!$H:$H,AK338)) -> 1 | AP338: =IF(E338<>"CAPTURE","",IF(M338>1,"Duplicate ID - Review",IF(AL338=0,"Unmatched Order",IF(AL338=1,"Matched to Order","Multiple Order Matches")))) -> Matched to Order | AQ338: =IF(COUNTIF($A$2:A338,A338)=1,1,0) -> 1
A339: pay_420000268 | C339: ORD26000285 | D339: 46268 | E339: CAPTURE | F339: Card | G339: 349 | H339: 6.28 | I339: 1.13 | J339: 341.59 | K339: 46270 | L339: STL-20260905 | M339: =COUNTIF($A:$A,A339) -> 1 | N339: =COUNTIF(Orders!$A:$A,C339) -> 1 | P339: =COUNTIF(Orders!$H:$H,UPPER(SUBSTITUTE(TRIM(C339),"-",""))) -> 1 | R339: =IF(E339="REFUND","Refund",IF(P339=0,"Unmatched Order Reference","Matched Order Reference")) -> Matched Order Reference | S339: =COUNTIFS($C$2:$C$5753,C339,$E$2:$E$5753,"CAPTURE") -> 1 | V339: {=IF(E339<>"CAPTURE",0,SUMPRODUCT((MDR_Rates!$A$2:$A$10=F339)*(G339>MDR_Rates!$B$2:$B$10)*((MDR_Rates!$C$2:$C$10="")+(G339<=MDR_Rates!$C$2:$C$10))*MDR_Rates!$D$2:$D$10))} -> 1.8 | W339: =IF(E339<>"CAPTURE",0,ROUND(G339*V339/100,2)) -> 6.28 | X339: =IF(E339<>"CAPTURE",0,ROUND(W339*18/100,2)) -> 1.13 | Y339: =IF(E339<>"CAPTURE",0,ROUND(H339-W339,2)) -> 0 | Z339: =IF(E339<>"CAPTURE",0,ROUND(I339-X339,2)) -> 0 | AG339: =IF(E339<>"REFUND","",IF(COUNTIFS($A:$A,B339,$E:$E,"CAPTURE")=0,"Missing Original Capture","Original Capture Found")) | AI339: =IF(E339="REFUND",_xlfn.MAXIFS($G:$G,$A:$A,B339,$E:$E,"CAPTURE"),"") | AJ339: =IF(E339<>"REFUND","",IF(G339>AI339,"Refund Exceeds Capture",IF(ABS(G339-AI339)<0.01,"Full Refund","Partial Refund"))) | AK339: =UPPER(SUBSTITUTE(TRIM(C339),"-","")) -> ORD26000285 | AL339: =IF(E339<>"CAPTURE","",COUNTIF(Orders!$H:$H,AK339)) -> 1 | AP339: =IF(E339<>"CAPTURE","",IF(M339>1,"Duplicate ID - Review",IF(AL339=0,"Unmatched Order",IF(AL339=1,"Matched to Order","Multiple Order Matches")))) -> Matched to Order | AQ339: =IF(COUNTIF($A$2:A339,A339)=1,1,0) -> 1
A340: pay_420000281 | C340: ord26000298 | D340: 46268 | E340: CAPTURE | F340: UPI | G340: 2398 | H340: 7.19 | I340: 1.29 | J340: 2389.52 | K340: 46270 | L340: STL-20260905 | M340: =COUNTIF($A:$A,A340) -> 1 | N340: =COUNTIF(Orders!$A:$A,C340) -> 1 | P340: =COUNTIF(Orders!$H:$H,UPPER(SUBSTITUTE(TRIM(C340),"-",""))) -> 1 | R340: =IF(E340="REFUND","Refund",IF(P340=0,"Unmatched Order Reference","Matched Order Reference")) -> Matched Order Reference | S340: =COUNTIFS($C$2:$C$5753,C340,$E$2:$E$5753,"CAPTURE") -> 1 | V340: {=IF(E340<>"CAPTURE",0,SUMPRODUCT((MDR_Rates!$A$2:$A$10=F340)*(G340>MDR_Rates!$B$2:$B$10)*((MDR_Rates!$C$2:$C$10="")+(G340<=MDR_Rates!$C$2:$C$10))*MDR_Rates!$D$2:$D$10))} -> 0.3 | W340: =IF(E340<>"CAPTURE",0,ROUND(G340*V340/100,2)) -> 7.19 | X340: =IF(E340<>"CAPTURE",0,ROUND(W340*18/100,2)) -> 1.29 | Y340: =IF(E340<>"CAPTURE",0,ROUND(H340-W340,2)) -> 0 | Z340: =IF(E340<>"CAPTURE",0,ROUND(I340-X340,2)) -> 0 | AG340: =IF(E340<>"REFUND","",IF(COUNTIFS($A:$A,B340,$E:$E,"CAPTURE")=0,"Missing Original Capture","Original Capture Found")) | AI340: =IF(E340="REFUND",_xlfn.MAXIFS($G:$G,$A:$A,B340,$E:$E,"CAPTURE"),"") | AJ340: =IF(E340<>"REFUND","",IF(G340>AI340,"Refund Exceeds Capture",IF(ABS(G340-AI340)<0.01,"Full Refund","Partial Refund"))) | AK340: =UPPER(SUBSTITUTE(TRIM(C340),"-","")) -> ORD26000298 | AL340: =IF(E340<>"CAPTURE","",COUNTIF(Orders!$H:$H,AK340)) -> 1 | AP340: =IF(E340<>"CAPTURE","",IF(M340>1,"Duplicate ID - Review",IF(AL340=0,"Unmatched Order",IF(AL340=1,"Matched to Order","Multiple Order Matches")))) -> Matched to Order | AQ340: =IF(COUNTIF($A$2:A340,A340)=1,1,0) -> 1
A341: pay_420000315 | C341: ORD26000330 | D341: 46268 | E341: CAPTURE | F341: UPI | G341: 3348 | H341: 10.04 | I341: 1.81 | J341: 3336.15 | K341: 46270 | L341: STL-20260905 | M341: =COUNTIF($A:$A,A341) -> 1 | N341: =COUNTIF(Orders!$A:$A,C341) -> 1 | P341: =COUNTIF(Orders!$H:$H,UPPER(SUBSTITUTE(TRIM(C341),"-",""))) -> 1 | R341: =IF(E341="REFUND","Refund",IF(P341=0,"Unmatched Order Reference","Matched Order Reference")) -> Matched Order Reference | S341: =COUNTIFS($C$2:$C$5753,C341,$E$2:$E$5753,"CAPTURE") -> 1 | V341: {=IF(E341<>"CAPTURE",0,SUMPRODUCT((MDR_Rates!$A$2:$A$10=F341)*(G341>MDR_Rates!$B$2:$B$10)*((MDR_Rates!$C$2:$C$10="")+(G341<=MDR_Rates!$C$2:$C$10))*MDR_Rates!$D$2:$D$10))} -> 0.3 | W341: =IF(E341<>"CAPTURE",0,ROUND(G341*V341/100,2)) -> 10.04 | X341: =IF(E341<>"CAPTURE",0,ROUND(W341*18/100,2)) -> 1.81 | Y341: =IF(E341<>"CAPTURE",0,ROUND(H341-W341,2)) -> 0 | Z341: =IF(E341<>"CAPTURE",0,ROUND(I341-X341,2)) -> 0 | AG341: =IF(E341<>"REFUND","",IF(COUNTIFS($A:$A,B341,$E:$E,"CAPTURE")=0,"Missing Original Capture","Original Capture Found")) | AI341: =IF(E341="REFUND",_xlfn.MAXIFS($G:$G,$A:$A,B341,$E:$E,"CAPTURE"),"") | AJ341: =IF(E341<>"REFUND","",IF(G341>AI341,"Refund Exceeds Capture",IF(ABS(G341-AI341)<0.01,"Full Refund","Partial Refund"))) | AK341: =UPPER(SUBSTITUTE(TRIM(C341),"-","")) -> ORD26000330 | AL341: =IF(E341<>"CAPTURE","",COUNTIF(Orders!$H:$H,AK341)) -> 1 | AP341: =IF(E341<>"CAPTURE","",IF(M341>1,"Duplicate ID - Review",IF(AL341=0,"Unmatched Order",IF(AL341=1,"Matched to Order","Multiple Order Matches")))) -> Matched to Order | AQ341: =IF(COUNTIF($A$2:A341,A341)=1,1,0) -> 1
A342: pay_420000430 | C342: ORD26000447 | D342: 46268 | E342: CAPTURE | F342: UPI | G342: 2999 | H342: 9 | I342: 1.62 | J342: 2988.38 | K342: 46270 | L342: STL-20260905 | M342: =COUNTIF($A:$A,A342) -> 1 | N342: =COUNTIF(Orders!$A:$A,C342) -> 1 | P342: =COUNTIF(Orders!$H:$H,UPPER(SUBSTITUTE(TRIM(C342),"-",""))) -> 1 | R342: =IF(E342="REFUND","Refund",IF(P342=0,"Unmatched Order Reference","Matched Order Reference")) -> Matched Order Reference | S342: =COUNTIFS($C$2:$C$5753,C342,$E$2:$E$5753,"CAPTURE") -> 1 | V342: {=IF(E342<>"CAPTURE",0,SUMPRODUCT((MDR_Rates!$A$2:$A$10=F342)*(G342>MDR_Rates!$B$2:$B$10)*((MDR_Rates!$C$2:$C$10="")+(G342<=MDR_Rates!$C$2:$C$10))*MDR_Rates!$D$2:$D$10))} -> 0.3 | W342: =IF(E342<>"CAPTURE",0,ROUND(G342*V342/100,2)) -> 9 | X342: =IF(E342<>"CAPTURE",0,ROUND(W342*18/100,2)) -> 1.62 | Y342: =IF(E342<>"CAPTURE",0,ROUND(H342-W342,2)) -> 0 | Z342: =IF(E342<>"CAPTURE",0,ROUND(I342-X342,2)) -> 0 | AG342: =IF(E342<>"REFUND","",IF(COUNTIFS($A:$A,B342,$E:$E,"CAPTURE")=0,"Missing Original Capture","Original Capture Found")) | AI342: =IF(E342="REFUND",_xlfn.MAXIFS($G:$G,$A:$A,B342,$E:$E,"CAPTURE"),"") | AJ342: =IF(E342<>"REFUND","",IF(G342>AI342,"Refund Exceeds Capture",IF(ABS(G342-AI342)<0.01,"Full Refund","Partial Refund"))) | AK342: =UPPER(SUBSTITUTE(TRIM(C342),"-","")) -> ORD26000447 | AL342: =IF(E342<>"CAPTURE","",COUNTIF(Orders!$H:$H,AK342)) -> 1 | AP342: =IF(E342<>"CAPTURE","",IF(M342>1,"Duplicate ID - Review",IF(AL342=0,"Unmatched Order",IF(AL342=1,"Matched to Order","Multiple Order Matches")))) -> Matched to Order | AQ342: =IF(COUNTIF($A$2:A342,A342)=1,1,0) -> 1
A343: pay_420000437 | C343: ord26000455 | D343: 46268 | E343: CAPTURE | F343: UPI | G343: 2798 | H343: 8.39 | I343: 1.51 | J343: 2788.1 | K343: 46270 | L343: STL-20260905 | M343: =COUNTIF($A:$A,A343) -> 1 | N343: =COUNTIF(Orders!$A:$A,C343) -> 1 | P343: =COUNTIF(Orders!$H:$H,UPPER(SUBSTITUTE(TRIM(C343),"-",""))) -> 1 | R343: =IF(E343="REFUND","Refund",IF(P343=0,"Unmatched Order Reference","Matched Order Reference")) -> Matched Order Reference | S343: =COUNTIFS($C$2:$C$5753,C343,$E$2:$E$5753,"CAPTURE") -> 1 | V343: {=IF(E343<>"CAPTURE",0,SUMPRODUCT((MDR_Rates!$A$2:$A$10=F343)*(G343>MDR_Rates!$B$2:$B$10)*((MDR_Rates!$C$2:$C$10="")+(G343<=MDR_Rates!$C$2:$C$10))*MDR_Rates!$D$2:$D$10))} -> 0.3 | W343: =IF(E343<>"CAPTURE",0,ROUND(G343*V343/100,2)) -> 8.39 | X343: =IF(E343<>"CAPTURE",0,ROUND(W343*18/100,2)) -> 1.51 | Y343: =IF(E343<>"CAPTURE",0,ROUND(H343-W343,2)) -> 0 | Z343: =IF(E343<>"CAPTURE",0,ROUND(I343-X343,2)) -> 0 | AG343: =IF(E343<>"REFUND","",IF(COUNTIFS($A:$A,B343,$E:$E,"CAPTURE")=0,"Missing Original Capture","Original Capture Found")) | AI343: =IF(E343="REFUND",_xlfn.MAXIFS($G:$G,$A:$A,B343,$E:$E,"CAPTURE"),"") | AJ343: =IF(E343<>"REFUND","",IF(G343>AI343,"Refund Exceeds Capture",IF(ABS(G343-AI343)<0.01,"Full Refund","Partial Refund"))) | AK343: =UPPER(SUBSTITUTE(TRIM(C343),"-","")) -> ORD26000455 | AL343: =IF(E343<>"CAPTURE","",COUNTIF(Orders!$H:$H,AK343)) -> 1 | AP343: =IF(E343<>"CAPTURE","",IF(M343>1,"Duplicate ID - Review",IF(AL343=0,"Unmatched Order",IF(AL343=1,"Matched to Order","Multiple Order Matches")))) -> Matched to Order | AQ343: =IF(COUNTIF($A$2:A343,A343)=1,1,0) -> 1
... A519: pay_420005699 | C519: ORD26005966 | D519: 46268 | E519: CAPTURE | F519: UPI | G519: 2798 | H519: 8.39 | I519: 1.51 | J519: 2788.1 | K519: 46270 | L519: STL-20260905 | M519: =COUNTIF($A:$A,A519) -> 1 | N519: =COUNTIF(Orders!$A:$A,C519) -> 1 | P519: =COUNTIF(Orders!$H:$H,UPPER(SUBSTITUTE(TRIM(C519),"-",""))) -> 1 | R519: =IF(E519="REFUND","Refund",IF(P519=0,"Unmatched Order Reference","Matched Order Reference")) -> Matched Order Reference | S519: =COUNTIFS($C$2:$C$5753,C519,$E$2:$E$5753,"CAPTURE") -> 1 | V519: {=IF(E519<>"CAPTURE",0,SUMPRODUCT((MDR_Rates!$A$2:$A$10=F519)*(G519>MDR_Rates!$B$2:$B$10)*((MDR_Rates!$C$2:$C$10="")+(G519<=MDR_Rates!$C$2:$C$10))*MDR_Rates!$D$2:$D$10))} -> 0.3 | W519: =IF(E519<>"CAPTURE",0,ROUND(G519*V519/100,2)) -> 8.39 | X519: =IF(E519<>"CAPTURE",0,ROUND(W519*18/100,2)) -> 1.51 | Y519: =IF(E519<>"CAPTURE",0,ROUND(H519-W519,2)) -> 0 | Z519: =IF(E519<>"CAPTURE",0,ROUND(I519-X519,2)) -> 0 | AG519: =IF(E519<>"REFUND","",IF(COUNTIFS($A:$A,B519,$E:$E,"CAPTURE")=0,"Missing Original Capture","Original Capture Found")) | AI519: =IF(E519="REFUND",_xlfn.MAXIFS($G:$G,$A:$A,B519,$E:$E,"CAPTURE"),"") | AJ519: =IF(E519<>"REFUND","",IF(G519>AI519,"Refund Exceeds Capture",IF(ABS(G519-AI519)<0.01,"Full Refund","Partial Refund"))) | AK519: =UPPER(SUBSTITUTE(TRIM(C519),"-","")) -> ORD26005966 | AL519: =IF(E519<>"CAPTURE","",COUNTIF(Orders!$H:$H,AK519)) -> 1 | AP519: =IF(E519<>"CAPTURE","",IF(M519>1,"Duplicate ID - Review",IF(AL519=0,"Unmatched Order",IF(AL519=1,"Matched to Order","Multiple Order Matches")))) -> Matched to Order | AQ519: =IF(COUNTIF($A$2:A519,A519)=1,1,0) -> 1
A520: rfnd_1C41Q7T6GFAL | B520: pay_420001351 | D520: 46268 | E520: REFUND | F520: Card | G520: 9297 | H520: 0 | I520: 0 | J520: -9297 | K520: 46270 | L520: STL-20260905 | M520: =COUNTIF($A:$A,A520) -> 1 | N520: =COUNTIF(Orders!$A:$A,C520) -> 0 | P520: =COUNTIF(Orders!$H:$H,UPPER(SUBSTITUTE(TRIM(C520),"-",""))) -> 1042575 | R520: =IF(E520="REFUND","Refund",IF(P520=0,"Unmatched Order Reference","Matched Order Reference")) -> Refund | S520: =COUNTIFS($C$2:$C$5753,C520,$E$2:$E$5753,"CAPTURE") -> 0 | V520: {=IF(E520<>"CAPTURE",0,SUMPRODUCT((MDR_Rates!$A$2:$A$10=F520)*(G520>MDR_Rates!$B$2:$B$10)*((MDR_Rates!$C$2:$C$10="")+(G520<=MDR_Rates!$C$2:$C$10))*MDR_Rates!$D$2:$D$10))} -> 0 | W520: =IF(E520<>"CAPTURE",0,ROUND(G520*V520/100,2)) -> 0 | X520: =IF(E520<>"CAPTURE",0,ROUND(W520*18/100,2)) -> 0 | Y520: =IF(E520<>"CAPTURE",0,ROUND(H520-W520,2)) -> 0 | Z520: =IF(E520<>"CAPTURE",0,ROUND(I520-X520,2)) -> 0 | AG520: =IF(E520<>"REFUND","",IF(COUNTIFS($A:$A,B520,$E:$E,"CAPTURE")=0,"Missing Original Capture","Original Capture Found")) -> Original Capture Found | AI520: =IF(E520="REFUND",_xlfn.MAXIFS($G:$G,$A:$A,B520,$E:$E,"CAPTURE"),"") -> 9297 | AJ520: =IF(E520<>"REFUND","",IF(G520>AI520,"Refund Exceeds Capture",IF(ABS(G520-AI520)<0.01,"Full Refund","Partial Refund"))) -> Full Refund | AK520: =UPPER(SUBSTITUTE(TRIM(C520),"-","")) | AL520: =IF(E520<>"CAPTURE","",COUNTIF(Orders!$H:$H,AK520)) | AP520: =IF(E520<>"CAPTURE","",IF(M520>1,"Duplicate ID - Review",IF(AL520=0,"Unmatched Order",IF(AL520=1,"Matched to Order","Multiple Order Matches")))) | AQ520: =IF(COUNTIF($A$2:A520,A520)=1,1,0) -> 1
A521: rfnd_KJKJAE6PT0EL | B521: pay_420003553 | D521: 46268 | E521: REFUND | F521: UPI | G521: 2499 | H521: 0 | I521: 0 | J521: -2499 | K521: 46270 | L521: STL-20260905 | M521: =COUNTIF($A:$A,A521) -> 1 | N521: =COUNTIF(Orders!$A:$A,C521) -> 0 | P521: =COUNTIF(Orders!$H:$H,UPPER(SUBSTITUTE(TRIM(C521),"-",""))) -> 1042575 | R521: =IF(E521="REFUND","Refund",IF(P521=0,"Unmatched Order Reference","Matched Order Reference")) -> Refund | S521: =COUNTIFS($C$2:$C$5753,C521,$E$2:$E$5753,"CAPTURE") -> 0 | V521: {=IF(E521<>"CAPTURE",0,SUMPRODUCT((MDR_Rates!$A$2:$A$10=F521)*(G521>MDR_Rates!$B$2:$B$10)*((MDR_Rates!$C$2:$C$10="")+(G521<=MDR_Rates!$C$2:$C$10))*MDR_Rates!$D$2:$D$10))} -> 0 | W521: =IF(E521<>"CAPTURE",0,ROUND(G521*V521/100,2)) -> 0 | X521: =IF(E521<>"CAPTURE",0,ROUND(W521*18/100,2)) -> 0 | Y521: =IF(E521<>"CAPTURE",0,ROUND(H521-W521,2)) -> 0 | Z521: =IF(E521<>"CAPTURE",0,ROUND(I521-X521,2)) -> 0 | AG521: =IF(E521<>"REFUND","",IF(COUNTIFS($A:$A,B521,$E:$E,"CAPTURE")=0,"Missing Original Capture","Original Capture Found")) -> Original Capture Found | AI521: =IF(E521="REFUND",_xlfn.MAXIFS($G:$G,$A:$A,B521,$E:$E,"CAPTURE"),"") -> 2499 | AJ521: =IF(E521<>"REFUND","",IF(G521>AI521,"Refund Exceeds Capture",IF(ABS(G521-AI521)<0.01,"Full Refund","Partial Refund"))) -> Full Refund | AK521: =UPPER(SUBSTITUTE(TRIM(C521),"-","")) | AL521: =IF(E521<>"CAPTURE","",COUNTIF(Orders!$H:$H,AK521)) | AP521: =IF(E521<>"CAPTURE","",IF(M521>1,"Duplicate ID - Review",IF(AL521=0,"Unmatched Order",IF(AL521=1,"Matched to Order","Multiple Order Matches")))) | AQ521: =IF(COUNTIF($A$2:A521,A521)=1,1,0) -> 1
A522: pay_420000042 | C522: ORD26000043 | D522: 46269 | E522: CAPTURE | F522: Card | G522: 3098 | H522: 49.57 | I522: 8.92 | J522: 3039.51 | K522: 46271 | L522: STL-20260906 | M522: =COUNTIF($A:$A,A522) -> 1 | N522: =COUNTIF(Orders!$A:$A,C522) -> 1 | P522: =COUNTIF(Orders!$H:$H,UPPER(SUBSTITUTE(TRIM(C522),"-",""))) -> 1 | R522: =IF(E522="REFUND","Refund",IF(P522=0,"Unmatched Order Reference","Matched Order Reference")) -> Matched Order Reference | S522: =COUNTIFS($C$2:$C$5753,C522,$E$2:$E$5753,"CAPTURE") -> 1 | V522: {=IF(E522<>"CAPTURE",0,SUMPRODUCT((MDR_Rates!$A$2:$A$10=F522)*(G522>MDR_Rates!$B$2:$B$10)*((MDR_Rates!$C$2:$C$10="")+(G522<=MDR_Rates!$C$2:$C$10))*MDR_Rates!$D$2:$D$10))} -> 1.6 | W522: =IF(E522<>"CAPTURE",0,ROUND(G522*V522/100,2)) -> 49.57 | X522: =IF(E522<>"CAPTURE",0,ROUND(W522*18/100,2)) -> 8.92 | Y522: =IF(E522<>"CAPTURE",0,ROUND(H522-W522,2)) -> 0 | Z522: =IF(E522<>"CAPTURE",0,ROUND(I522-X522,2)) -> 0 | AG522: =IF(E522<>"REFUND","",IF(COUNTIFS($A:$A,B522,$E:$E,"CAPTURE")=0,"Missing Original Capture","Original Capture Found")) | AI522: =IF(E522="REFUND",_xlfn.MAXIFS($G:$G,$A:$A,B522,$E:$E,"CAPTURE"),"") | AJ522: =IF(E522<>"REFUND","",IF(G522>AI522,"Refund Exceeds Capture",IF(ABS(G522-AI522)<0.01,"Full Refund","Partial Refund"))) | AK522: =UPPER(SUBSTITUTE(TRIM(C522),"-","")) -> ORD26000043 | AL522: =IF(E522<>"CAPTURE","",COUNTIF(Orders!$H:$H,AK522)) -> 1 | AP522: =IF(E522<>"CAPTURE","",IF(M522>1,"Duplicate ID - Review",IF(AL522=0,"Unmatched Order",IF(AL522=1,"Matched to Order","Multiple Order Matches")))) -> Matched to Order | AQ522: =IF(COUNTIF($A$2:A522,A522)=1,1,0) -> 1
A523: pay_420000048 | C523: ORD26000050 | D523: 46269 | E523: CAPTURE | F523: UPI | G523: 3499 | H523: 10.5 | I523: 1.89 | J523: 3486.61 | K523: 46271 | L523: STL-20260906 | M523: =COUNTIF($A:$A,A523) -> 1 | N523: =COUNTIF(Orders!$A:$A,C523) -> 1 | P523: =COUNTIF(Orders!$H:$H,UPPER(SUBSTITUTE(TRIM(C523),"-",""))) -> 1 | R523: =IF(E523="REFUND","Refund",IF(P523=0,"Unmatched Order Reference","Matched Order Reference")) -> Matched Order Reference | S523: =COUNTIFS($C$2:$C$5753,C523,$E$2:$E$5753,"CAPTURE") -> 1 | V523: {=IF(E523<>"CAPTURE",0,SUMPRODUCT((MDR_Rates!$A$2:$A$10=F523)*(G523>MDR_Rates!$B$2:$B$10)*((MDR_Rates!$C$2:$C$10="")+(G523<=MDR_Rates!$C$2:$C$10))*MDR_Rates!$D$2:$D$10))} -> 0.3 | W523: =IF(E523<>"CAPTURE",0,ROUND(G523*V523/100,2)) -> 10.5 | X523: =IF(E523<>"CAPTURE",0,ROUND(W523*18/100,2)) -> 1.89 | Y523: =IF(E523<>"CAPTURE",0,ROUND(H523-W523,2)) -> 0 | Z523: =IF(E523<>"CAPTURE",0,ROUND(I523-X523,2)) -> 0 | AG523: =IF(E523<>"REFUND","",IF(COUNTIFS($A:$A,B523,$E:$E,"CAPTURE")=0,"Missing Original Capture","Original Capture Found")) | AI523: =IF(E523="REFUND",_xlfn.MAXIFS($G:$G,$A:$A,B523,$E:$E,"CAPTURE"),"") | AJ523: =IF(E523<>"REFUND","",IF(G523>AI523,"Refund Exceeds Capture",IF(ABS(G523-AI523)<0.01,"Full Refund","Partial Refund"))) | AK523: =UPPER(SUBSTITUTE(TRIM(C523),"-","")) -> ORD26000050 | AL523: =IF(E523<>"CAPTURE","",COUNTIF(Orders!$H:$H,AK523)) -> 1 | AP523: =IF(E523<>"CAPTURE","",IF(M523>1,"Duplicate ID - Review",IF(AL523=0,"Unmatched Order",IF(AL523=1,"Matched to Order","Multiple Order Matches")))) -> Matched to Order | AQ523: =IF(COUNTIF($A$2:A523,A523)=1,1,0) -> 1
A524: pay_420000091 | C524: ORD-26000097 | D524: 46269 | E524: CAPTURE | F524: Wallet | G524: 1098 | H524: 20.86 | I524: 3.75 | J524: 1073.39 | K524: 46271 | L524: STL-20260906 | M524: =COUNTIF($A:$A,A524) -> 1 | N524: =COUNTIF(Orders!$A:$A,C524) -> 0 | P524: =COUNTIF(Orders!$H:$H,UPPER(SUBSTITUTE(TRIM(C524),"-",""))) -> 1 | R524: =IF(E524="REFUND","Refund",IF(P524=0,"Unmatched Order Reference","Matched Order Reference")) -> Matched Order Reference | S524: =COUNTIFS($C$2:$C$5753,C524,$E$2:$E$5753,"CAPTURE") -> 1 | V524: {=IF(E524<>"CAPTURE",0,SUMPRODUCT((MDR_Rates!$A$2:$A$10=F524)*(G524>MDR_Rates!$B$2:$B$10)*((MDR_Rates!$C$2:$C$10="")+(G524<=MDR_Rates!$C$2:$C$10))*MDR_Rates!$D$2:$D$10))} -> 1.9 | W524: =IF(E524<>"CAPTURE",0,ROUND(G524*V524/100,2)) -> 20.86 | X524: =IF(E524<>"CAPTURE",0,ROUND(W524*18/100,2)) -> 3.75 | Y524: =IF(E524<>"CAPTURE",0,ROUND(H524-W524,2)) -> 0 | Z524: =IF(E524<>"CAPTURE",0,ROUND(I524-X524,2)) -> 0 | AG524: =IF(E524<>"REFUND","",IF(COUNTIFS($A:$A,B524,$E:$E,"CAPTURE")=0,"Missing Original Capture","Original Capture Found")) | AI524: =IF(E524="REFUND",_xlfn.MAXIFS($G:$G,$A:$A,B524,$E:$E,"CAPTURE"),"") | AJ524: =IF(E524<>"REFUND","",IF(G524>AI524,"Refund Exceeds Capture",IF(ABS(G524-AI524)<0.01,"Full Refund","Partial Refund"))) | AK524: =UPPER(SUBSTITUTE(TRIM(C524),"-","")) -> ORD26000097 | AL524: =IF(E524<>"CAPTURE","",COUNTIF(Orders!$H:$H,AK524)) -> 1 | AP524: =IF(E524<>"CAPTURE","",IF(M524>1,"Duplicate ID - Review",IF(AL524=0,"Unmatched Order",IF(AL524=1,"Matched to Order","Multiple Order Matches")))) -> Matched to Order | AQ524: =IF(COUNTIF($A$2:A524,A524)=1,1,0) -> 1
A525: pay_420000104 | C525: ORD26000112 | D525: 46269 | E525: CAPTURE | F525: UPI | G525: 10297 | H525: 30.89 | I525: 5.56 | J525: 10260.55 | K525: 46271 | L525: STL-20260906 | M525: =COUNTIF($A:$A,A525) -> 1 | N525: =COUNTIF(Orders!$A:$A,C525) -> 1 | P525: =COUNTIF(Orders!$H:$H,UPPER(SUBSTITUTE(TRIM(C525),"-",""))) -> 1 | R525: =IF(E525="REFUND","Refund",IF(P525=0,"Unmatched Order Reference","Matched Order Reference")) -> Matched Order Reference | S525: =COUNTIFS($C$2:$C$5753,C525,$E$2:$E$5753,"CAPTURE") -> 1 | V525: {=IF(E525<>"CAPTURE",0,SUMPRODUCT((MDR_Rates!$A$2:$A$10=F525)*(G525>MDR_Rates!$B$2:$B$10)*((MDR_Rates!$C$2:$C$10="")+(G525<=MDR_Rates!$C$2:$C$10))*MDR_Rates!$D$2:$D$10))} -> 0.3 | W525: =IF(E525<>"CAPTURE",0,ROUND(G525*V525/100,2)) -> 30.89 | X525: =IF(E525<>"CAPTURE",0,ROUND(W525*18/100,2)) -> 5.56 | Y525: =IF(E525<>"CAPTURE",0,ROUND(H525-W525,2)) -> 0 | Z525: =IF(E525<>"CAPTURE",0,ROUND(I525-X525,2)) -> 0 | AG525: =IF(E525<>"REFUND","",IF(COUNTIFS($A:$A,B525,$E:$E,"CAPTURE")=0,"Missing Original Capture","Original Capture Found")) | AI525: =IF(E525="REFUND",_xlfn.MAXIFS($G:$G,$A:$A,B525,$E:$E,"CAPTURE"),"") | AJ525: =IF(E525<>"REFUND","",IF(G525>AI525,"Refund Exceeds Capture",IF(ABS(G525-AI525)<0.01,"Full Refund","Partial Refund"))) | AK525: =UPPER(SUBSTITUTE(TRIM(C525),"-","")) -> ORD26000112 | AL525: =IF(E525<>"CAPTURE","",COUNTIF(Orders!$H:$H,AK525)) -> 1 | AP525: =IF(E525<>"CAPTURE","",IF(M525>1,"Duplicate ID - Review",IF(AL525=0,"Unmatched Order",IF(AL525=1,"Matched to Order","Multiple Order Matches")))) -> Matched to Order | AQ525: =IF(COUNTIF($A$2:A525,A525)=1,1,0) -> 1
A526: pay_420000108 | C526: ORD26000116 | D526: 46269 | E526: CAPTURE | F526: UPI | G526: 2499 | H526: 7.5 | I526: 1.35 | J526: 2490.15 | K526: 46271 | L526: STL-20260906 | M526: =COUNTIF($A:$A,A526) -> 1 | N526: =COUNTIF(Orders!$A:$A,C526) -> 1 | P526: =COUNTIF(Orders!$H:$H,UPPER(SUBSTITUTE(TRIM(C526),"-",""))) -> 1 | R526: =IF(E526="REFUND","Refund",IF(P526=0,"Unmatched Order Reference","Matched Order Reference")) -> Matched Order Reference | S526: =COUNTIFS($C$2:$C$5753,C526,$E$2:$E$5753,"CAPTURE") -> 1 | V526: {=IF(E526<>"CAPTURE",0,SUMPRODUCT((MDR_Rates!$A$2:$A$10=F526)*(G526>MDR_Rates!$B$2:$B$10)*((MDR_Rates!$C$2:$C$10="")+(G526<=MDR_Rates!$C$2:$C$10))*MDR_Rates!$D$2:$D$10))} -> 0.3 | W526: =IF(E526<>"CAPTURE",0,ROUND(G526*V526/100,2)) -> 7.5 | X526: =IF(E526<>"CAPTURE",0,ROUND(W526*18/100,2)) -> 1.35 | Y526: =IF(E526<>"CAPTURE",0,ROUND(H526-W526,2)) -> 0 | Z526: =IF(E526<>"CAPTURE",0,ROUND(I526-X526,2)) -> 0 | AG526: =IF(E526<>"REFUND","",IF(COUNTIFS($A:$A,B526,$E:$E,"CAPTURE")=0,"Missing Original Capture","Original Capture Found")) | AI526: =IF(E526="REFUND",_xlfn.MAXIFS($G:$G,$A:$A,B526,$E:$E,"CAPTURE"),"") | AJ526: =IF(E526<>"REFUND","",IF(G526>AI526,"Refund Exceeds Capture",IF(ABS(G526-AI526)<0.01,"Full Refund","Partial Refund"))) | AK526: =UPPER(SUBSTITUTE(TRIM(C526),"-","")) -> ORD26000116 | AL526: =IF(E526<>"CAPTURE","",COUNTIF(Orders!$H:$H,AK526)) -> 1 | AP526: =IF(E526<>"CAPTURE","",IF(M526>1,"Duplicate ID - Review",IF(AL526=0,"Unmatched Order",IF(AL526=1,"Matched to Order","Multiple Order Matches")))) -> Matched to Order | AQ526: =IF(COUNTIF($A$2:A526,A526)=1,1,0) -> 1
A527: pay_420000110 | C527: ORD26000118 | D527: 46269 | E527: CAPTURE | F527: UPI | G527: 5998 | H527: 17.99 | I527: 3.24 | J527: 5976.77 | K527: 46271 | L527: STL-20260906 | M527: =COUNTIF($A:$A,A527) -> 1 | N527: =COUNTIF(Orders!$A:$A,C527) -> 1 | P527: =COUNTIF(Orders!$H:$H,UPPER(SUBSTITUTE(TRIM(C527),"-",""))) -> 1 | R527: =IF(E527="REFUND","Refund",IF(P527=0,"Unmatched Order Reference","Matched Order Reference")) -> Matched Order Reference | S527: =COUNTIFS($C$2:$C$5753,C527,$E$2:$E$5753,"CAPTURE") -> 1 | V527: {=IF(E527<>"CAPTURE",0,SUMPRODUCT((MDR_Rates!$A$2:$A$10=F527)*(G527>MDR_Rates!$B$2:$B$10)*((MDR_Rates!$C$2:$C$10="")+(G527<=MDR_Rates!$C$2:$C$10))*MDR_Rates!$D$2:$D$10))} -> 0.3 | W527: =IF(E527<>"CAPTURE",0,ROUND(G527*V527/100,2)) -> 17.99 | X527: =IF(E527<>"CAPTURE",0,ROUND(W527*18/100,2)) -> 3.24 | Y527: =IF(E527<>"CAPTURE",0,ROUND(H527-W527,2)) -> 0 | Z527: =IF(E527<>"CAPTURE",0,ROUND(I527-X527,2)) -> 0 | AG527: =IF(E527<>"REFUND","",IF(COUNTIFS($A:$A,B527,$E:$E,"CAPTURE")=0,"Missing Original Capture","Original Capture Found")) | AI527: =IF(E527="REFUND",_xlfn.MAXIFS($G:$G,$A:$A,B527,$E:$E,"CAPTURE"),"") | AJ527: =IF(E527<>"REFUND","",IF(G527>AI527,"Refund Exceeds Capture",IF(ABS(G527-AI527)<0.01,"Full Refund","Partial Refund"))) | AK527: =UPPER(SUBSTITUTE(TRIM(C527),"-","")) -> ORD26000118 | AL527: =IF(E527<>"CAPTURE","",COUNTIF(Orders!$H:$H,AK527)) -> 1 | AP527: =IF(E527<>"CAPTURE","",IF(M527>1,"Duplicate ID - Review",IF(AL527=0,"Unmatched Order",IF(AL527=1,"Matched to Order","Multiple Order Matches")))) -> Matched to Order | AQ527: =IF(COUNTIF($A$2:A527,A527)=1,1,0) -> 1
A528: pay_420000150 | C528: ORD26000160 | D528: 46269 | E528: CAPTURE | F528: Card | G528: 1299 | H528: 23.38 | I528: 4.21 | J528: 1271.41 | K528: 46271 | L528: STL-20260906 | M528: =COUNTIF($A:$A,A528) -> 1 | N528: =COUNTIF(Orders!$A:$A,C528) -> 1 | P528: =COUNTIF(Orders!$H:$H,UPPER(SUBSTITUTE(TRIM(C528),"-",""))) -> 1 | R528: =IF(E528="REFUND","Refund",IF(P528=0,"Unmatched Order Reference","Matched Order Reference")) -> Matched Order Reference | S528: =COUNTIFS($C$2:$C$5753,C528,$E$2:$E$5753,"CAPTURE") -> 1 | V528: {=IF(E528<>"CAPTURE",0,SUMPRODUCT((MDR_Rates!$A$2:$A$10=F528)*(G528>MDR_Rates!$B$2:$B$10)*((MDR_Rates!$C$2:$C$10="")+(G528<=MDR_Rates!$C$2:$C$10))*MDR_Rates!$D$2:$D$10))} -> 1.8 | W528: =IF(E528<>"CAPTURE",0,ROUND(G528*V528/100,2)) -> 23.38 | X528: =IF(E528<>"CAPTURE",0,ROUND(W528*18/100,2)) -> 4.21 | Y528: =IF(E528<>"CAPTURE",0,ROUND(H528-W528,2)) -> 0 | Z528: =IF(E528<>"CAPTURE",0,ROUND(I528-X528,2)) -> 0 | AG528: =IF(E528<>"REFUND","",IF(COUNTIFS($A:$A,B528,$E:$E,"CAPTURE")=0,"Missing Original Capture","Original Capture Found")) | AI528: =IF(E528="REFUND",_xlfn.MAXIFS($G:$G,$A:$A,B528,$E:$E,"CAPTURE"),"") | AJ528: =IF(E528<>"REFUND","",IF(G528>AI528,"Refund Exceeds Capture",IF(ABS(G528-AI528)<0.01,"Full Refund","Partial Refund"))) | AK528: =UPPER(SUBSTITUTE(TRIM(C528),"-","")) -> ORD26000160 | AL528: =IF(E528<>"CAPTURE","",COUNTIF(Orders!$H:$H,AK528)) -> 1 | AP528: =IF(E528<>"CAPTURE","",IF(M528>1,"Duplicate ID - Review",IF(AL528=0,"Unmatched Order",IF(AL528=1,"Matched to Order","Multiple Order Matches")))) -> Matched to Order | AQ528: =IF(COUNTIF($A$2:A528,A528)=1,1,0) -> 1
A529: pay_420000189 | C529: ORD26000202 | D529: 46269 | E529: CAPTURE | F529: UPI | G529: 3499 | H529: 10.5 | I529: 1.89 | J529: 3486.61 | K529: 46271 | L529: STL-20260906 | M529: =COUNTIF($A:$A,A529) -> 1 | N529: =COUNTIF(Orders!$A:$A,C529) -> 1 | P529: =COUNTIF(Orders!$H:$H,UPPER(SUBSTITUTE(TRIM(C529),"-",""))) -> 1 | R529: =IF(E529="REFUND","Refund",IF(P529=0,"Unmatched Order Reference","Matched Order Reference")) -> Matched Order Reference | S529: =COUNTIFS($C$2:$C$5753,C529,$E$2:$E$5753,"CAPTURE") -> 1 | V529: {=IF(E529<>"CAPTURE",0,SUMPRODUCT((MDR_Rates!$A$2:$A$10=F529)*(G529>MDR_Rates!$B$2:$B$10)*((MDR_Rates!$C$2:$C$10="")+(G529<=MDR_Rates!$C$2:$C$10))*MDR_Rates!$D$2:$D$10))} -> 0.3 | W529: =IF(E529<>"CAPTURE",0,ROUND(G529*V529/100,2)) -> 10.5 | X529: =IF(E529<>"CAPTURE",0,ROUND(W529*18/100,2)) -> 1.89 | Y529: =IF(E529<>"CAPTURE",0,ROUND(H529-W529,2)) -> 0 | Z529: =IF(E529<>"CAPTURE",0,ROUND(I529-X529,2)) -> 0 | AG529: =IF(E529<>"REFUND","",IF(COUNTIFS($A:$A,B529,$E:$E,"CAPTURE")=0,"Missing Original Capture","Original Capture Found")) | AI529: =IF(E529="REFUND",_xlfn.MAXIFS($G:$G,$A:$A,B529,$E:$E,"CAPTURE"),"") | AJ529: =IF(E529<>"REFUND","",IF(G529>AI529,"Refund Exceeds Capture",IF(ABS(G529-AI529)<0.01,"Full Refund","Partial Refund"))) | AK529: =UPPER(SUBSTITUTE(TRIM(C529),"-","")) -> ORD26000202 | AL529: =IF(E529<>"CAPTURE","",COUNTIF(Orders!$H:$H,AK529)) -> 1 | AP529: =IF(E529<>"CAPTURE","",IF(M529>1,"Duplicate ID - Review",IF(AL529=0,"Unmatched Order",IF(AL529=1,"Matched to Order","Multiple Order Matches")))) -> Matched to Order | AQ529: =IF(COUNTIF($A$2:A529,A529)=1,1,0) -> 1
A530: pay_420000207 | C530: ORD26000221 | D530: 46269 | E530: CAPTURE | F530: UPI | G530: 1499 | H530: 0 | I530: 0 | J530: 1499 | K530: 46271 | L530: STL-20260906 | M530: =COUNTIF($A:$A,A530) -> 1 | N530: =COUNTIF(Orders!$A:$A,C530) -> 1 | P530: =COUNTIF(Orders!$H:$H,UPPER(SUBSTITUTE(TRIM(C530),"-",""))) -> 1 | R530: =IF(E530="REFUND","Refund",IF(P530=0,"Unmatched Order Reference","Matched Order Reference")) -> Matched Order Reference | S530: =COUNTIFS($C$2:$C$5753,C530,$E$2:$E$5753,"CAPTURE") -> 1 | V530: {=IF(E530<>"CAPTURE",0,SUMPRODUCT((MDR_Rates!$A$2:$A$10=F530)*(G530>MDR_Rates!$B$2:$B$10)*((MDR_Rates!$C$2:$C$10="")+(G530<=MDR_Rates!$C$2:$C$10))*MDR_Rates!$D$2:$D$10))} -> 0 | W530: =IF(E530<>"CAPTURE",0,ROUND(G530*V530/100,2)) -> 0 | X530: =IF(E530<>"CAPTURE",0,ROUND(W530*18/100,2)) -> 0 | Y530: =IF(E530<>"CAPTURE",0,ROUND(H530-W530,2)) -> 0 | Z530: =IF(E530<>"CAPTURE",0,ROUND(I530-X530,2)) -> 0 | AG530: =IF(E530<>"REFUND","",IF(COUNTIFS($A:$A,B530,$E:$E,"CAPTURE")=0,"Missing Original Capture","Original Capture Found")) | AI530: =IF(E530="REFUND",_xlfn.MAXIFS($G:$G,$A:$A,B530,$E:$E,"CAPTURE"),"") | AJ530: =IF(E530<>"REFUND","",IF(G530>AI530,"Refund Exceeds Capture",IF(ABS(G530-AI530)<0.01,"Full Refund","Partial Refund"))) | AK530: =UPPER(SUBSTITUTE(TRIM(C530),"-","")) -> ORD26000221 | AL530: =IF(E530<>"CAPTURE","",COUNTIF(Orders!$H:$H,AK530)) -> 1 | AP530: =IF(E530<>"CAPTURE","",IF(M530>1,"Duplicate ID - Review",IF(AL530=0,"Unmatched Order",IF(AL530=1,"Matched to Order","Multiple Order Matches")))) -> Matched to Order | AQ530: =IF(COUNTIF($A$2:A530,A530)=1,1,0) -> 1
A531: pay_420000253 | C531: ORD26000270 | D531: 46269 | E531: CAPTURE | F531: UPI | G531: 3100 | H531: 9.3 | I531: 1.67 | J531: 3089.03 | K531: 46271 | L531: STL-20260906 | M531: =COUNTIF($A:$A,A531) -> 1 | N531: =COUNTIF(Orders!$A:$A,C531) -> 1 | P531: =COUNTIF(Orders!$H:$H,UPPER(SUBSTITUTE(TRIM(C531),"-",""))) -> 1 | R531: =IF(E531="REFUND","Refund",IF(P531=0,"Unmatched Order Reference","Matched Order Reference")) -> Matched Order Reference | S531: =COUNTIFS($C$2:$C$5753,C531,$E$2:$E$5753,"CAPTURE") -> 1 | V531: {=IF(E531<>"CAPTURE",0,SUMPRODUCT((MDR_Rates!$A$2:$A$10=F531)*(G531>MDR_Rates!$B$2:$B$10)*((MDR_Rates!$C$2:$C$10="")+(G531<=MDR_Rates!$C$2:$C$10))*MDR_Rates!$D$2:$D$10))} -> 0.3 | W531: =IF(E531<>"CAPTURE",0,ROUND(G531*V531/100,2)) -> 9.3 | X531: =IF(E531<>"CAPTURE",0,ROUND(W531*18/100,2)) -> 1.67 | Y531: =IF(E531<>"CAPTURE",0,ROUND(H531-W531,2)) -> 0 | Z531: =IF(E531<>"CAPTURE",0,ROUND(I531-X531,2)) -> 0 | AG531: =IF(E531<>"REFUND","",IF(COUNTIFS($A:$A,B531,$E:$E,"CAPTURE")=0,"Missing Original Capture","Original Capture Found")) | AI531: =IF(E531="REFUND",_xlfn.MAXIFS($G:$G,$A:$A,B531,$E:$E,"CAPTURE"),"") | AJ531: =IF(E531<>"REFUND","",IF(G531>AI531,"Refund Exceeds Capture",IF(ABS(G531-AI531)<0.01,"Full Refund","Partial Refund"))) | AK531: =UPPER(SUBSTITUTE(TRIM(C531),"-","")) -> ORD26000270 | AL531: =IF(E531<>"CAPTURE","",COUNTIF(Orders!$H:$H,AK531)) -> 1 | AP531: =IF(E531<>"CAPTURE","",IF(M531>1,"Duplicate ID - Review",IF(AL531=0,"Unmatched Order",IF(AL531=1,"Matched to Order","Multiple Order Matches")))) -> Matched to Order | AQ531: =IF(COUNTIF($A$2:A531,A531)=1,1,0) -> 1
A532: pay_420000284 | C532: ORD26000300 | D532: 46269 | E532: CAPTURE | F532: Card | G532: 5998 | H532: 95.97 | I532: 17.27 | J532: 5884.76 | K532: 46271 | L532: STL-20260906 | M532: =COUNTIF($A:$A,A532) -> 1 | N532: =COUNTIF(Orders!$A:$A,C532) -> 0 | P532: =COUNTIF(Orders!$H:$H,UPPER(SUBSTITUTE(TRIM(C532),"-",""))) -> 1 | R532: =IF(E532="REFUND","Refund",IF(P532=0,"Unmatched Order Reference","Matched Order Reference")) -> Matched Order Reference | S532: =COUNTIFS($C$2:$C$5753,C532,$E$2:$E$5753,"CAPTURE") -> 1 | V532: {=IF(E532<>"CAPTURE",0,SUMPRODUCT((MDR_Rates!$A$2:$A$10=F532)*(G532>MDR_Rates!$B$2:$B$10)*((MDR_Rates!$C$2:$C$10="")+(G532<=MDR_Rates!$C$2:$C$10))*MDR_Rates!$D$2:$D$10))} -> 1.6 | W532: =IF(E532<>"CAPTURE",0,ROUND(G532*V532/100,2)) -> 95.97 | X532: =IF(E532<>"CAPTURE",0,ROUND(W532*18/100,2)) -> 17.27 | Y532: =IF(E532<>"CAPTURE",0,ROUND(H532-W532,2)) -> 0 | Z532: =IF(E532<>"CAPTURE",0,ROUND(I532-X532,2)) -> 0 | AG532: =IF(E532<>"REFUND","",IF(COUNTIFS($A:$A,B532,$E:$E,"CAPTURE")=0,"Missing Original Capture","Original Capture Found")) | AI532: =IF(E532="REFUND",_xlfn.MAXIFS($G:$G,$A:$A,B532,$E:$E,"CAPTURE"),"") | AJ532: =IF(E532<>"REFUND","",IF(G532>AI532,"Refund Exceeds Capture",IF(ABS(G532-AI532)<0.01,"Full Refund","Partial Refund"))) | AK532: =UPPER(SUBSTITUTE(TRIM(C532),"-","")) -> ORD26000300 | AL532: =IF(E532<>"CAPTURE","",COUNTIF(Orders!$H:$H,AK532)) -> 1 | AP532: =IF(E532<>"CAPTURE","",IF(M532>1,"Duplicate ID - Review",IF(AL532=0,"Unmatched Order",IF(AL532=1,"Matched to Order","Multiple Order Matches")))) -> Matched to Order | AQ532: =IF(COUNTIF($A$2:A532,A532)=1,1,0) -> 1
A533: pay_420000304 | C533: ORD26000320 | D533: 46269 | E533: CAPTURE | F533: Card | G533: 4498 | H533: 71.97 | I533: 12.95 | J533: 4413.08 | K533: 46271 | L533: STL-20260906 | M533: =COUNTIF($A:$A,A533) -> 1 | N533: =COUNTIF(Orders!$A:$A,C533) -> 1 | P533: =COUNTIF(Orders!$H:$H,UPPER(SUBSTITUTE(TRIM(C533),"-",""))) -> 1 | R533: =IF(E533="REFUND","Refund",IF(P533=0,"Unmatched Order Reference","Matched Order Reference")) -> Matched Order Reference | S533: =COUNTIFS($C$2:$C$5753,C533,$E$2:$E$5753,"CAPTURE") -> 1 | V533: {=IF(E533<>"CAPTURE",0,SUMPRODUCT((MDR_Rates!$A$2:$A$10=F533)*(G533>MDR_Rates!$B$2:$B$10)*((MDR_Rates!$C$2:$C$10="")+(G533<=MDR_Rates!$C$2:$C$10))*MDR_Rates!$D$2:$D$10))} -> 1.6 | W533: =IF(E533<>"CAPTURE",0,ROUND(G533*V533/100,2)) -> 71.97 | X533: =IF(E533<>"CAPTURE",0,ROUND(W533*18/100,2)) -> 12.95 | Y533: =IF(E533<>"CAPTURE",0,ROUND(H533-W533,2)) -> 0 | Z533: =IF(E533<>"CAPTURE",0,ROUND(I533-X533,2)) -> 0 | AG533: =IF(E533<>"REFUND","",IF(COUNTIFS($A:$A,B533,$E:$E,"CAPTURE")=0,"Missing Original Capture","Original Capture Found")) | AI533: =IF(E533="REFUND",_xlfn.MAXIFS($G:$G,$A:$A,B533,$E:$E,"CAPTURE"),"") | AJ533: =IF(E533<>"REFUND","",IF(G533>AI533,"Refund Exceeds Capture",IF(ABS(G533-AI533)<0.01,"Full Refund","Partial Refund"))) | AK533: =UPPER(SUBSTITUTE(TRIM(C533),"-","")) -> ORD26000320 | AL533: =IF(E533<>"CAPTURE","",COUNTIF(Orders!$H:$H,AK533)) -> 1 | AP533: =IF(E533<>"CAPTURE","",IF(M533>1,"Duplicate ID - Review",IF(AL533=0,"Unmatched Order",IF(AL533=1,"Matched to Order","Multiple Order Matches")))) -> Matched to Order | AQ533: =IF(COUNTIF($A$2:A533,A533)=1,1,0) -> 1
... A717: pay_420005731 | C717: ORD26005998 | D717: 46269 | E717: CAPTURE | F717: UPI | G717: 349 | H717: 0 | I717: 0 | J717: 349 | K717: 46271 | L717: STL-20260906 | M717: =COUNTIF($A:$A,A717) -> 1 | N717: =COUNTIF(Orders!$A:$A,C717) -> 1 | P717: =COUNTIF(Orders!$H:$H,UPPER(SUBSTITUTE(TRIM(C717),"-",""))) -> 1 | R717: =IF(E717="REFUND","Refund",IF(P717=0,"Unmatched Order Reference","Matched Order Reference")) -> Matched Order Reference | S717: =COUNTIFS($C$2:$C$5753,C717,$E$2:$E$5753,"CAPTURE") -> 1 | V717: {=IF(E717<>"CAPTURE",0,SUMPRODUCT((MDR_Rates!$A$2:$A$10=F717)*(G717>MDR_Rates!$B$2:$B$10)*((MDR_Rates!$C$2:$C$10="")+(G717<=MDR_Rates!$C$2:$C$10))*MDR_Rates!$D$2:$D$10))} -> 0 | W717: =IF(E717<>"CAPTURE",0,ROUND(G717*V717/100,2)) -> 0 | X717: =IF(E717<>"CAPTURE",0,ROUND(W717*18/100,2)) -> 0 | Y717: =IF(E717<>"CAPTURE",0,ROUND(H717-W717,2)) -> 0 | Z717: =IF(E717<>"CAPTURE",0,ROUND(I717-X717,2)) -> 0 | AG717: =IF(E717<>"REFUND","",IF(COUNTIFS($A:$A,B717,$E:$E,"CAPTURE")=0,"Missing Original Capture","Original Capture Found")) | AI717: =IF(E717="REFUND",_xlfn.MAXIFS($G:$G,$A:$A,B717,$E:$E,"CAPTURE"),"") | AJ717: =IF(E717<>"REFUND","",IF(G717>AI717,"Refund Exceeds Capture",IF(ABS(G717-AI717)<0.01,"Full Refund","Partial Refund"))) | AK717: =UPPER(SUBSTITUTE(TRIM(C717),"-","")) -> ORD26005998 | AL717: =IF(E717<>"CAPTURE","",COUNTIF(Orders!$H:$H,AK717)) -> 1 | AP717: =IF(E717<>"CAPTURE","",IF(M717>1,"Duplicate ID - Review",IF(AL717=0,"Unmatched Order",IF(AL717=1,"Matched to Order","Multiple Order Matches")))) -> Matched to Order | AQ717: =IF(COUNTIF($A$2:A717,A717)=1,1,0) -> 1
A718: rfnd_1R7WDBXGYHDQ | B718: pay_420002852 | D718: 46269 | E718: REFUND | F718: UPI | G718: 5998 | H718: 0 | I718: 0 | J718: -5998 | K718: 46271 | L718: STL-20260906 | M718: =COUNTIF($A:$A,A718) -> 1 | N718: =COUNTIF(Orders!$A:$A,C718) -> 0 | P718: =COUNTIF(Orders!$H:$H,UPPER(SUBSTITUTE(TRIM(C718),"-",""))) -> 1042575 | R718: =IF(E718="REFUND","Refund",IF(P718=0,"Unmatched Order Reference","Matched Order Reference")) -> Refund | S718: =COUNTIFS($C$2:$C$5753,C718,$E$2:$E$5753,"CAPTURE") -> 0 | V718: {=IF(E718<>"CAPTURE",0,SUMPRODUCT((MDR_Rates!$A$2:$A$10=F718)*(G718>MDR_Rates!$B$2:$B$10)*((MDR_Rates!$C$2:$C$10="")+(G718<=MDR_Rates!$C$2:$C$10))*MDR_Rates!$D$2:$D$10))} -> 0 | W718: =IF(E718<>"CAPTURE",0,ROUND(G718*V718/100,2)) -> 0 | X718: =IF(E718<>"CAPTURE",0,ROUND(W718*18/100,2)) -> 0 | Y718: =IF(E718<>"CAPTURE",0,ROUND(H718-W718,2)) -> 0 | Z718: =IF(E718<>"CAPTURE",0,ROUND(I718-X718,2)) -> 0 | AG718: =IF(E718<>"REFUND","",IF(COUNTIFS($A:$A,B718,$E:$E,"CAPTURE")=0,"Missing Original Capture","Original Capture Found")) -> Original Capture Found | AI718: =IF(E718="REFUND",_xlfn.MAXIFS($G:$G,$A:$A,B718,$E:$E,"CAPTURE"),"") -> 5998 | AJ718: =IF(E718<>"REFUND","",IF(G718>AI718,"Refund Exceeds Capture",IF(ABS(G718-AI718)<0.01,"Full Refund","Partial Refund"))) -> Full Refund | AK718: =UPPER(SUBSTITUTE(TRIM(C718),"-","")) | AL718: =IF(E718<>"CAPTURE","",COUNTIF(Orders!$H:$H,AK718)) | AP718: =IF(E718<>"CAPTURE","",IF(M718>1,"Duplicate ID - Review",IF(AL718=0,"Unmatched Order",IF(AL718=1,"Matched to Order","Multiple Order Matches")))) | AQ718: =IF(COUNTIF($A$2:A718,A718)=1,1,0) -> 1
A719: rfnd_GKK57QSMZQR7 | B719: pay_420003990 | D719: 46269 | E719: REFUND | F719: Card | G719: 7999 | H719: 0 | I719: 0 | J719: -7999 | K719: 46271 | L719: STL-20260906 | M719: =COUNTIF($A:$A,A719) -> 1 | N719: =COUNTIF(Orders!$A:$A,C719) -> 0 | P719: =COUNTIF(Orders!$H:$H,UPPER(SUBSTITUTE(TRIM(C719),"-",""))) -> 1042575 | R719: =IF(E719="REFUND","Refund",IF(P719=0,"Unmatched Order Reference","Matched Order Reference")) -> Refund | S719: =COUNTIFS($C$2:$C$5753,C719,$E$2:$E$5753,"CAPTURE") -> 0 | V719: {=IF(E719<>"CAPTURE",0,SUMPRODUCT((MDR_Rates!$A$2:$A$10=F719)*(G719>MDR_Rates!$B$2:$B$10)*((MDR_Rates!$C$2:$C$10="")+(G719<=MDR_Rates!$C$2:$C$10))*MDR_Rates!$D$2:$D$10))} -> 0 | W719: =IF(E719<>"CAPTURE",0,ROUND(G719*V719/100,2)) -> 0 | X719: =IF(E719<>"CAPTURE",0,ROUND(W719*18/100,2)) -> 0 | Y719: =IF(E719<>"CAPTURE",0,ROUND(H719-W719,2)) -> 0 | Z719: =IF(E719<>"CAPTURE",0,ROUND(I719-X719,2)) -> 0 | AG719: =IF(E719<>"REFUND","",IF(COUNTIFS($A:$A,B719,$E:$E,"CAPTURE")=0,"Missing Original Capture","Original Capture Found")) -> Original Capture Found | AI719: =IF(E719="REFUND",_xlfn.MAXIFS($G:$G,$A:$A,B719,$E:$E,"CAPTURE"),"") -> 7999 | AJ719: =IF(E719<>"REFUND","",IF(G719>AI719,"Refund Exceeds Capture",IF(ABS(G719-AI719)<0.01,"Full Refund","Partial Refund"))) -> Full Refund | AK719: =UPPER(SUBSTITUTE(TRIM(C719),"-","")) | AL719: =IF(E719<>"CAPTURE","",COUNTIF(Orders!$H:$H,AK719)) | AP719: =IF(E719<>"CAPTURE","",IF(M719>1,"Duplicate ID - Review",IF(AL719=0,"Unmatched Order",IF(AL719=1,"Matched to Order","Multiple Order Matches")))) | AQ719: =IF(COUNTIF($A$2:A719,A719)=1,1,0) -> 1
A720: pay_420000116 | C720: ORD26000125 | D720: 46270 | E720: CAPTURE | F720: UPI | G720: 3598 | H720: 10.79 | I720: 1.94 | J720: 3585.27 | K720: 46272 | L720: STL-20260907 | M720: =COUNTIF($A:$A,A720) -> 1 | N720: =COUNTIF(Orders!$A:$A,C720) -> 1 | P720: =COUNTIF(Orders!$H:$H,UPPER(SUBSTITUTE(TRIM(C720),"-",""))) -> 1 | R720: =IF(E720="REFUND","Refund",IF(P720=0,"Unmatched Order Reference","Matched Order Reference")) -> Matched Order Reference | S720: =COUNTIFS($C$2:$C$5753,C720,$E$2:$E$5753,"CAPTURE") -> 1 | V720: {=IF(E720<>"CAPTURE",0,SUMPRODUCT((MDR_Rates!$A$2:$A$10=F720)*(G720>MDR_Rates!$B$2:$B$10)*((MDR_Rates!$C$2:$C$10="")+(G720<=MDR_Rates!$C$2:$C$10))*MDR_Rates!$D$2:$D$10))} -> 0.3 | W720: =IF(E720<>"CAPTURE",0,ROUND(G720*V720/100,2)) -> 10.79 | X720: =IF(E720<>"CAPTURE",0,ROUND(W720*18/100,2)) -> 1.94 | Y720: =IF(E720<>"CAPTURE",0,ROUND(H720-W720,2)) -> 0 | Z720: =IF(E720<>"CAPTURE",0,ROUND(I720-X720,2)) -> 0 | AG720: =IF(E720<>"REFUND","",IF(COUNTIFS($A:$A,B720,$E:$E,"CAPTURE")=0,"Missing Original Capture","Original Capture Found")) | AI720: =IF(E720="REFUND",_xlfn.MAXIFS($G:$G,$A:$A,B720,$E:$E,"CAPTURE"),"") | AJ720: =IF(E720<>"REFUND","",IF(G720>AI720,"Refund Exceeds Capture",IF(ABS(G720-AI720)<0.01,"Full Refund","Partial Refund"))) | AK720: =UPPER(SUBSTITUTE(TRIM(C720),"-","")) -> ORD26000125 | AL720: =IF(E720<>"CAPTURE","",COUNTIF(Orders!$H:$H,AK720)) -> 1 | AP720: =IF(E720<>"CAPTURE","",IF(M720>1,"Duplicate ID - Review",IF(AL720=0,"Unmatched Order",IF(AL720=1,"Matched to Order","Multiple Order Matches")))) -> Matched to Order | AQ720: =IF(COUNTIF($A$2:A720,A720)=1,1,0) -> 1
A721: pay_420000220 | C721: ORD26000235 | D721: 46270 | E721: CAPTURE | F721: NetBanking | G721: 1798 | H721: 26.97 | I721: 4.85 | J721: 1766.18 | K721: 46272 | L721: STL-20260907 | M721: =COUNTIF($A:$A,A721) -> 1 | N721: =COUNTIF(Orders!$A:$A,C721) -> 1 | P721: =COUNTIF(Orders!$H:$H,UPPER(SUBSTITUTE(TRIM(C721),"-",""))) -> 1 | R721: =IF(E721="REFUND","Refund",IF(P721=0,"Unmatched Order Reference","Matched Order Reference")) -> Matched Order Reference | S721: =COUNTIFS($C$2:$C$5753,C721,$E$2:$E$5753,"CAPTURE") -> 1 | V721: {=IF(E721<>"CAPTURE",0,SUMPRODUCT((MDR_Rates!$A$2:$A$10=F721)*(G721>MDR_Rates!$B$2:$B$10)*((MDR_Rates!$C$2:$C$10="")+(G721<=MDR_Rates!$C$2:$C$10))*MDR_Rates!$D$2:$D$10))} -> 1.5 | W721: =IF(E721<>"CAPTURE",0,ROUND(G721*V721/100,2)) -> 26.97 | X721: =IF(E721<>"CAPTURE",0,ROUND(W721*18/100,2)) -> 4.85 | Y721: =IF(E721<>"CAPTURE",0,ROUND(H721-W721,2)) -> 0 | Z721: =IF(E721<>"CAPTURE",0,ROUND(I721-X721,2)) -> 0 | AG721: =IF(E721<>"REFUND","",IF(COUNTIFS($A:$A,B721,$E:$E,"CAPTURE")=0,"Missing Original Capture","Original Capture Found")) | AI721: =IF(E721="REFUND",_xlfn.MAXIFS($G:$G,$A:$A,B721,$E:$E,"CAPTURE"),"") | AJ721: =IF(E721<>"REFUND","",IF(G721>AI721,"Refund Exceeds Capture",IF(ABS(G721-AI721)<0.01,"Full Refund","Partial Refund"))) | AK721: =UPPER(SUBSTITUTE(TRIM(C721),"-","")) -> ORD26000235 | AL721: =IF(E721<>"CAPTURE","",COUNTIF(Orders!$H:$H,AK721)) -> 1 | AP721: =IF(E721<>"CAPTURE","",IF(M721>1,"Duplicate ID - Review",IF(AL721=0,"Unmatched Order",IF(AL721=1,"Matched to Order","Multiple Order Matches")))) -> Matched to Order | AQ721: =IF(COUNTIF($A$2:A721,A721)=1,1,0) -> 1
A722: pay_420000266 | C722: ORD26000283 | D722: 46270 | E722: CAPTURE | F722: Card | G722: 5097 | H722: 81.55 | I722: 14.68 | J722: 5000.77 | K722: 46272 | L722: STL-20260907 | M722: =COUNTIF($A:$A,A722) -> 1 | N722: =COUNTIF(Orders!$A:$A,C722) -> 1 | P722: =COUNTIF(Orders!$H:$H,UPPER(SUBSTITUTE(TRIM(C722),"-",""))) -> 1 | R722: =IF(E722="REFUND","Refund",IF(P722=0,"Unmatched Order Reference","Matched Order Reference")) -> Matched Order Reference | S722: =COUNTIFS($C$2:$C$5753,C722,$E$2:$E$5753,"CAPTURE") -> 1 | V722: {=IF(E722<>"CAPTURE",0,SUMPRODUCT((MDR_Rates!$A$2:$A$10=F722)*(G722>MDR_Rates!$B$2:$B$10)*((MDR_Rates!$C$2:$C$10="")+(G722<=MDR_Rates!$C$2:$C$10))*MDR_Rates!$D$2:$D$10))} -> 1.6 | W722: =IF(E722<>"CAPTURE",0,ROUND(G722*V722/100,2)) -> 81.55 | X722: =IF(E722<>"CAPTURE",0,ROUND(W722*18/100,2)) -> 14.68 | Y722: =IF(E722<>"CAPTURE",0,ROUND(H722-W722,2)) -> 0 | Z722: =IF(E722<>"CAPTURE",0,ROUND(I722-X722,2)) -> 0 | AG722: =IF(E722<>"REFUND","",IF(COUNTIFS($A:$A,B722,$E:$E,"CAPTURE")=0,"Missing Original Capture","Original Capture Found")) | AI722: =IF(E722="REFUND",_xlfn.MAXIFS($G:$G,$A:$A,B722,$E:$E,"CAPTURE"),"") | AJ722: =IF(E722<>"REFUND","",IF(G722>AI722,"Refund Exceeds Capture",IF(ABS(G722-AI722)<0.01,"Full Refund","Partial Refund"))) | AK722: =UPPER(SUBSTITUTE(TRIM(C722),"-","")) -> ORD26000283 | AL722: =IF(E722<>"CAPTURE","",COUNTIF(Orders!$H:$H,AK722)) -> 1 | AP722: =IF(E722<>"CAPTURE","",IF(M722>1,"Duplicate ID - Review",IF(AL722=0,"Unmatched Order",IF(AL722=1,"Matched to Order","Multiple Order Matches")))) -> Matched to Order | AQ722: =IF(COUNTIF($A$2:A722,A722)=1,1,0) -> 1
A723: pay_420000267 | C723: ORD26000284 | D723: 46270 | E723: CAPTURE | F723: Wallet | G723: 2999 | H723: 50.98 | I723: 9.18 | J723: 2938.84 | K723: 46272 | L723: STL-20260907 | M723: =COUNTIF($A:$A,A723) -> 1 | N723: =COUNTIF(Orders!$A:$A,C723) -> 0 | P723: =COUNTIF(Orders!$H:$H,UPPER(SUBSTITUTE(TRIM(C723),"-",""))) -> 1 | R723: =IF(E723="REFUND","Refund",IF(P723=0,"Unmatched Order Reference","Matched Order Reference")) -> Matched Order Reference | S723: =COUNTIFS($C$2:$C$5753,C723,$E$2:$E$5753,"CAPTURE") -> 1 | V723: {=IF(E723<>"CAPTURE",0,SUMPRODUCT((MDR_Rates!$A$2:$A$10=F723)*(G723>MDR_Rates!$B$2:$B$10)*((MDR_Rates!$C$2:$C$10="")+(G723<=MDR_Rates!$C$2:$C$10))*MDR_Rates!$D$2:$D$10))} -> 1.7 | W723: =IF(E723<>"CAPTURE",0,ROUND(G723*V723/100,2)) -> 50.98 | X723: =IF(E723<>"CAPTURE",0,ROUND(W723*18/100,2)) -> 9.18 | Y723: =IF(E723<>"CAPTURE",0,ROUND(H723-W723,2)) -> 0 | Z723: =IF(E723<>"CAPTURE",0,ROUND(I723-X723,2)) -> 0 | AG723: =IF(E723<>"REFUND","",IF(COUNTIFS($A:$A,B723,$E:$E,"CAPTURE")=0,"Missing Original Capture","Original Capture Found")) | AI723: =IF(E723="REFUND",_xlfn.MAXIFS($G:$G,$A:$A,B723,$E:$E,"CAPTURE"),"") | AJ723: =IF(E723<>"REFUND","",IF(G723>AI723,"Refund Exceeds Capture",IF(ABS(G723-AI723)<0.01,"Full Refund","Partial Refund"))) | AK723: =UPPER(SUBSTITUTE(TRIM(C723),"-","")) -> ORD26000284 | AL723: =IF(E723<>"CAPTURE","",COUNTIF(Orders!$H:$H,AK723)) -> 1 | AP723: =IF(E723<>"CAPTURE","",IF(M723>1,"Duplicate ID - Review",IF(AL723=0,"Unmatched Order",IF(AL723=1,"Matched to Order","Multiple Order Matches")))) -> Matched to Order | AQ723: =IF(COUNTIF($A$2:A723,A723)=1,1,0) -> 1
A724: pay_420000320 | C724: ORD26000335 | D724: 46270 | E724: CAPTURE | F724: Card | G724: 5998 | H724: 95.97 | I724: 17.27 | J724: 5884.76 | K724: 46272 | L724: STL-20260907 | M724: =COUNTIF($A:$A,A724) -> 1 | N724: =COUNTIF(Orders!$A:$A,C724) -> 1 | P724: =COUNTIF(Orders!$H:$H,UPPER(SUBSTITUTE(TRIM(C724),"-",""))) -> 1 | R724: =IF(E724="REFUND","Refund",IF(P724=0,"Unmatched Order Reference","Matched Order Reference")) -> Matched Order Reference | S724: =COUNTIFS($C$2:$C$5753,C724,$E$2:$E$5753,"CAPTURE") -> 1 | V724: {=IF(E724<>"CAPTURE",0,SUMPRODUCT((MDR_Rates!$A$2:$A$10=F724)*(G724>MDR_Rates!$B$2:$B$10)*((MDR_Rates!$C$2:$C$10="")+(G724<=MDR_Rates!$C$2:$C$10))*MDR_Rates!$D$2:$D$10))} -> 1.6 | W724: =IF(E724<>"CAPTURE",0,ROUND(G724*V724/100,2)) -> 95.97 | X724: =IF(E724<>"CAPTURE",0,ROUND(W724*18/100,2)) -> 17.27 | Y724: =IF(E724<>"CAPTURE",0,ROUND(H724-W724,2)) -> 0 | Z724: =IF(E724<>"CAPTURE",0,ROUND(I724-X724,2)) -> 0 | AG724: =IF(E724<>"REFUND","",IF(COUNTIFS($A:$A,B724,$E:$E,"CAPTURE")=0,"Missing Original Capture","Original Capture Found")) | AI724: =IF(E724="REFUND",_xlfn.MAXIFS($G:$G,$A:$A,B724,$E:$E,"CAPTURE"),"") | AJ724: =IF(E724<>"REFUND","",IF(G724>AI724,"Refund Exceeds Capture",IF(ABS(G724-AI724)<0.01,"Full Refund","Partial Refund"))) | AK724: =UPPER(SUBSTITUTE(TRIM(C724),"-","")) -> ORD26000335 | AL724: =IF(E724<>"CAPTURE","",COUNTIF(Orders!$H:$H,AK724)) -> 1 | AP724: =IF(E724<>"CAPTURE","",IF(M724>1,"Duplicate ID - Review",IF(AL724=0,"Unmatched Order",IF(AL724=1,"Matched to Order","Multiple Order Matches")))) -> Matched to Order | AQ724: =IF(COUNTIF($A$2:A724,A724)=1,1,0) -> 1
A725: pay_420000329 | C725: ORD26000345 | D725: 46270 | E725: CAPTURE | F725: UPI | G725: 9347 | H725: 28.04 | I725: 5.05 | J725: 9313.91 | K725: 46272 | L725: STL-20260907 | M725: =COUNTIF($A:$A,A725) -> 1 | N725: =COUNTIF(Orders!$A:$A,C725) -> 1 | P725: =COUNTIF(Orders!$H:$H,UPPER(SUBSTITUTE(TRIM(C725),"-",""))) -> 1 | R725: =IF(E725="REFUND","Refund",IF(P725=0,"Unmatched Order Reference","Matched Order Reference")) -> Matched Order Reference | S725: =COUNTIFS($C$2:$C$5753,C725,$E$2:$E$5753,"CAPTURE") -> 1 | V725: {=IF(E725<>"CAPTURE",0,SUMPRODUCT((MDR_Rates!$A$2:$A$10=F725)*(G725>MDR_Rates!$B$2:$B$10)*((MDR_Rates!$C$2:$C$10="")+(G725<=MDR_Rates!$C$2:$C$10))*MDR_Rates!$D$2:$D$10))} -> 0.3 | W725: =IF(E725<>"CAPTURE",0,ROUND(G725*V725/100,2)) -> 28.04 | X725: =IF(E725<>"CAPTURE",0,ROUND(W725*18/100,2)) -> 5.05 | Y725: =IF(E725<>"CAPTURE",0,ROUND(H725-W725,2)) -> 0 | Z725: =IF(E725<>"CAPTURE",0,ROUND(I725-X725,2)) -> 0 | AG725: =IF(E725<>"REFUND","",IF(COUNTIFS($A:$A,B725,$E:$E,"CAPTURE")=0,"Missing Original Capture","Original Capture Found")) | AI725: =IF(E725="REFUND",_xlfn.MAXIFS($G:$G,$A:$A,B725,$E:$E,"CAPTURE"),"") | AJ725: =IF(E725<>"REFUND","",IF(G725>AI725,"Refund Exceeds Capture",IF(ABS(G725-AI725)<0.01,"Full Refund","Partial Refund"))) | AK725: =UPPER(SUBSTITUTE(TRIM(C725),"-","")) -> ORD26000345 | AL725: =IF(E725<>"CAPTURE","",COUNTIF(Orders!$H:$H,AK725)) -> 1 | AP725: =IF(E725<>"CAPTURE","",IF(M725>1,"Duplicate ID - Review",IF(AL725=0,"Unmatched Order",IF(AL725=1,"Matched to Order","Multiple Order Matches")))) -> Matched to Order | AQ725: =IF(COUNTIF($A$2:A725,A725)=1,1,0) -> 1
A726: pay_420000387 | C726: ORD26000405 | D726: 46270 | E726: CAPTURE | F726: Card | G726: 2197 | H726: 35.15 | I726: 6.33 | J726: 2155.52 | K726: 46272 | L726: STL-20260907 | M726: =COUNTIF($A:$A,A726) -> 1 | N726: =COUNTIF(Orders!$A:$A,C726) -> 1 | P726: =COUNTIF(Orders!$H:$H,UPPER(SUBSTITUTE(TRIM(C726),"-",""))) -> 1 | R726: =IF(E726="REFUND","Refund",IF(P726=0,"Unmatched Order Reference","Matched Order Reference")) -> Matched Order Reference | S726: =COUNTIFS($C$2:$C$5753,C726,$E$2:$E$5753,"CAPTURE") -> 1 | V726: {=IF(E726<>"CAPTURE",0,SUMPRODUCT((MDR_Rates!$A$2:$A$10=F726)*(G726>MDR_Rates!$B$2:$B$10)*((MDR_Rates!$C$2:$C$10="")+(G726<=MDR_Rates!$C$2:$C$10))*MDR_Rates!$D$2:$D$10))} -> 1.6 | W726: =IF(E726<>"CAPTURE",0,ROUND(G726*V726/100,2)) -> 35.15 | X726: =IF(E726<>"CAPTURE",0,ROUND(W726*18/100,2)) -> 6.33 | Y726: =IF(E726<>"CAPTURE",0,ROUND(H726-W726,2)) -> 0 | Z726: =IF(E726<>"CAPTURE",0,ROUND(I726-X726,2)) -> 0 | AG726: =IF(E726<>"REFUND","",IF(COUNTIFS($A:$A,B726,$E:$E,"CAPTURE")=0,"Missing Original Capture","Original Capture Found")) | AI726: =IF(E726="REFUND",_xlfn.MAXIFS($G:$G,$A:$A,B726,$E:$E,"CAPTURE"),"") | AJ726: =IF(E726<>"REFUND","",IF(G726>AI726,"Refund Exceeds Capture",IF(ABS(G726-AI726)<0.01,"Full Refund","Partial Refund"))) | AK726: =UPPER(SUBSTITUTE(TRIM(C726),"-","")) -> ORD26000405 | AL726: =IF(E726<>"CAPTURE","",COUNTIF(Orders!$H:$H,AK726)) -> 1 | AP726: =IF(E726<>"CAPTURE","",IF(M726>1,"Duplicate ID - Review",IF(AL726=0,"Unmatched Order",IF(AL726=1,"Matched to Order","Multiple Order Matches")))) -> Matched to Order | AQ726: =IF(COUNTIF($A$2:A726,A726)=1,1,0) -> 1
A727: pay_420000389 | C727: ORD26000408 | D727: 46270 | E727: CAPTURE | F727: UPI | G727: 2999 | H727: 9 | I727: 1.62 | J727: 2988.38 | K727: 46272 | L727: STL-20260907 | M727: =COUNTIF($A:$A,A727) -> 1 | N727: =COUNTIF(Orders!$A:$A,C727) -> 1 | P727: =COUNTIF(Orders!$H:$H,UPPER(SUBSTITUTE(TRIM(C727),"-",""))) -> 1 | R727: =IF(E727="REFUND","Refund",IF(P727=0,"Unmatched Order Reference","Matched Order Reference")) -> Matched Order Reference | S727: =COUNTIFS($C$2:$C$5753,C727,$E$2:$E$5753,"CAPTURE") -> 1 | V727: {=IF(E727<>"CAPTURE",0,SUMPRODUCT((MDR_Rates!$A$2:$A$10=F727)*(G727>MDR_Rates!$B$2:$B$10)*((MDR_Rates!$C$2:$C$10="")+(G727<=MDR_Rates!$C$2:$C$10))*MDR_Rates!$D$2:$D$10))} -> 0.3 | W727: =IF(E727<>"CAPTURE",0,ROUND(G727*V727/100,2)) -> 9 | X727: =IF(E727<>"CAPTURE",0,ROUND(W727*18/100,2)) -> 1.62 | Y727: =IF(E727<>"CAPTURE",0,ROUND(H727-W727,2)) -> 0 | Z727: =IF(E727<>"CAPTURE",0,ROUND(I727-X727,2)) -> 0 | AG727: =IF(E727<>"REFUND","",IF(COUNTIFS($A:$A,B727,$E:$E,"CAPTURE")=0,"Missing Original Capture","Original Capture Found")) | AI727: =IF(E727="REFUND",_xlfn.MAXIFS($G:$G,$A:$A,B727,$E:$E,"CAPTURE"),"") | AJ727: =IF(E727<>"REFUND","",IF(G727>AI727,"Refund Exceeds Capture",IF(ABS(G727-AI727)<0.01,"Full Refund","Partial Refund"))) | AK727: =UPPER(SUBSTITUTE(TRIM(C727),"-","")) -> ORD26000408 | AL727: =IF(E727<>"CAPTURE","",COUNTIF(Orders!$H:$H,AK727)) -> 1 | AP727: =IF(E727<>"CAPTURE","",IF(M727>1,"Duplicate ID - Review",IF(AL727=0,"Unmatched Order",IF(AL727=1,"Matched to Order","Multiple Order Matches")))) -> Matched to Order | AQ727: =IF(COUNTIF($A$2:A727,A727)=1,1,0) -> 1
A728: pay_420000486 | C728: ORD26000510 | D728: 46270 | E728: CAPTURE | F728: Wallet | G728: 8598 | H728: 146.17 | I728: 26.31 | J728: 8425.52 | K728: 46272 | L728: STL-20260907 | M728: =COUNTIF($A:$A,A728) -> 1 | N728: =COUNTIF(Orders!$A:$A,C728) -> 1 | P728: =COUNTIF(Orders!$H:$H,UPPER(SUBSTITUTE(TRIM(C728),"-",""))) -> 1 | R728: =IF(E728="REFUND","Refund",IF(P728=0,"Unmatched Order Reference","Matched Order Reference")) -> Matched Order Reference | S728: =COUNTIFS($C$2:$C$5753,C728,$E$2:$E$5753,"CAPTURE") -> 1 | V728: {=IF(E728<>"CAPTURE",0,SUMPRODUCT((MDR_Rates!$A$2:$A$10=F728)*(G728>MDR_Rates!$B$2:$B$10)*((MDR_Rates!$C$2:$C$10="")+(G728<=MDR_Rates!$C$2:$C$10))*MDR_Rates!$D$2:$D$10))} -> 1.7 | W728: =IF(E728<>"CAPTURE",0,ROUND(G728*V728/100,2)) -> 146.17 | X728: =IF(E728<>"CAPTURE",0,ROUND(W728*18/100,2)) -> 26.31 | Y728: =IF(E728<>"CAPTURE",0,ROUND(H728-W728,2)) -> 0 | Z728: =IF(E728<>"CAPTURE",0,ROUND(I728-X728,2)) -> 0 | AG728: =IF(E728<>"REFUND","",IF(COUNTIFS($A:$A,B728,$E:$E,"CAPTURE")=0,"Missing Original Capture","Original Capture Found")) | AI728: =IF(E728="REFUND",_xlfn.MAXIFS($G:$G,$A:$A,B728,$E:$E,"CAPTURE"),"") | AJ728: =IF(E728<>"REFUND","",IF(G728>AI728,"Refund Exceeds Capture",IF(ABS(G728-AI728)<0.01,"Full Refund","Partial Refund"))) | AK728: =UPPER(SUBSTITUTE(TRIM(C728),"-","")) -> ORD26000510 | AL728: =IF(E728<>"CAPTURE","",COUNTIF(Orders!$H:$H,AK728)) -> 1 | AP728: =IF(E728<>"CAPTURE","",IF(M728>1,"Duplicate ID - Review",IF(AL728=0,"Unmatched Order",IF(AL728=1,"Matched to Order","Multiple Order Matches")))) -> Matched to Order | AQ728: =IF(COUNTIF($A$2:A728,A728)=1,1,0) -> 1
A729: pay_420000504 | C729: ORD26000526 | D729: 46270 | E729: CAPTURE | F729: UPI | G729: 999 | H729: 0 | I729: 0 | J729: 999 | K729: 46272 | L729: STL-20260907 | M729: =COUNTIF($A:$A,A729) -> 1 | N729: =COUNTIF(Orders!$A:$A,C729) -> 1 | P729: =COUNTIF(Orders!$H:$H,UPPER(SUBSTITUTE(TRIM(C729),"-",""))) -> 1 | R729: =IF(E729="REFUND","Refund",IF(P729=0,"Unmatched Order Reference","Matched Order Reference")) -> Matched Order Reference | S729: =COUNTIFS($C$2:$C$5753,C729,$E$2:$E$5753,"CAPTURE") -> 1 | V729: {=IF(E729<>"CAPTURE",0,SUMPRODUCT((MDR_Rates!$A$2:$A$10=F729)*(G729>MDR_Rates!$B$2:$B$10)*((MDR_Rates!$C$2:$C$10="")+(G729<=MDR_Rates!$C$2:$C$10))*MDR_Rates!$D$2:$D$10))} -> 0 | W729: =IF(E729<>"CAPTURE",0,ROUND(G729*V729/100,2)) -> 0 | X729: =IF(E729<>"CAPTURE",0,ROUND(W729*18/100,2)) -> 0 | Y729: =IF(E729<>"CAPTURE",0,ROUND(H729-W729,2)) -> 0 | Z729: =IF(E729<>"CAPTURE",0,ROUND(I729-X729,2)) -> 0 | AG729: =IF(E729<>"REFUND","",IF(COUNTIFS($A:$A,B729,$E:$E,"CAPTURE")=0,"Missing Original Capture","Original Capture Found")) | AI729: =IF(E729="REFUND",_xlfn.MAXIFS($G:$G,$A:$A,B729,$E:$E,"CAPTURE"),"") | AJ729: =IF(E729<>"REFUND","",IF(G729>AI729,"Refund Exceeds Capture",IF(ABS(G729-AI729)<0.01,"Full Refund","Partial Refund"))) | AK729: =UPPER(SUBSTITUTE(TRIM(C729),"-","")) -> ORD26000526 | AL729: =IF(E729<>"CAPTURE","",COUNTIF(Orders!$H:$H,AK729)) -> 1 | AP729: =IF(E729<>"CAPTURE","",IF(M729>1,"Duplicate ID - Review",IF(AL729=0,"Unmatched Order",IF(AL729=1,"Matched to Order","Multiple Order Matches")))) -> Matched to Order | AQ729: =IF(COUNTIF($A$2:A729,A729)=1,1,0) -> 1
A730: pay_420000520 | C730: ORD26000545 | D730: 46270 | E730: CAPTURE | F730: Card | G730: 998 | H730: 17.96 | I730: 3.23 | J730: 976.81 | K730: 46272 | L730: STL-20260907 | M730: =COUNTIF($A:$A,A730) -> 1 | N730: =COUNTIF(Orders!$A:$A,C730) -> 1 | P730: =COUNTIF(Orders!$H:$H,UPPER(SUBSTITUTE(TRIM(C730),"-",""))) -> 1 | R730: =IF(E730="REFUND","Refund",IF(P730=0,"Unmatched Order Reference","Matched Order Reference")) -> Matched Order Reference | S730: =COUNTIFS($C$2:$C$5753,C730,$E$2:$E$5753,"CAPTURE") -> 1 | V730: {=IF(E730<>"CAPTURE",0,SUMPRODUCT((MDR_Rates!$A$2:$A$10=F730)*(G730>MDR_Rates!$B$2:$B$10)*((MDR_Rates!$C$2:$C$10="")+(G730<=MDR_Rates!$C$2:$C$10))*MDR_Rates!$D$2:$D$10))} -> 1.8 | W730: =IF(E730<>"CAPTURE",0,ROUND(G730*V730/100,2)) -> 17.96 | X730: =IF(E730<>"CAPTURE",0,ROUND(W730*18/100,2)) -> 3.23 | Y730: =IF(E730<>"CAPTURE",0,ROUND(H730-W730,2)) -> 0 | Z730: =IF(E730<>"CAPTURE",0,ROUND(I730-X730,2)) -> 0 | AG730: =IF(E730<>"REFUND","",IF(COUNTIFS($A:$A,B730,$E:$E,"CAPTURE")=0,"Missing Original Capture","Original Capture Found")) | AI730: =IF(E730="REFUND",_xlfn.MAXIFS($G:$G,$A:$A,B730,$E:$E,"CAPTURE"),"") | AJ730: =IF(E730<>"REFUND","",IF(G730>AI730,"Refund Exceeds Capture",IF(ABS(G730-AI730)<0.01,"Full Refund","Partial Refund"))) | AK730: =UPPER(SUBSTITUTE(TRIM(C730),"-","")) -> ORD26000545 | AL730: =IF(E730<>"CAPTURE","",COUNTIF(Orders!$H:$H,AK730)) -> 1 | AP730: =IF(E730<>"CAPTURE","",IF(M730>1,"Duplicate ID - Review",IF(AL730=0,"Unmatched Order",IF(AL730=1,"Matched to Order","Multiple Order Matches")))) -> Matched to Order | AQ730: =IF(COUNTIF($A$2:A730,A730)=1,1,0) -> 1
A731: pay_420000578 | C731: ORD26000599 | D731: 46270 | E731: CAPTURE | F731: UPI | G731: 7999 | H731: 24 | I731: 4.32 | J731: 7970.68 | K731: 46272 | L731: STL-20260907 | M731: =COUNTIF($A:$A,A731) -> 1 | N731: =COUNTIF(Orders!$A:$A,C731) -> 1 | P731: =COUNTIF(Orders!$H:$H,UPPER(SUBSTITUTE(TRIM(C731),"-",""))) -> 1 | R731: =IF(E731="REFUND","Refund",IF(P731=0,"Unmatched Order Reference","Matched Order Reference")) -> Matched Order Reference | S731: =COUNTIFS($C$2:$C$5753,C731,$E$2:$E$5753,"CAPTURE") -> 1 | V731: {=IF(E731<>"CAPTURE",0,SUMPRODUCT((MDR_Rates!$A$2:$A$10=F731)*(G731>MDR_Rates!$B$2:$B$10)*((MDR_Rates!$C$2:$C$10="")+(G731<=MDR_Rates!$C$2:$C$10))*MDR_Rates!$D$2:$D$10))} -> 0.3 | W731: =IF(E731<>"CAPTURE",0,ROUND(G731*V731/100,2)) -> 24 | X731: =IF(E731<>"CAPTURE",0,ROUND(W731*18/100,2)) -> 4.32 | Y731: =IF(E731<>"CAPTURE",0,ROUND(H731-W731,2)) -> 0 | Z731: =IF(E731<>"CAPTURE",0,ROUND(I731-X731,2)) -> 0 | AG731: =IF(E731<>"REFUND","",IF(COUNTIFS($A:$A,B731,$E:$E,"CAPTURE")=0,"Missing Original Capture","Original Capture Found")) | AI731: =IF(E731="REFUND",_xlfn.MAXIFS($G:$G,$A:$A,B731,$E:$E,"CAPTURE"),"") | AJ731: =IF(E731<>"REFUND","",IF(G731>AI731,"Refund Exceeds Capture",IF(ABS(G731-AI731)<0.01,"Full Refund","Partial Refund"))) | AK731: =UPPER(SUBSTITUTE(TRIM(C731),"-","")) -> ORD26000599 | AL731: =IF(E731<>"CAPTURE","",COUNTIF(Orders!$H:$H,AK731)) -> 1 | AP731: =IF(E731<>"CAPTURE","",IF(M731>1,"Duplicate ID - Review",IF(AL731=0,"Unmatched Order",IF(AL731=1,"Matched to Order","Multiple Order Matches")))) -> Matched to Order | AQ731: =IF(COUNTIF($A$2:A731,A731)=1,1,0) -> 1
... A900: pay_420005709 | C900: ORD26005977 | D900: 46270 | E900: CAPTURE | F900: UPI | G900: 2999 | H900: 9 | I900: 1.62 | J900: 2988.38 | K900: 46272 | L900: STL-20260907 | M900: =COUNTIF($A:$A,A900) -> 1 | N900: =COUNTIF(Orders!$A:$A,C900) -> 1 | P900: =COUNTIF(Orders!$H:$H,UPPER(SUBSTITUTE(TRIM(C900),"-",""))) -> 1 | R900: =IF(E900="REFUND","Refund",IF(P900=0,"Unmatched Order Reference","Matched Order Reference")) -> Matched Order Reference | S900: =COUNTIFS($C$2:$C$5753,C900,$E$2:$E$5753,"CAPTURE") -> 1 | V900: {=IF(E900<>"CAPTURE",0,SUMPRODUCT((MDR_Rates!$A$2:$A$10=F900)*(G900>MDR_Rates!$B$2:$B$10)*((MDR_Rates!$C$2:$C$10="")+(G900<=MDR_Rates!$C$2:$C$10))*MDR_Rates!$D$2:$D$10))} -> 0.3 | W900: =IF(E900<>"CAPTURE",0,ROUND(G900*V900/100,2)) -> 9 | X900: =IF(E900<>"CAPTURE",0,ROUND(W900*18/100,2)) -> 1.62 | Y900: =IF(E900<>"CAPTURE",0,ROUND(H900-W900,2)) -> 0 | Z900: =IF(E900<>"CAPTURE",0,ROUND(I900-X900,2)) -> 0 | AG900: =IF(E900<>"REFUND","",IF(COUNTIFS($A:$A,B900,$E:$E,"CAPTURE")=0,"Missing Original Capture","Original Capture Found")) | AI900: =IF(E900="REFUND",_xlfn.MAXIFS($G:$G,$A:$A,B900,$E:$E,"CAPTURE"),"") | AJ900: =IF(E900<>"REFUND","",IF(G900>AI900,"Refund Exceeds Capture",IF(ABS(G900-AI900)<0.01,"Full Refund","Partial Refund"))) | AK900: =UPPER(SUBSTITUTE(TRIM(C900),"-","")) -> ORD26005977 | AL900: =IF(E900<>"CAPTURE","",COUNTIF(Orders!$H:$H,AK900)) -> 1 | AP900: =IF(E900<>"CAPTURE","",IF(M900>1,"Duplicate ID - Review",IF(AL900=0,"Unmatched Order",IF(AL900=1,"Matched to Order","Multiple Order Matches")))) -> Matched to Order | AQ900: =IF(COUNTIF($A$2:A900,A900)=1,1,0) -> 1
A901: rfnd_GKEQ4YTEEKX2 | B901: pay_420000735 | D901: 46270 | E901: REFUND | F901: UPI | G901: 798 | H901: 0 | I901: 0 | J901: -798 | K901: 46272 | L901: STL-20260907 | M901: =COUNTIF($A:$A,A901) -> 1 | N901: =COUNTIF(Orders!$A:$A,C901) -> 0 | P901: =COUNTIF(Orders!$H:$H,UPPER(SUBSTITUTE(TRIM(C901),"-",""))) -> 1042575 | R901: =IF(E901="REFUND","Refund",IF(P901=0,"Unmatched Order Reference","Matched Order Reference")) -> Refund | S901: =COUNTIFS($C$2:$C$5753,C901,$E$2:$E$5753,"CAPTURE") -> 0 | V901: {=IF(E901<>"CAPTURE",0,SUMPRODUCT((MDR_Rates!$A$2:$A$10=F901)*(G901>MDR_Rates!$B$2:$B$10)*((MDR_Rates!$C$2:$C$10="")+(G901<=MDR_Rates!$C$2:$C$10))*MDR_Rates!$D$2:$D$10))} -> 0 | W901: =IF(E901<>"CAPTURE",0,ROUND(G901*V901/100,2)) -> 0 | X901: =IF(E901<>"CAPTURE",0,ROUND(W901*18/100,2)) -> 0 | Y901: =IF(E901<>"CAPTURE",0,ROUND(H901-W901,2)) -> 0 | Z901: =IF(E901<>"CAPTURE",0,ROUND(I901-X901,2)) -> 0 | AG901: =IF(E901<>"REFUND","",IF(COUNTIFS($A:$A,B901,$E:$E,"CAPTURE")=0,"Missing Original Capture","Original Capture Found")) -> Original Capture Found | AI901: =IF(E901="REFUND",_xlfn.MAXIFS($G:$G,$A:$A,B901,$E:$E,"CAPTURE"),"") -> 798 | AJ901: =IF(E901<>"REFUND","",IF(G901>AI901,"Refund Exceeds Capture",IF(ABS(G901-AI901)<0.01,"Full Refund","Partial Refund"))) -> Full Refund | AK901: =UPPER(SUBSTITUTE(TRIM(C901),"-","")) | AL901: =IF(E901<>"CAPTURE","",COUNTIF(Orders!$H:$H,AK901)) | AP901: =IF(E901<>"CAPTURE","",IF(M901>1,"Duplicate ID - Review",IF(AL901=0,"Unmatched Order",IF(AL901=1,"Matched to Order","Multiple Order Matches")))) | AQ901: =IF(COUNTIF($A$2:A901,A901)=1,1,0) -> 1
A902: rfnd_LNGG7VFY20ET | B902: pay_420004700 | D902: 46270 | E902: REFUND | F902: UPI | G902: 1299 | H902: 0 | I902: 0 | J902: -1299 | K902: 46272 | L902: STL-20260907 | M902: =COUNTIF($A:$A,A902) -> 1 | N902: =COUNTIF(Orders!$A:$A,C902) -> 0 | P902: =COUNTIF(Orders!$H:$H,UPPER(SUBSTITUTE(TRIM(C902),"-",""))) -> 1042575 | R902: =IF(E902="REFUND","Refund",IF(P902=0,"Unmatched Order Reference","Matched Order Reference")) -> Refund | S902: =COUNTIFS($C$2:$C$5753,C902,$E$2:$E$5753,"CAPTURE") -> 0 | V902: {=IF(E902<>"CAPTURE",0,SUMPRODUCT((MDR_Rates!$A$2:$A$10=F902)*(G902>MDR_Rates!$B$2:$B$10)*((MDR_Rates!$C$2:$C$10="")+(G902<=MDR_Rates!$C$2:$C$10))*MDR_Rates!$D$2:$D$10))} -> 0 | W902: =IF(E902<>"CAPTURE",0,ROUND(G902*V902/100,2)) -> 0 | X902: =IF(E902<>"CAPTURE",0,ROUND(W902*18/100,2)) -> 0 | Y902: =IF(E902<>"CAPTURE",0,ROUND(H902-W902,2)) -> 0 | Z902: =IF(E902<>"CAPTURE",0,ROUND(I902-X902,2)) -> 0 | AG902: =IF(E902<>"REFUND","",IF(COUNTIFS($A:$A,B902,$E:$E,"CAPTURE")=0,"Missing Original Capture","Original Capture Found")) -> Original Capture Found | AI902: =IF(E902="REFUND",_xlfn.MAXIFS($G:$G,$A:$A,B902,$E:$E,"CAPTURE"),"") -> 1299 | AJ902: =IF(E902<>"REFUND","",IF(G902>AI902,"Refund Exceeds Capture",IF(ABS(G902-AI902)<0.01,"Full Refund","Partial Refund"))) -> Full Refund | AK902: =UPPER(SUBSTITUTE(TRIM(C902),"-","")) | AL902: =IF(E902<>"CAPTURE","",COUNTIF(Orders!$H:$H,AK902)) | AP902: =IF(E902<>"CAPTURE","",IF(M902>1,"Duplicate ID - Review",IF(AL902=0,"Unmatched Order",IF(AL902=1,"Matched to Order","Multiple Order Matches")))) | AQ902: =IF(COUNTIF($A$2:A902,A902)=1,1,0) -> 1
A903: pay_420000021 | C903: ord26000020 | D903: 46271 | E903: CAPTURE | F903: UPI | G903: 3798 | H903: 11.39 | I903: 2.05 | J903: 3784.56 | K903: 46273 | L903: STL-20260908 | M903: =COUNTIF($A:$A,A903) -> 1 | N903: =COUNTIF(Orders!$A:$A,C903) -> 1 | P903: =COUNTIF(Orders!$H:$H,UPPER(SUBSTITUTE(TRIM(C903),"-",""))) -> 1 | R903: =IF(E903="REFUND","Refund",IF(P903=0,"Unmatched Order Reference","Matched Order Reference")) -> Matched Order Reference | S903: =COUNTIFS($C$2:$C$5753,C903,$E$2:$E$5753,"CAPTURE") -> 1 | V903: {=IF(E903<>"CAPTURE",0,SUMPRODUCT((MDR_Rates!$A$2:$A$10=F903)*(G903>MDR_Rates!$B$2:$B$10)*((MDR_Rates!$C$2:$C$10="")+(G903<=MDR_Rates!$C$2:$C$10))*MDR_Rates!$D$2:$D$10))} -> 0.3 | W903: =IF(E903<>"CAPTURE",0,ROUND(G903*V903/100,2)) -> 11.39 | X903: =IF(E903<>"CAPTURE",0,ROUND(W903*18/100,2)) -> 2.05 | Y903: =IF(E903<>"CAPTURE",0,ROUND(H903-W903,2)) -> 0 | Z903: =IF(E903<>"CAPTURE",0,ROUND(I903-X903,2)) -> 0 | AG903: =IF(E903<>"REFUND","",IF(COUNTIFS($A:$A,B903,$E:$E,"CAPTURE")=0,"Missing Original Capture","Original Capture Found")) | AI903: =IF(E903="REFUND",_xlfn.MAXIFS($G:$G,$A:$A,B903,$E:$E,"CAPTURE"),"") | AJ903: =IF(E903<>"REFUND","",IF(G903>AI903,"Refund Exceeds Capture",IF(ABS(G903-AI903)<0.01,"Full Refund","Partial Refund"))) | AK903: =UPPER(SUBSTITUTE(TRIM(C903),"-","")) -> ORD26000020 | AL903: =IF(E903<>"CAPTURE","",COUNTIF(Orders!$H:$H,AK903)) -> 1 | AP903: =IF(E903<>"CAPTURE","",IF(M903>1,"Duplicate ID - Review",IF(AL903=0,"Unmatched Order",IF(AL903=1,"Matched to Order","Multiple Order Matches")))) -> Matched to Order | AQ903: =IF(COUNTIF($A$2:A903,A903)=1,1,0) -> 1
A904: pay_420000038 | C904: ORD26000038 | D904: 46271 | E904: CAPTURE | F904: Card | G904: 1598 | H904: 28.76 | I904: 5.18 | J904: 1564.06 | K904: 46273 | L904: STL-20260908 | M904: =COUNTIF($A:$A,A904) -> 1 | N904: =COUNTIF(Orders!$A:$A,C904) -> 1 | P904: =COUNTIF(Orders!$H:$H,UPPER(SUBSTITUTE(TRIM(C904),"-",""))) -> 1 | R904: =IF(E904="REFUND","Refund",IF(P904=0,"Unmatched Order Reference","Matched Order Reference")) -> Matched Order Reference | S904: =COUNTIFS($C$2:$C$5753,C904,$E$2:$E$5753,"CAPTURE") -> 1 | V904: {=IF(E904<>"CAPTURE",0,SUMPRODUCT((MDR_Rates!$A$2:$A$10=F904)*(G904>MDR_Rates!$B$2:$B$10)*((MDR_Rates!$C$2:$C$10="")+(G904<=MDR_Rates!$C$2:$C$10))*MDR_Rates!$D$2:$D$10))} -> 1.8 | W904: =IF(E904<>"CAPTURE",0,ROUND(G904*V904/100,2)) -> 28.76 | X904: =IF(E904<>"CAPTURE",0,ROUND(W904*18/100,2)) -> 5.18 | Y904: =IF(E904<>"CAPTURE",0,ROUND(H904-W904,2)) -> 0 | Z904: =IF(E904<>"CAPTURE",0,ROUND(I904-X904,2)) -> 0 | AG904: =IF(E904<>"REFUND","",IF(COUNTIFS($A:$A,B904,$E:$E,"CAPTURE")=0,"Missing Original Capture","Original Capture Found")) | AI904: =IF(E904="REFUND",_xlfn.MAXIFS($G:$G,$A:$A,B904,$E:$E,"CAPTURE"),"") | AJ904: =IF(E904<>"REFUND","",IF(G904>AI904,"Refund Exceeds Capture",IF(ABS(G904-AI904)<0.01,"Full Refund","Partial Refund"))) | AK904: =UPPER(SUBSTITUTE(TRIM(C904),"-","")) -> ORD26000038 | AL904: =IF(E904<>"CAPTURE","",COUNTIF(Orders!$H:$H,AK904)) -> 1 | AP904: =IF(E904<>"CAPTURE","",IF(M904>1,"Duplicate ID - Review",IF(AL904=0,"Unmatched Order",IF(AL904=1,"Matched to Order","Multiple Order Matches")))) -> Matched to Order | AQ904: =IF(COUNTIF($A$2:A904,A904)=1,1,0) -> 1
A905: pay_420000079 | C905: ORD26000083 | D905: 46271 | E905: CAPTURE | F905: Card | G905: 1299 | H905: 23.38 | I905: 4.21 | J905: 1271.41 | K905: 46273 | L905: STL-20260908 | M905: =COUNTIF($A:$A,A905) -> 1 | N905: =COUNTIF(Orders!$A:$A,C905) -> 1 | P905: =COUNTIF(Orders!$H:$H,UPPER(SUBSTITUTE(TRIM(C905),"-",""))) -> 1 | R905: =IF(E905="REFUND","Refund",IF(P905=0,"Unmatched Order Reference","Matched Order Reference")) -> Matched Order Reference | S905: =COUNTIFS($C$2:$C$5753,C905,$E$2:$E$5753,"CAPTURE") -> 1 | V905: {=IF(E905<>"CAPTURE",0,SUMPRODUCT((MDR_Rates!$A$2:$A$10=F905)*(G905>MDR_Rates!$B$2:$B$10)*((MDR_Rates!$C$2:$C$10="")+(G905<=MDR_Rates!$C$2:$C$10))*MDR_Rates!$D$2:$D$10))} -> 1.8 | W905: =IF(E905<>"CAPTURE",0,ROUND(G905*V905/100,2)) -> 23.38 | X905: =IF(E905<>"CAPTURE",0,ROUND(W905*18/100,2)) -> 4.21 | Y905: =IF(E905<>"CAPTURE",0,ROUND(H905-W905,2)) -> 0 | Z905: =IF(E905<>"CAPTURE",0,ROUND(I905-X905,2)) -> 0 | AG905: =IF(E905<>"REFUND","",IF(COUNTIFS($A:$A,B905,$E:$E,"CAPTURE")=0,"Missing Original Capture","Original Capture Found")) | AI905: =IF(E905="REFUND",_xlfn.MAXIFS($G:$G,$A:$A,B905,$E:$E,"CAPTURE"),"") | AJ905: =IF(E905<>"REFUND","",IF(G905>AI905,"Refund Exceeds Capture",IF(ABS(G905-AI905)<0.01,"Full Refund","Partial Refund"))) | AK905: =UPPER(SUBSTITUTE(TRIM(C905),"-","")) -> ORD26000083 | AL905: =IF(E905<>"CAPTURE","",COUNTIF(Orders!$H:$H,AK905)) -> 1 | AP905: =IF(E905<>"CAPTURE","",IF(M905>1,"Duplicate ID - Review",IF(AL905=0,"Unmatched Order",IF(AL905=1,"Matched to Order","Multiple Order Matches")))) -> Matched to Order | AQ905: =IF(COUNTIF($A$2:A905,A905)=1,1,0) -> 1
A906: pay_420000090 | C906: ORD26000096 | D906: 46271 | E906: CAPTURE | F906: Card | G906: 5998 | H906: 95.97 | I906: 17.27 | J906: 5884.76 | K906: 46273 | L906: STL-20260908 | M906: =COUNTIF($A:$A,A906) -> 1 | N906: =COUNTIF(Orders!$A:$A,C906) -> 1 | P906: =COUNTIF(Orders!$H:$H,UPPER(SUBSTITUTE(TRIM(C906),"-",""))) -> 1 | R906: =IF(E906="REFUND","Refund",IF(P906=0,"Unmatched Order Reference","Matched Order Reference")) -> Matched Order Reference | S906: =COUNTIFS($C$2:$C$5753,C906,$E$2:$E$5753,"CAPTURE") -> 1 | V906: {=IF(E906<>"CAPTURE",0,SUMPRODUCT((MDR_Rates!$A$2:$A$10=F906)*(G906>MDR_Rates!$B$2:$B$10)*((MDR_Rates!$C$2:$C$10="")+(G906<=MDR_Rates!$C$2:$C$10))*MDR_Rates!$D$2:$D$10))} -> 1.6 | W906: =IF(E906<>"CAPTURE",0,ROUND(G906*V906/100,2)) -> 95.97 | X906: =IF(E906<>"CAPTURE",0,ROUND(W906*18/100,2)) -> 17.27 | Y906: =IF(E906<>"CAPTURE",0,ROUND(H906-W906,2)) -> 0 | Z906: =IF(E906<>"CAPTURE",0,ROUND(I906-X906,2)) -> 0 | AG906: =IF(E906<>"REFUND","",IF(COUNTIFS($A:$A,B906,$E:$E,"CAPTURE")=0,"Missing Original Capture","Original Capture Found")) | AI906: =IF(E906="REFUND",_xlfn.MAXIFS($G:$G,$A:$A,B906,$E:$E,"CAPTURE"),"") | AJ906: =IF(E906<>"REFUND","",IF(G906>AI906,"Refund Exceeds Capture",IF(ABS(G906-AI906)<0.01,"Full Refund","Partial Refund"))) | AK906: =UPPER(SUBSTITUTE(TRIM(C906),"-","")) -> ORD26000096 | AL906: =IF(E906<>"CAPTURE","",COUNTIF(Orders!$H:$H,AK906)) -> 1 | AP906: =IF(E906<>"CAPTURE","",IF(M906>1,"Duplicate ID - Review",IF(AL906=0,"Unmatched Order",IF(AL906=1,"Matched to Order","Multiple Order Matches")))) -> Matched to Order | AQ906: =IF(COUNTIF($A$2:A906,A906)=1,1,0) -> 1
A907: pay_420000146 | C907: ORD26000156 | D907: 46271 | E907: CAPTURE | F907: Card | G907: 2499 | H907: 39.98 | I907: 7.2 | J907: 2451.82 | K907: 46273 | L907: STL-20260908 | M907: =COUNTIF($A:$A,A907) -> 1 | N907: =COUNTIF(Orders!$A:$A,C907) -> 0 | P907: =COUNTIF(Orders!$H:$H,UPPER(SUBSTITUTE(TRIM(C907),"-",""))) -> 1 | R907: =IF(E907="REFUND","Refund",IF(P907=0,"Unmatched Order Reference","Matched Order Reference")) -> Matched Order Reference | S907: =COUNTIFS($C$2:$C$5753,C907,$E$2:$E$5753,"CAPTURE") -> 1 | V907: {=IF(E907<>"CAPTURE",0,SUMPRODUCT((MDR_Rates!$A$2:$A$10=F907)*(G907>MDR_Rates!$B$2:$B$10)*((MDR_Rates!$C$2:$C$10="")+(G907<=MDR_Rates!$C$2:$C$10))*MDR_Rates!$D$2:$D$10))} -> 1.6 | W907: =IF(E907<>"CAPTURE",0,ROUND(G907*V907/100,2)) -> 39.98 | X907: =IF(E907<>"CAPTURE",0,ROUND(W907*18/100,2)) -> 7.2 | Y907: =IF(E907<>"CAPTURE",0,ROUND(H907-W907,2)) -> 0 | Z907: =IF(E907<>"CAPTURE",0,ROUND(I907-X907,2)) -> 0 | AG907: =IF(E907<>"REFUND","",IF(COUNTIFS($A:$A,B907,$E:$E,"CAPTURE")=0,"Missing Original Capture","Original Capture Found")) | AI907: =IF(E907="REFUND",_xlfn.MAXIFS($G:$G,$A:$A,B907,$E:$E,"CAPTURE"),"") | AJ907: =IF(E907<>"REFUND","",IF(G907>AI907,"Refund Exceeds Capture",IF(ABS(G907-AI907)<0.01,"Full Refund","Partial Refund"))) | AK907: =UPPER(SUBSTITUTE(TRIM(C907),"-","")) -> ORD26000156 | AL907: =IF(E907<>"CAPTURE","",COUNTIF(Orders!$H:$H,AK907)) -> 1 | AP907: =IF(E907<>"CAPTURE","",IF(M907>1,"Duplicate ID - Review",IF(AL907=0,"Unmatched Order",IF(AL907=1,"Matched to Order","Multiple Order Matches")))) -> Matched to Order | AQ907: =IF(COUNTIF($A$2:A907,A907)=1,1,0) -> 1
A908: pay_420000180 | C908: ORD26000194 | D908: 46271 | E908: CAPTURE | F908: UPI | G908: 2197 | H908: 6.59 | I908: 1.19 | J908: 2189.22 | K908: 46273 | L908: STL-20260908 | M908: =COUNTIF($A:$A,A908) -> 1 | N908: =COUNTIF(Orders!$A:$A,C908) -> 1 | P908: =COUNTIF(Orders!$H:$H,UPPER(SUBSTITUTE(TRIM(C908),"-",""))) -> 1 | R908: =IF(E908="REFUND","Refund",IF(P908=0,"Unmatched Order Reference","Matched Order Reference")) -> Matched Order Reference | S908: =COUNTIFS($C$2:$C$5753,C908,$E$2:$E$5753,"CAPTURE") -> 1 | V908: {=IF(E908<>"CAPTURE",0,SUMPRODUCT((MDR_Rates!$A$2:$A$10=F908)*(G908>MDR_Rates!$B$2:$B$10)*((MDR_Rates!$C$2:$C$10="")+(G908<=MDR_Rates!$C$2:$C$10))*MDR_Rates!$D$2:$D$10))} -> 0.3 | W908: =IF(E908<>"CAPTURE",0,ROUND(G908*V908/100,2)) -> 6.59 | X908: =IF(E908<>"CAPTURE",0,ROUND(W908*18/100,2)) -> 1.19 | Y908: =IF(E908<>"CAPTURE",0,ROUND(H908-W908,2)) -> 0 | Z908: =IF(E908<>"CAPTURE",0,ROUND(I908-X908,2)) -> 0 | AG908: =IF(E908<>"REFUND","",IF(COUNTIFS($A:$A,B908,$E:$E,"CAPTURE")=0,"Missing Original Capture","Original Capture Found")) | AI908: =IF(E908="REFUND",_xlfn.MAXIFS($G:$G,$A:$A,B908,$E:$E,"CAPTURE"),"") | AJ908: =IF(E908<>"REFUND","",IF(G908>AI908,"Refund Exceeds Capture",IF(ABS(G908-AI908)<0.01,"Full Refund","Partial Refund"))) | AK908: =UPPER(SUBSTITUTE(TRIM(C908),"-","")) -> ORD26000194 | AL908: =IF(E908<>"CAPTURE","",COUNTIF(Orders!$H:$H,AK908)) -> 1 | AP908: =IF(E908<>"CAPTURE","",IF(M908>1,"Duplicate ID - Review",IF(AL908=0,"Unmatched Order",IF(AL908=1,"Matched to Order","Multiple Order Matches")))) -> Matched to Order | AQ908: =IF(COUNTIF($A$2:A908,A908)=1,1,0) -> 1
A909: pay_420000203 | C909: ORD26000218 | D909: 46271 | E909: CAPTURE | F909: Card | G909: 7997 | H909: 127.95 | I909: 23.03 | J909: 7846.02 | K909: 46273 | L909: STL-20260908 | M909: =COUNTIF($A:$A,A909) -> 1 | N909: =COUNTIF(Orders!$A:$A,C909) -> 1 | P909: =COUNTIF(Orders!$H:$H,UPPER(SUBSTITUTE(TRIM(C909),"-",""))) -> 1 | R909: =IF(E909="REFUND","Refund",IF(P909=0,"Unmatched Order Reference","Matched Order Reference")) -> Matched Order Reference | S909: =COUNTIFS($C$2:$C$5753,C909,$E$2:$E$5753,"CAPTURE") -> 1 | V909: {=IF(E909<>"CAPTURE",0,SUMPRODUCT((MDR_Rates!$A$2:$A$10=F909)*(G909>MDR_Rates!$B$2:$B$10)*((MDR_Rates!$C$2:$C$10="")+(G909<=MDR_Rates!$C$2:$C$10))*MDR_Rates!$D$2:$D$10))} -> 1.6 | W909: =IF(E909<>"CAPTURE",0,ROUND(G909*V909/100,2)) -> 127.95 | X909: =IF(E909<>"CAPTURE",0,ROUND(W909*18/100,2)) -> 23.03 | Y909: =IF(E909<>"CAPTURE",0,ROUND(H909-W909,2)) -> 0 | Z909: =IF(E909<>"CAPTURE",0,ROUND(I909-X909,2)) -> 0 | AG909: =IF(E909<>"REFUND","",IF(COUNTIFS($A:$A,B909,$E:$E,"CAPTURE")=0,"Missing Original Capture","Original Capture Found")) | AI909: =IF(E909="REFUND",_xlfn.MAXIFS($G:$G,$A:$A,B909,$E:$E,"CAPTURE"),"") | AJ909: =IF(E909<>"REFUND","",IF(G909>AI909,"Refund Exceeds Capture",IF(ABS(G909-AI909)<0.01,"Full Refund","Partial Refund"))) | AK909: =UPPER(SUBSTITUTE(TRIM(C909),"-","")) -> ORD26000218 | AL909: =IF(E909<>"CAPTURE","",COUNTIF(Orders!$H:$H,AK909)) -> 1 | AP909: =IF(E909<>"CAPTURE","",IF(M909>1,"Duplicate ID - Review",IF(AL909=0,"Unmatched Order",IF(AL909=1,"Matched to Order","Multiple Order Matches")))) -> Matched to Order | AQ909: =IF(COUNTIF($A$2:A909,A909)=1,1,0) -> 1
A910: pay_420000216 | C910: ord26000230 | D910: 46271 | E910: CAPTURE | F910: UPI | G910: 3848 | H910: 11.54 | I910: 2.08 | J910: 3834.38 | K910: 46273 | L910: STL-20260908 | M910: =COUNTIF($A:$A,A910) -> 1 | N910: =COUNTIF(Orders!$A:$A,C910) -> 1 | P910: =COUNTIF(Orders!$H:$H,UPPER(SUBSTITUTE(TRIM(C910),"-",""))) -> 1 | R910: =IF(E910="REFUND","Refund",IF(P910=0,"Unmatched Order Reference","Matched Order Reference")) -> Matched Order Reference | S910: =COUNTIFS($C$2:$C$5753,C910,$E$2:$E$5753,"CAPTURE") -> 1 | V910: {=IF(E910<>"CAPTURE",0,SUMPRODUCT((MDR_Rates!$A$2:$A$10=F910)*(G910>MDR_Rates!$B$2:$B$10)*((MDR_Rates!$C$2:$C$10="")+(G910<=MDR_Rates!$C$2:$C$10))*MDR_Rates!$D$2:$D$10))} -> 0.3 | W910: =IF(E910<>"CAPTURE",0,ROUND(G910*V910/100,2)) -> 11.54 | X910: =IF(E910<>"CAPTURE",0,ROUND(W910*18/100,2)) -> 2.08 | Y910: =IF(E910<>"CAPTURE",0,ROUND(H910-W910,2)) -> 0 | Z910: =IF(E910<>"CAPTURE",0,ROUND(I910-X910,2)) -> 0 | AG910: =IF(E910<>"REFUND","",IF(COUNTIFS($A:$A,B910,$E:$E,"CAPTURE")=0,"Missing Original Capture","Original Capture Found")) | AI910: =IF(E910="REFUND",_xlfn.MAXIFS($G:$G,$A:$A,B910,$E:$E,"CAPTURE"),"") | AJ910: =IF(E910<>"REFUND","",IF(G910>AI910,"Refund Exceeds Capture",IF(ABS(G910-AI910)<0.01,"Full Refund","Partial Refund"))) | AK910: =UPPER(SUBSTITUTE(TRIM(C910),"-","")) -> ORD26000230 | AL910: =IF(E910<>"CAPTURE","",COUNTIF(Orders!$H:$H,AK910)) -> 1 | AP910: =IF(E910<>"CAPTURE","",IF(M910>1,"Duplicate ID - Review",IF(AL910=0,"Unmatched Order",IF(AL910=1,"Matched to Order","Multiple Order Matches")))) -> Matched to Order | AQ910: =IF(COUNTIF($A$2:A910,A910)=1,1,0) -> 1
A911: pay_420000263 | C911: ord26000280 | D911: 46271 | E911: CAPTURE | F911: NetBanking | G911: 1299 | H911: 19.49 | I911: 3.51 | J911: 1276 | K911: 46273 | L911: STL-20260908 | M911: =COUNTIF($A:$A,A911) -> 1 | N911: =COUNTIF(Orders!$A:$A,C911) -> 1 | P911: =COUNTIF(Orders!$H:$H,UPPER(SUBSTITUTE(TRIM(C911),"-",""))) -> 1 | R911: =IF(E911="REFUND","Refund",IF(P911=0,"Unmatched Order Reference","Matched Order Reference")) -> Matched Order Reference | S911: =COUNTIFS($C$2:$C$5753,C911,$E$2:$E$5753,"CAPTURE") -> 1 | V911: {=IF(E911<>"CAPTURE",0,SUMPRODUCT((MDR_Rates!$A$2:$A$10=F911)*(G911>MDR_Rates!$B$2:$B$10)*((MDR_Rates!$C$2:$C$10="")+(G911<=MDR_Rates!$C$2:$C$10))*MDR_Rates!$D$2:$D$10))} -> 1.5 | W911: =IF(E911<>"CAPTURE",0,ROUND(G911*V911/100,2)) -> 19.49 | X911: =IF(E911<>"CAPTURE",0,ROUND(W911*18/100,2)) -> 3.51 | Y911: =IF(E911<>"CAPTURE",0,ROUND(H911-W911,2)) -> 0 | Z911: =IF(E911<>"CAPTURE",0,ROUND(I911-X911,2)) -> 0 | AG911: =IF(E911<>"REFUND","",IF(COUNTIFS($A:$A,B911,$E:$E,"CAPTURE")=0,"Missing Original Capture","Original Capture Found")) | AI911: =IF(E911="REFUND",_xlfn.MAXIFS($G:$G,$A:$A,B911,$E:$E,"CAPTURE"),"") | AJ911: =IF(E911<>"REFUND","",IF(G911>AI911,"Refund Exceeds Capture",IF(ABS(G911-AI911)<0.01,"Full Refund","Partial Refund"))) | AK911: =UPPER(SUBSTITUTE(TRIM(C911),"-","")) -> ORD26000280 | AL911: =IF(E911<>"CAPTURE","",COUNTIF(Orders!$H:$H,AK911)) -> 1 | AP911: =IF(E911<>"CAPTURE","",IF(M911>1,"Duplicate ID - Review",IF(AL911=0,"Unmatched Order",IF(AL911=1,"Matched to Order","Multiple Order Matches")))) -> Matched to Order | AQ911: =IF(COUNTIF($A$2:A911,A911)=1,1,0) -> 1
A912: pay_420000264 | C912: ORD26000281 | D912: 46271 | E912: CAPTURE | F912: Wallet | G912: 499 | H912: 9.48 | I912: 1.71 | J912: 487.81 | K912: 46273 | L912: STL-20260908 | M912: =COUNTIF($A:$A,A912) -> 1 | N912: =COUNTIF(Orders!$A:$A,C912) -> 1 | P912: =COUNTIF(Orders!$H:$H,UPPER(SUBSTITUTE(TRIM(C912),"-",""))) -> 1 | R912: =IF(E912="REFUND","Refund",IF(P912=0,"Unmatched Order Reference","Matched Order Reference")) -> Matched Order Reference | S912: =COUNTIFS($C$2:$C$5753,C912,$E$2:$E$5753,"CAPTURE") -> 1 | V912: {=IF(E912<>"CAPTURE",0,SUMPRODUCT((MDR_Rates!$A$2:$A$10=F912)*(G912>MDR_Rates!$B$2:$B$10)*((MDR_Rates!$C$2:$C$10="")+(G912<=MDR_Rates!$C$2:$C$10))*MDR_Rates!$D$2:$D$10))} -> 1.9 | W912: =IF(E912<>"CAPTURE",0,ROUND(G912*V912/100,2)) -> 9.48 | X912: =IF(E912<>"CAPTURE",0,ROUND(W912*18/100,2)) -> 1.71 | Y912: =IF(E912<>"CAPTURE",0,ROUND(H912-W912,2)) -> 0 | Z912: =IF(E912<>"CAPTURE",0,ROUND(I912-X912,2)) -> 0 | AG912: =IF(E912<>"REFUND","",IF(COUNTIFS($A:$A,B912,$E:$E,"CAPTURE")=0,"Missing Original Capture","Original Capture Found")) | AI912: =IF(E912="REFUND",_xlfn.MAXIFS($G:$G,$A:$A,B912,$E:$E,"CAPTURE"),"") | AJ912: =IF(E912<>"REFUND","",IF(G912>AI912,"Refund Exceeds Capture",IF(ABS(G912-AI912)<0.01,"Full Refund","Partial Refund"))) | AK912: =UPPER(SUBSTITUTE(TRIM(C912),"-","")) -> ORD26000281 | AL912: =IF(E912<>"CAPTURE","",COUNTIF(Orders!$H:$H,AK912)) -> 1 | AP912: =IF(E912<>"CAPTURE","",IF(M912>1,"Duplicate ID - Review",IF(AL912=0,"Unmatched Order",IF(AL912=1,"Matched to Order","Multiple Order Matches")))) -> Matched to Order | AQ912: =IF(COUNTIF($A$2:A912,A912)=1,1,0) -> 1
A913: pay_420000365 | C913: ORD26000384 | D913: 46271 | E913: CAPTURE | F913: Card | G913: 9647 | H913: 154.35 | I913: 27.78 | J913: 9464.87 | K913: 46273 | L913: STL-20260908 | M913: =COUNTIF($A:$A,A913) -> 1 | N913: =COUNTIF(Orders!$A:$A,C913) -> 1 | P913: =COUNTIF(Orders!$H:$H,UPPER(SUBSTITUTE(TRIM(C913),"-",""))) -> 1 | R913: =IF(E913="REFUND","Refund",IF(P913=0,"Unmatched Order Reference","Matched Order Reference")) -> Matched Order Reference | S913: =COUNTIFS($C$2:$C$5753,C913,$E$2:$E$5753,"CAPTURE") -> 1 | V913: {=IF(E913<>"CAPTURE",0,SUMPRODUCT((MDR_Rates!$A$2:$A$10=F913)*(G913>MDR_Rates!$B$2:$B$10)*((MDR_Rates!$C$2:$C$10="")+(G913<=MDR_Rates!$C$2:$C$10))*MDR_Rates!$D$2:$D$10))} -> 1.6 | W913: =IF(E913<>"CAPTURE",0,ROUND(G913*V913/100,2)) -> 154.35 | X913: =IF(E913<>"CAPTURE",0,ROUND(W913*18/100,2)) -> 27.78 | Y913: =IF(E913<>"CAPTURE",0,ROUND(H913-W913,2)) -> 0 | Z913: =IF(E913<>"CAPTURE",0,ROUND(I913-X913,2)) -> 0 | AG913: =IF(E913<>"REFUND","",IF(COUNTIFS($A:$A,B913,$E:$E,"CAPTURE")=0,"Missing Original Capture","Original Capture Found")) | AI913: =IF(E913="REFUND",_xlfn.MAXIFS($G:$G,$A:$A,B913,$E:$E,"CAPTURE"),"") | AJ913: =IF(E913<>"REFUND","",IF(G913>AI913,"Refund Exceeds Capture",IF(ABS(G913-AI913)<0.01,"Full Refund","Partial Refund"))) | AK913: =UPPER(SUBSTITUTE(TRIM(C913),"-","")) -> ORD26000384 | AL913: =IF(E913<>"CAPTURE","",COUNTIF(Orders!$H:$H,AK913)) -> 1 | AP913: =IF(E913<>"CAPTURE","",IF(M913>1,"Duplicate ID - Review",IF(AL913=0,"Unmatched Order",IF(AL913=1,"Matched to Order","Multiple Order Matches")))) -> Matched to Order | AQ913: =IF(COUNTIF($A$2:A913,A913)=1,1,0) -> 1
A914: pay_420000382 | C914: ORD26000400 | D914: 46271 | E914: CAPTURE | F914: Card | G914: 999 | H914: 17.98 | I914: 3.24 | J914: 977.78 | K914: 46273 | L914: STL-20260908 | M914: =COUNTIF($A:$A,A914) -> 1 | N914: =COUNTIF(Orders!$A:$A,C914) -> 1 | P914: =COUNTIF(Orders!$H:$H,UPPER(SUBSTITUTE(TRIM(C914),"-",""))) -> 1 | R914: =IF(E914="REFUND","Refund",IF(P914=0,"Unmatched Order Reference","Matched Order Reference")) -> Matched Order Reference | S914: =COUNTIFS($C$2:$C$5753,C914,$E$2:$E$5753,"CAPTURE") -> 1 | V914: {=IF(E914<>"CAPTURE",0,SUMPRODUCT((MDR_Rates!$A$2:$A$10=F914)*(G914>MDR_Rates!$B$2:$B$10)*((MDR_Rates!$C$2:$C$10="")+(G914<=MDR_Rates!$C$2:$C$10))*MDR_Rates!$D$2:$D$10))} -> 1.8 | W914: =IF(E914<>"CAPTURE",0,ROUND(G914*V914/100,2)) -> 17.98 | X914: =IF(E914<>"CAPTURE",0,ROUND(W914*18/100,2)) -> 3.24 | Y914: =IF(E914<>"CAPTURE",0,ROUND(H914-W914,2)) -> 0 | Z914: =IF(E914<>"CAPTURE",0,ROUND(I914-X914,2)) -> 0 | AG914: =IF(E914<>"REFUND","",IF(COUNTIFS($A:$A,B914,$E:$E,"CAPTURE")=0,"Missing Original Capture","Original Capture Found")) | AI914: =IF(E914="REFUND",_xlfn.MAXIFS($G:$G,$A:$A,B914,$E:$E,"CAPTURE"),"") | AJ914: =IF(E914<>"REFUND","",IF(G914>AI914,"Refund Exceeds Capture",IF(ABS(G914-AI914)<0.01,"Full Refund","Partial Refund"))) | AK914: =UPPER(SUBSTITUTE(TRIM(C914),"-","")) -> ORD26000400 | AL914: =IF(E914<>"CAPTURE","",COUNTIF(Orders!$H:$H,AK914)) -> 1 | AP914: =IF(E914<>"CAPTURE","",IF(M914>1,"Duplicate ID - Review",IF(AL914=0,"Unmatched Order",IF(AL914=1,"Matched to Order","Multiple Order Matches")))) -> Matched to Order | AQ914: =IF(COUNTIF($A$2:A914,A914)=1,1,0) -> 1
... A1091: pay_420005739 | C1091: ORD26006504 | D1091: 46271 | E1091: CAPTURE | F1091: NetBanking | G1091: 999 | H1091: 14.99 | I1091: 2.7 | J1091: 981.31 | K1091: 46273 | L1091: STL-20260908 | M1091: =COUNTIF($A:$A,A1091) -> 1 | N1091: =COUNTIF(Orders!$A:$A,C1091) -> 0 | P1091: =COUNTIF(Orders!$H:$H,UPPER(SUBSTITUTE(TRIM(C1091),"-",""))) -> 0 | R1091: =IF(E1091="REFUND","Refund",IF(P1091=0,"Unmatched Order Reference","Matched Order Reference")) -> Unmatched Order Reference | S1091: =COUNTIFS($C$2:$C$5753,C1091,$E$2:$E$5753,"CAPTURE") -> 1 | V1091: {=IF(E1091<>"CAPTURE",0,SUMPRODUCT((MDR_Rates!$A$2:$A$10=F1091)*(G1091>MDR_Rates!$B$2:$B$10)*((MDR_Rates!$C$2:$C$10="")+(G1091<=MDR_Rates!$C$2:$C$10))*MDR_Rates!$D$2:$D$10))} -> 1.5 | W1091: =IF(E1091<>"CAPTURE",0,ROUND(G1091*V1091/100,2)) -> 14.99 | X1091: =IF(E1091<>"CAPTURE",0,ROUND(W1091*18/100,2)) -> 2.7 | Y1091: =IF(E1091<>"CAPTURE",0,ROUND(H1091-W1091,2)) -> 0 | Z1091: =IF(E1091<>"CAPTURE",0,ROUND(I1091-X1091,2)) -> 0 | AG1091: =IF(E1091<>"REFUND","",IF(COUNTIFS($A:$A,B1091,$E:$E,"CAPTURE")=0,"Missing Original Capture","Original Capture Found")) | AI1091: =IF(E1091="REFUND",_xlfn.MAXIFS($G:$G,$A:$A,B1091,$E:$E,"CAPTURE"),"") | AJ1091: =IF(E1091<>"REFUND","",IF(G1091>AI1091,"Refund Exceeds Capture",IF(ABS(G1091-AI1091)<0.01,"Full Refund","Partial Refund"))) | AK1091: =UPPER(SUBSTITUTE(TRIM(C1091),"-","")) -> ORD26006504 | AL1091: =IF(E1091<>"CAPTURE","",COUNTIF(Orders!$H:$H,AK1091)) -> 0 | AP1091: =IF(E1091<>"CAPTURE","",IF(M1091>1,"Duplicate ID - Review",IF(AL1091=0,"Unmatched Order",IF(AL1091=1,"Matched to Order","Multiple Order Matches")))) -> Unmatched Order | AQ1091: =IF(COUNTIF($A$2:A1091,A1091)=1,1,0) -> 1
A1092: rfnd_7D82HBZNK9EM | B1092: pay_420000284 | D1092: 46271 | E1092: REFUND | F1092: Card | G1092: 5998 | H1092: 0 | I1092: 0 | J1092: -5998 | K1092: 46273 | L1092: STL-20260908 | M1092: =COUNTIF($A:$A,A1092) -> 1 | N1092: =COUNTIF(Orders!$A:$A,C1092) -> 0 | P1092: =COUNTIF(Orders!$H:$H,UPPER(SUBSTITUTE(TRIM(C1092),"-",""))) -> 1042575 | R1092: =IF(E1092="REFUND","Refund",IF(P1092=0,"Unmatched Order Reference","Matched Order Reference")) -> Refund | S1092: =COUNTIFS($C$2:$C$5753,C1092,$E$2:$E$5753,"CAPTURE") -> 0 | V1092: {=IF(E1092<>"CAPTURE",0,SUMPRODUCT((MDR_Rates!$A$2:$A$10=F1092)*(G1092>MDR_Rates!$B$2:$B$10)*((MDR_Rates!$C$2:$C$10="")+(G1092<=MDR_Rates!$C$2:$C$10))*MDR_Rates!$D$2:$D$10))} -> 0 | W1092: =IF(E1092<>"CAPTURE",0,ROUND(G1092*V1092/100,2)) -> 0 | X1092: =IF(E1092<>"CAPTURE",0,ROUND(W1092*18/100,2)) -> 0 | Y1092: =IF(E1092<>"CAPTURE",0,ROUND(H1092-W1092,2)) -> 0 | Z1092: =IF(E1092<>"CAPTURE",0,ROUND(I1092-X1092,2)) -> 0 | AG1092: =IF(E1092<>"REFUND","",IF(COUNTIFS($A:$A,B1092,$E:$E,"CAPTURE")=0,"Missing Original Capture","Original Capture Found")) -> Original Capture Found | AI1092: =IF(E1092="REFUND",_xlfn.MAXIFS($G:$G,$A:$A,B1092,$E:$E,"CAPTURE"),"") -> 5998 | AJ1092: =IF(E1092<>"REFUND","",IF(G1092>AI1092,"Refund Exceeds Capture",IF(ABS(G1092-AI1092)<0.01,"Full Refund","Partial Refund"))) -> Full Refund | AK1092: =UPPER(SUBSTITUTE(TRIM(C1092),"-","")) | AL1092: =IF(E1092<>"CAPTURE","",COUNTIF(Orders!$H:$H,AK1092)) | AP1092: =IF(E1092<>"CAPTURE","",IF(M1092>1,"Duplicate ID - Review",IF(AL1092=0,"Unmatched Order",IF(AL1092=1,"Matched to Order","Multiple Order Matches")))) | AQ1092: =IF(COUNTIF($A$2:A1092,A1092)=1,1,0) -> 1
A1093: rfnd_HS8RMLB6WJAB | B1093: pay_420002345 | D1093: 46271 | E1093: REFUND | F1093: UPI | G1093: 3499 | H1093: 0 | I1093: 0 | J1093: -3499 | K1093: 46273 | L1093: STL-20260908 | M1093: =COUNTIF($A:$A,A1093) -> 1 | N1093: =COUNTIF(Orders!$A:$A,C1093) -> 0 | P1093: =COUNTIF(Orders!$H:$H,UPPER(SUBSTITUTE(TRIM(C1093),"-",""))) -> 1042575 | R1093: =IF(E1093="REFUND","Refund",IF(P1093=0,"Unmatched Order Reference","Matched Order Reference")) -> Refund | S1093: =COUNTIFS($C$2:$C$5753,C1093,$E$2:$E$5753,"CAPTURE") -> 0 | V1093: {=IF(E1093<>"CAPTURE",0,SUMPRODUCT((MDR_Rates!$A$2:$A$10=F1093)*(G1093>MDR_Rates!$B$2:$B$10)*((MDR_Rates!$C$2:$C$10="")+(G1093<=MDR_Rates!$C$2:$C$10))*MDR_Rates!$D$2:$D$10))} -> 0 | W1093: =IF(E1093<>"CAPTURE",0,ROUND(G1093*V1093/100,2)) -> 0 | X1093: =IF(E1093<>"CAPTURE",0,ROUND(W1093*18/100,2)) -> 0 | Y1093: =IF(E1093<>"CAPTURE",0,ROUND(H1093-W1093,2)) -> 0 | Z1093: =IF(E1093<>"CAPTURE",0,ROUND(I1093-X1093,2)) -> 0 | AG1093: =IF(E1093<>"REFUND","",IF(COUNTIFS($A:$A,B1093,$E:$E,"CAPTURE")=0,"Missing Original Capture","Original Capture Found")) -> Original Capture Found | AI1093: =IF(E1093="REFUND",_xlfn.MAXIFS($G:$G,$A:$A,B1093,$E:$E,"CAPTURE"),"") -> 3499 | AJ1093: =IF(E1093<>"REFUND","",IF(G1093>AI1093,"Refund Exceeds Capture",IF(ABS(G1093-AI1093)<0.01,"Full Refund","Partial Refund"))) -> Full Refund | AK1093: =UPPER(SUBSTITUTE(TRIM(C1093),"-","")) | AL1093: =IF(E1093<>"CAPTURE","",COUNTIF(Orders!$H:$H,AK1093)) | AP1093: =IF(E1093<>"CAPTURE","",IF(M1093>1,"Duplicate ID - Review",IF(AL1093=0,"Unmatched Order",IF(AL1093=1,"Matched to Order","Multiple Order Matches")))) | AQ1093: =IF(COUNTIF($A$2:A1093,A1093)=1,1,0) -> 1
A1094: rfnd_QUZMW0YB4Y1L | B1094: pay_420003659 | D1094: 46271 | E1094: REFUND | F1094: Card | G1094: 999 | H1094: 0 | I1094: 0 | J1094: -999 | K1094: 46273 | L1094: STL-20260908 | M1094: =COUNTIF($A:$A,A1094) -> 1 | N1094: =COUNTIF(Orders!$A:$A,C1094) -> 0 | P1094: =COUNTIF(Orders!$H:$H,UPPER(SUBSTITUTE(TRIM(C1094),"-",""))) -> 1042575 | R1094: =IF(E1094="REFUND","Refund",IF(P1094=0,"Unmatched Order Reference","Matched Order Reference")) -> Refund | S1094: =COUNTIFS($C$2:$C$5753,C1094,$E$2:$E$5753,"CAPTURE") -> 0 | V1094: {=IF(E1094<>"CAPTURE",0,SUMPRODUCT((MDR_Rates!$A$2:$A$10=F1094)*(G1094>MDR_Rates!$B$2:$B$10)*((MDR_Rates!$C$2:$C$10="")+(G1094<=MDR_Rates!$C$2:$C$10))*MDR_Rates!$D$2:$D$10))} -> 0 | W1094: =IF(E1094<>"CAPTURE",0,ROUND(G1094*V1094/100,2)) -> 0 | X1094: =IF(E1094<>"CAPTURE",0,ROUND(W1094*18/100,2)) -> 0 | Y1094: =IF(E1094<>"CAPTURE",0,ROUND(H1094-W1094,2)) -> 0 | Z1094: =IF(E1094<>"CAPTURE",0,ROUND(I1094-X1094,2)) -> 0 | AG1094: =IF(E1094<>"REFUND","",IF(COUNTIFS($A:$A,B1094,$E:$E,"CAPTURE")=0,"Missing Original Capture","Original Capture Found")) -> Original Capture Found | AI1094: =IF(E1094="REFUND",_xlfn.MAXIFS($G:$G,$A:$A,B1094,$E:$E,"CAPTURE"),"") -> 999 | AJ1094: =IF(E1094<>"REFUND","",IF(G1094>AI1094,"Refund Exceeds Capture",IF(ABS(G1094-AI1094)<0.01,"Full Refund","Partial Refund"))) -> Full Refund | AK1094: =UPPER(SUBSTITUTE(TRIM(C1094),"-","")) | AL1094: =IF(E1094<>"CAPTURE","",COUNTIF(Orders!$H:$H,AK1094)) | AP1094: =IF(E1094<>"CAPTURE","",IF(M1094>1,"Duplicate ID - Review",IF(AL1094=0,"Unmatched Order",IF(AL1094=1,"Matched to Order","Multiple Order Matches")))) | AQ1094: =IF(COUNTIF($A$2:A1094,A1094)=1,1,0) -> 1
A1095: pay_420000099 | C1095: ORD26000106 | D1095: 46272 | E1095: CAPTURE | F1095: UPI | G1095: 1598 | H1095: 0 | I1095: 0 | J1095: 1598 | K1095: 46274 | L1095: STL-20260909 | M1095: =COUNTIF($A:$A,A1095) -> 1 | N1095: =COUNTIF(Orders!$A:$A,C1095) -> 1 | P1095: =COUNTIF(Orders!$H:$H,UPPER(SUBSTITUTE(TRIM(C1095),"-",""))) -> 1 | R1095: =IF(E1095="REFUND","Refund",IF(P1095=0,"Unmatched Order Reference","Matched Order Reference")) -> Matched Order Reference | S1095: =COUNTIFS($C$2:$C$5753,C1095,$E$2:$E$5753,"CAPTURE") -> 1 | V1095: {=IF(E1095<>"CAPTURE",0,SUMPRODUCT((MDR_Rates!$A$2:$A$10=F1095)*(G1095>MDR_Rates!$B$2:$B$10)*((MDR_Rates!$C$2:$C$10="")+(G1095<=MDR_Rates!$C$2:$C$10))*MDR_Rates!$D$2:$D$10))} -> 0 | W1095: =IF(E1095<>"CAPTURE",0,ROUND(G1095*V1095/100,2)) -> 0 | X1095: =IF(E1095<>"CAPTURE",0,ROUND(W1095*18/100,2)) -> 0 | Y1095: =IF(E1095<>"CAPTURE",0,ROUND(H1095-W1095,2)) -> 0 | Z1095: =IF(E1095<>"CAPTURE",0,ROUND(I1095-X1095,2)) -> 0 | AG1095: =IF(E1095<>"REFUND","",IF(COUNTIFS($A:$A,B1095,$E:$E,"CAPTURE")=0,"Missing Original Capture","Original Capture Found")) | AI1095: =IF(E1095="REFUND",_xlfn.MAXIFS($G:$G,$A:$A,B1095,$E:$E,"CAPTURE"),"") | AJ1095: =IF(E1095<>"REFUND","",IF(G1095>AI1095,"Refund Exceeds Capture",IF(ABS(G1095-AI1095)<0.01,"Full Refund","Partial Refund"))) | AK1095: =UPPER(SUBSTITUTE(TRIM(C1095),"-","")) -> ORD26000106 | AL1095: =IF(E1095<>"CAPTURE","",COUNTIF(Orders!$H:$H,AK1095)) -> 1 | AP1095: =IF(E1095<>"CAPTURE","",IF(M1095>1,"Duplicate ID - Review",IF(AL1095=0,"Unmatched Order",IF(AL1095=1,"Matched to Order","Multiple Order Matches")))) -> Matched to Order | AQ1095: =IF(COUNTIF($A$2:A1095,A1095)=1,1,0) -> 1
A1096: pay_420000156 | C1096: ORD26000166 | D1096: 46272 | E1096: CAPTURE | F1096: NetBanking | G1096: 499 | H1096: 7.49 | I1096: 1.35 | J1096: 490.16 | K1096: 46274 | L1096: STL-20260909 | M1096: =COUNTIF($A:$A,A1096) -> 2 | N1096: =COUNTIF(Orders!$A:$A,C1096) -> 1 | P1096: =COUNTIF(Orders!$H:$H,UPPER(SUBSTITUTE(TRIM(C1096),"-",""))) -> 1 | R1096: =IF(E1096="REFUND","Refund",IF(P1096=0,"Unmatched Order Reference","Matched Order Reference")) -> Matched Order Reference | S1096: =COUNTIFS($C$2:$C$5753,C1096,$E$2:$E$5753,"CAPTURE") -> 2 | V1096: {=IF(E1096<>"CAPTURE",0,SUMPRODUCT((MDR_Rates!$A$2:$A$10=F1096)*(G1096>MDR_Rates!$B$2:$B$10)*((MDR_Rates!$C$2:$C$10="")+(G1096<=MDR_Rates!$C$2:$C$10))*MDR_Rates!$D$2:$D$10))} -> 1.5 | W1096: =IF(E1096<>"CAPTURE",0,ROUND(G1096*V1096/100,2)) -> 7.49 | X1096: =IF(E1096<>"CAPTURE",0,ROUND(W1096*18/100,2)) -> 1.35 | Y1096: =IF(E1096<>"CAPTURE",0,ROUND(H1096-W1096,2)) -> 0 | Z1096: =IF(E1096<>"CAPTURE",0,ROUND(I1096-X1096,2)) -> 0 | AG1096: =IF(E1096<>"REFUND","",IF(COUNTIFS($A:$A,B1096,$E:$E,"CAPTURE")=0,"Missing Original Capture","Original Capture Found")) | AI1096: =IF(E1096="REFUND",_xlfn.MAXIFS($G:$G,$A:$A,B1096,$E:$E,"CAPTURE"),"") | AJ1096: =IF(E1096<>"REFUND","",IF(G1096>AI1096,"Refund Exceeds Capture",IF(ABS(G1096-AI1096)<0.01,"Full Refund","Partial Refund"))) | AK1096: =UPPER(SUBSTITUTE(TRIM(C1096),"-","")) -> ORD26000166 | AL1096: =IF(E1096<>"CAPTURE","",COUNTIF(Orders!$H:$H,AK1096)) -> 1 | AP1096: =IF(E1096<>"CAPTURE","",IF(M1096>1,"Duplicate ID - Review",IF(AL1096=0,"Unmatched Order",IF(AL1096=1,"Matched to Order","Multiple Order Matches")))) -> Duplicate ID - Review | AQ1096: =IF(COUNTIF($A$2:A1096,A1096)=1,1,0) -> 1
